Workbook

Sheet IRR inputs & outputs
A1: Model inputs | D1: Reference values | E1: AC single port 22kW | F1: AC dual port 22kW | G1: DC dual port 40kW
A2: Charger rated capacity (kW) | B2: 22 | E2: 22 | F2: 22 | G2: 40
A3: Number of ports | B3: 1 | E3: 1 | F3: 2 | G3: 2
A4: Capex | B4: 5000 | E4: 5000 | F4: 30000 | G4: 50000
A5: Capex subsidy | B5: 1 | G5: 0
A6: Post subsidy Capex | B6: =B4*(1-B5) -> 0 | E6: =E4*(1-E5) -> 5000 | F6: =F4*(1-F5) -> 30000 | G6: =G4*(1-G5) -> 50000
A7: Charger average power (% of rated capacity) | B7: 0.51 | E7: 0.51 | F7: 0.51 | G7: 0.62
A8: Charger efficiency (%) | B8: 0.95 | E8: 0.95 | F8: 0.95 | G8: 0.95
A9: Per unit electricity costs ($/kWh) | B9: 0.2 | E9: 0.2 | F9: 0.2 | G9: 0.2
A10: Fixed electricity costs ($ p.a.) | G10: 0
A11: Per unit software costs (% of revenue) | B11: 0.075 | E11: 0.075 | F11: 0.075 | G11: 0.075
A12: Fixed software costs ($ p.a.) | B12: 300 | E12: 300 | F12: 600 | G12: 600
A13: Sale price ($/kWh) | B13: 0.45 | E13: 0.45 | F13: 0.45 | G13: 0.55
A14: Maintenance ($ p.a.) | B14: 500 | E14: 500 | F14: 500 | G14: 750
A15: Replacement capex ($ in year 5) | B15: 3000 | E15: 3000 | F15: 3000 | G15: 35000
A16: Establishment fee to council (one off) | B16: 500 | E16: 500 | F16: 500 | G16: 1000
A17: Parking license fee to council or Ausgrid ($ p.a.) | B17: 750 | E17: 750 | F17: 800 | G17: 5000
A18: DNSP regulated return rate (WACC) | B18: 0.0585
A19: Commercial hurdle rate | B19: 0.12
A22: Model outputs
A23: Utilisation | B23: 0.05 | C23: 0.075 | D23: 0.1 | E23: 0.125 | F23: 0.15 | G23: 0.175 | H23: 0.2 | I23: 0.225 | J23: 0.25 | K23: 0.3 | L23: 0.35 | M23: 0.4 | N23: 0.45 | O23: 0.5
A24: IRR | B24: ='5% utilisation'!B23 -> #N/A | C24: ='7.5% utilisation'!B23 -> #N/A | D24: ='10% utilisation'!B23 -> 0.58195842 | E24: ='12.5% utilisation'!B23 -> 1.8993305 | F24: ='15% utilisation'!B23 -> 2.9475492 | G24: ='17.5% utilisation'!B23 -> 3.9691409 | H24: ='20% utilisation'!B23 -> 4.9841048 | I24: ='22.5% utilisation'!B23 -> 5.9968565 | J24: ='25% utilisation'!B23 -> 7.0087261 | K24: ='30% utilisation'!B23 -> 9.0314695 | L24: ='35% utilisation'!B23 -> 11.053743 | M24: ='40% utilisation'!B23 -> 13.075862 | N24: ='45% utilisation'!B23 -> 15.097921 | O24: ='50% utilisation'!B23 -> 17.119952
A25: Net income p.a. | B25: ='5% utilisation'!C21 -> -538.99976 | C25: ='7.5% utilisation'!C21 -> -33.499633 | D25: ='10% utilisation'!C21 -> 472.00049 | E25: ='12.5% utilisation'!C21 -> 977.50061 | F25: ='15% utilisation'!C21 -> 1483.0007 | G25: ='17.5% utilisation'!C21 -> 1988.5009 | H25: ='20% utilisation'!C21 -> 2494.001 | I25: ='22.5% utilisation'!C21 -> 2999.5011 | J25: ='25% utilisation'!C21 -> 3505.0012 | K25: ='30% utilisation'!C21 -> 4516.0015 | L25: ='35% utilisation'!C21 -> 5527.0017 | M25: ='40% utilisation'!C21 -> 6538.002 | N25: ='45% utilisation'!C21 -> 7549.0022 | O25: ='50% utilisation'!C21 -> 8560.0024
A26: NSP regulated return | B26: =$B$18 -> 0.0585 | C26: =$B$18 -> 0.0585 | D26: =$B$18 -> 0.0585 | E26: =$B$18 -> 0.0585 | F26: =$B$18 -> 0.0585 | G26: =$B$18 -> 0.0585 | H26: =$B$18 -> 0.0585 | I26: =$B$18 -> 0.0585 | ... O26: =$B$18 -> 0.0585
A27: Commercial hurdle rate | B27: =$B$19 -> 0.12 | C27: =$B$19 -> 0.12 | D27: =$B$19 -> 0.12 | E27: =$B$19 -> 0.12 | F27: =$B$19 -> 0.12 | G27: =$B$19 -> 0.12 | H27: =$B$19 -> 0.12 | I27: =$B$19 -> 0.12 | ... O27: =$B$19 -> 0.12
A29: Subsidy % DNSP | B29: ='5% utilisation'!$B$125 -> #N/A | C29: ='7.5% utilisation'!$B$125 -> #N/A | D29: ='10% utilisation'!$B$125 -> #N/A | E29: ='12.5% utilisation'!$B$125 -> #N/A | F29: ='15% utilisation'!$B$125 -> #N/A | G29: ='17.5% utilisation'!$B$125 -> #N/A | H29: ='20% utilisation'!$B$125 -> #N/A | I29: ='22.5% utilisation'!$B$125 -> #N/A | J29: ='25% utilisation'!$B$125 -> #N/A | K29: ='30% utilisation'!$B$125 -> #N/A | L29: ='35% utilisation'!$B$125 -> #N/A | M29: ='40% utilisation'!$B$125 -> #N/A | N29: ='45% utilisation'!$B$125 -> #N/A | O29: ='50% utilisation'!$B$125 -> #N/A
A30: Subsidy % CPO | B30: ='5% utilisation'!$B$126 -> #N/A | C30: ='7.5% utilisation'!$B$126 -> #N/A | D30: ='10% utilisation'!$B$126 -> #N/A | E30: ='12.5% utilisation'!$B$126 -> #N/A | F30: ='15% utilisation'!$B$126 -> #N/A | G30: ='17.5% utilisation'!$B$126 -> #N/A | H30: ='20% utilisation'!$B$126 -> #N/A | I30: ='22.5% utilisation'!$B$126 -> #N/A | J30: ='25% utilisation'!$B$126 -> #N/A | K30: ='30% utilisation'!$B$126 -> #N/A | L30: ='35% utilisation'!$B$126 -> #N/A | M30: ='40% utilisation'!$B$126 -> #N/A | N30: ='45% utilisation'!$B$126 -> #N/A | O30: ='50% utilisation'!$B$126 -> #N/A
A31: Retailer costs | B31: =SUM('5% utilisation'!$C$16:$G$18) -> 7502.3088 | C31: =SUM('7.5% utilisation'!$C$16:$G$18) -> 10503.463 | D31: =SUM('10% utilisation'!$C$16:$G$18) -> 13504.618 | E31: =SUM('12.5% utilisation'!$C$16:$G$18) -> 16505.772 | F31: =SUM('15% utilisation'!$C$16:$G$18) -> 19506.926 | G31: =SUM('17.5% utilisation'!$C$16:$G$18) -> 22508.081 | H31: =SUM('20% utilisation'!$C$16:$G$18) -> 25509.235
A32: DNSP opex | B32: =SUM('5% utilisation'!$C$14:$G$15) -> 6250 | C32: =SUM('7.5% utilisation'!$C$14:$G$15) -> 6250 | D32: =SUM('10% utilisation'!$C$14:$G$15) -> 6250 | E32: =SUM('12.5% utilisation'!$C$14:$G$15) -> 6250 | F32: =SUM('15% utilisation'!$C$14:$G$15) -> 6250 | G32: =SUM('17.5% utilisation'!$C$14:$G$15) -> 6250 | H32: =SUM('20% utilisation'!$C$14:$G$15) -> 6250
A33: Revenue | B33: =SUM('5% utilisation'!$C$9:$G$9) -> 11057.31 | C33: =SUM('5% utilisation'!$C$9:$G$9) -> 11057.31 | D33: =SUM('10% utilisation'!$C$9:$G$9) -> 22114.62 | E33: =SUM('12.5% utilisation'!$C$9:$G$9) -> 27643.275 | F33: =SUM('5% utilisation'!$C$9:$G$9) -> 11057.31 | G33: =SUM('17.5% utilisation'!$C$9:$G$9) -> 38700.585 | H33: =SUM('20% utilisation'!$C$9:$G$9) -> 44229.24

Sheet Bar chart
A1: AC 22kW dual port - 10% utilisation
A2: Subsidy % | B2: 0.3
A3: Taxpayer subsidy | B3: =1*B4*B2 -> 1155
A4: Capex | B4: =('IRR inputs & outputs'!B4+'IRR inputs & outputs'!B16)*(1-B2) -> 3850
A5: DNSP opex | B5: =1*('IRR inputs & outputs'!D32) -> 6250
A6: Retailer opex | B6: =1*('IRR inputs & outputs'!D31) -> 13504.618
A7: Revenue to retailer | C7: =B6*1.1 -> 14855.079
A8: DNSP revenue potential or benefit to EV drivers | C8: =C10-C7 -> 7259.5407
A10: Revenue (current pricing) | C10: ='IRR inputs & outputs'!D33 -> 22114.62

Sheet 5% utilisation
A1: Utilisation | B1: 0.05
A2: Hours in year | B2: =24*365 -> 8760
A3: Energy delivered | B3: =B2*B1*'IRR inputs & outputs'!B2*'IRR inputs & outputs'!B3*'IRR inputs & outputs'!$B$7 -> 4914.36 | C3: kWh p.a.
A5: Year | B5: 0 | C5: 1 | D5: 2 | E5: 3 | F5: 4 | G5: 5 | H5: 6 | I5: 7 | J5: 8 | K5: 9 | L5: 10
A6: Income
A7: Charging | C7: =$B$3*'IRR inputs & outputs'!$B$13 -> 2211.462 | D7: =$B$3*'IRR inputs & outputs'!$B$13 -> 2211.462 | E7: =$B$3*'IRR inputs & outputs'!$B$13 -> 2211.462 | F7: =$B$3*'IRR inputs & outputs'!$B$13 -> 2211.462 | G7: =$B$3*'IRR inputs & outputs'!$B$13 -> 2211.462 | H7: =$B$3*'IRR inputs & outputs'!$B$13 -> 2211.462 | I7: =$B$3*'IRR inputs & outputs'!$B$13 -> 2211.462 | J7: =$B$3*'IRR inputs & outputs'!$B$13 -> 2211.462 | ... L7: =$B$3*'IRR inputs & outputs'!$B$13 -> 2211.462
A9: Total income | C9: =SUM(C7:C8) -> 2211.462 | D9: =SUM(D7:D8) -> 2211.462 | E9: =SUM(E7:E8) -> 2211.462 | F9: =SUM(F7:F8) -> 2211.462 | G9: =SUM(G7:G8) -> 2211.462 | H9: =SUM(H7:H8) -> 2211.462 | I9: =SUM(I7:I8) -> 2211.462 | J9: =SUM(J7:J8) -> 2211.462 | ... L9: =SUM(L7:L8) -> 2211.462
A11: Outgoing
A12: Capex | B12: ='IRR inputs & outputs'!B6 -> 0 | G12: ='IRR inputs & outputs'!B15 -> 3000
A13: Site establishment | B13: ='IRR inputs & outputs'!B16 -> 500
A14: Site license | C14: ='IRR inputs & outputs'!$B$17 -> 750 | D14: ='IRR inputs & outputs'!$B$17 -> 750 | E14: ='IRR inputs & outputs'!$B$17 -> 750 | F14: ='IRR inputs & outputs'!$B$17 -> 750 | G14: ='IRR inputs & outputs'!$B$17 -> 750 | H14: ='IRR inputs & outputs'!$B$17 -> 750 | I14: ='IRR inputs & outputs'!$B$17 -> 750 | J14: ='IRR inputs & outputs'!$B$17 -> 750 | ... L14: ='IRR inputs & outputs'!$B$17 -> 750
A15: Maintenance | C15: ='IRR inputs & outputs'!B14 -> 500 | D15: ='IRR inputs & outputs'!B14 -> 500 | E15: ='IRR inputs & outputs'!B14 -> 500 | F15: ='IRR inputs & outputs'!B14 -> 500 | G15: ='IRR inputs & outputs'!B14 -> 500 | H15: ='IRR inputs & outputs'!B14 -> 500 | I15: ='IRR inputs & outputs'!B14 -> 500 | J15: ='IRR inputs & outputs'!B14 -> 500 | K15: ='IRR inputs & outputs'!B14 -> 500 | L15: ='IRR inputs & outputs'!B14 -> 500
A16: Electricity | C16: =(1/'IRR inputs & outputs'!$B$8)*$B$3*'IRR inputs & outputs'!$B$9+'IRR inputs & outputs'!$B$10 -> 1034.6021 | D16: =(1/'IRR inputs & outputs'!$B$8)*$B$3*'IRR inputs & outputs'!$B$9+'IRR inputs & outputs'!$B$10 -> 1034.6021 | E16: =(1/'IRR inputs & outputs'!$B$8)*$B$3*'IRR inputs & outputs'!$B$9+'IRR inputs & outputs'!$B$10 -> 1034.6021 | F16: =(1/'IRR inputs & outputs'!$B$8)*$B$3*'IRR inputs & outputs'!$B$9+'IRR inputs & outputs'!$B$10 -> 1034.6021 | G16: =(1/'IRR inputs & outputs'!$B$8)*$B$3*'IRR inputs & outputs'!$B$9+'IRR inputs & outputs'!$B$10 -> 1034.6021 | H16: =(1/'IRR inputs & outputs'!$B$8)*$B$3*'IRR inputs & outputs'!$B$9+'IRR inputs & outputs'!$B$10 -> 1034.6021 | I16: =(1/'IRR inputs & outputs'!$B$8)*$B$3*'IRR inputs & outputs'!$B$9+'IRR inputs & outputs'!$B$10 -> 1034.6021 | J16: =(1/'IRR inputs & outputs'!$B$8)*$B$3*'IRR inputs & outputs'!$B$9+'IRR inputs & outputs'!$B$10 -> 1034.6021 | ... L16: =(1/'IRR inputs & outputs'!$B$8)*$B$3*'IRR inputs & outputs'!$B$9+'IRR inputs & outputs'!$B$10 -> 1034.6021
A17: Software - fixed | C17: ='IRR inputs & outputs'!$B$12 -> 300 | D17: ='IRR inputs & outputs'!$B$12 -> 300 | E17: ='IRR inputs & outputs'!$B$12 -> 300 | F17: ='IRR inputs & outputs'!$B$12 -> 300 | G17: ='IRR inputs & outputs'!$B$12 -> 300 | H17: ='IRR inputs & outputs'!$B$12 -> 300 | I17: ='IRR inputs & outputs'!$B$12 -> 300 | J17: ='IRR inputs & outputs'!$B$12 -> 300 | ... L17: ='IRR inputs & outputs'!$B$12 -> 300
A18: Software - variable | C18: =$B$3*'IRR inputs & outputs'!$B$11*'IRR inputs & outputs'!$B$13 -> 165.85965 | D18: =$B$3*'IRR inputs & outputs'!$B$11*'IRR inputs & outputs'!$B$13 -> 165.85965 | E18: =$B$3*'IRR inputs & outputs'!$B$11*'IRR inputs & outputs'!$B$13 -> 165.85965 | F18: =$B$3*'IRR inputs & outputs'!$B$11*'IRR inputs & outputs'!$B$13 -> 165.85965 | G18: =$B$3*'IRR inputs & outputs'!$B$11*'IRR inputs & outputs'!$B$13 -> 165.85965 | H18: =$B$3*'IRR inputs & outputs'!$B$11*'IRR inputs & outputs'!$B$13 -> 165.85965 | I18: =$B$3*'IRR inputs & outputs'!$B$11*'IRR inputs & outputs'!$B$13 -> 165.85965 | J18: =$B$3*'IRR inputs & outputs'!$B$11*'IRR inputs & outputs'!$B$13 -> 165.85965 | ... L18: =$B$3*'IRR inputs & outputs'!$B$11*'IRR inputs & outputs'!$B$13 -> 165.85965
A19: Total outgoings | B19: =SUM(B12:B18) -> 500 | C19: =SUM(C12:C18) -> 2750.4618 | D19: =SUM(D12:D18) -> 2750.4618 | E19: =SUM(E12:E18) -> 2750.4618 | F19: =SUM(F12:F18) -> 2750.4618 | G19: =SUM(G12:G18) -> 5750.4618 | H19: =SUM(H12:H18) -> 2750.4618 | I19: =SUM(I12:I18) -> 2750.4618 | ... L19: =SUM(L12:L18) -> 2750.4618
A21: Total | B21: =B9-B19 -> -500 | C21: =C9-C19 -> -538.99976 | D21: =D9-D19 -> -538.99976 | E21: =E9-E19 -> -538.99976 | F21: =F9-F19 -> -538.99976 | G21: =G9-G19 -> -3538.9998 | H21: =H9-H19 -> -538.99976 | I21: =I9-I19 -> -538.99976 | ... L21: =L9-L19 -> -538.99976
A23: IRR | B23: =IFERROR(IRR(B21:L21),NA()) -> #N/A
A25: Subsidy effect
A26: Subsidy | B26: 0.1
A27: Subsidised capex | B27: =$B$12*(1-B26) -> 0
A28: Cashflow | B28: =-B27 -> 0 | C28: =$C$21 -> -538.99976 | D28: =$D$21 -> -538.99976 | E28: =$E$21 -> -538.99976 | F28: =$F$21 -> -538.99976 | G28: =$G$21 -> -3538.9998 | H28: =$H$21 -> -538.99976 | I28: =$I$21 -> -538.99976 | J28: =$J$21 -> -538.99976 | K28: =$K$21 -> -538.99976 | L28: =$L$21 -> -538.99976
A29: IRR | B29: =IFERROR(IRR(B28:L28),NA()) -> #N/A
A31: Subsidy | B31: 0.15
A32: Subsidised capex | B32: =$B$12*(1-B31) -> 0
A33: Cashflow | B33: =-B32 -> 0 | C33: =$C$21 -> -538.99976 | D33: =$D$21 -> -538.99976 | E33: =$E$21 -> -538.99976 | F33: =$F$21 -> -538.99976 | G33: =$G$21 -> -3538.9998 | H33: =$H$21 -> -538.99976 | I33: =$I$21 -> -538.99976 | J33: =$J$21 -> -538.99976 | K33: =$K$21 -> -538.99976 | L33: =$L$21 -> -538.99976
A34: IRR | B34: =IFERROR(IRR(B33:L33),NA()) -> #N/A
A36: Subsidy | B36: 0.2
A37: Subsidised capex | B37: =$B$12*(1-B36) -> 0
A38: Cashflow | B38: =-B37 -> 0 | C38: =$C$21 -> -538.99976 | D38: =$D$21 -> -538.99976 | E38: =$E$21 -> -538.99976 | F38: =$F$21 -> -538.99976 | G38: =$G$21 -> -3538.9998 | H38: =$H$21 -> -538.99976 | I38: =$I$21 -> -538.99976 | J38: =$J$21 -> -538.99976 | K38: =$K$21 -> -538.99976 | L38: =$L$21 -> -538.99976
A39: IRR | B39: =IFERROR(IRR(B38:L38),NA()) -> #N/A
A41: Subsidy | B41: 0.25
A42: Subsidised capex | B42: =$B$12*(1-B41) -> 0
A43: Cashflow | B43: =-B42 -> 0 | C43: =$C$21 -> -538.99976 | D43: =$D$21 -> -538.99976 | E43: =$E$21 -> -538.99976 | F43: =$F$21 -> -538.99976 | G43: =$G$21 -> -3538.9998 | H43: =$H$21 -> -538.99976 | I43: =$I$21 -> -538.99976 | J43: =$J$21 -> -538.99976 | K43: =$K$21 -> -538.99976 | L43: =$L$21 -> -538.99976
A44: IRR | B44: =IFERROR(IRR(B43:L43),NA()) -> #N/A
A46: Subsidy | B46: 0.3
A47: Subsidised capex | B47: =$B$12*(1-B46) -> 0
A48: Cashflow | B48: =-B47 -> 0 | C48: =$C$21 -> -538.99976 | D48: =$D$21 -> -538.99976 | E48: =$E$21 -> -538.99976 | F48: =$F$21 -> -538.99976 | G48: =$G$21 -> -3538.9998 | H48: =$H$21 -> -538.99976 | I48: =$I$21 -> -538.99976 | J48: =$J$21 -> -538.99976 | K48: =$K$21 -> -538.99976 | L48: =$L$21 -> -538.99976
A49: IRR | B49: =IFERROR(IRR(B48:L48),NA()) -> #N/A
A51: Subsidy | B51: 0.35
A52: Subsidised capex | B52: =$B$12*(1-B51) -> 0
A53: Cashflow | B53: =-B52 -> 0 | C53: =$C$21 -> -538.99976 | D53: =$D$21 -> -538.99976 | E53: =$E$21 -> -538.99976 | F53: =$F$21 -> -538.99976 | G53: =$G$21 -> -3538.9998 | H53: =$H$21 -> -538.99976 | I53: =$I$21 -> -538.99976 | J53: =$J$21 -> -538.99976 | K53: =$K$21 -> -538.99976 | L53: =$L$21 -> -538.99976
A54: IRR | B54: =IFERROR(IRR(B53:L53),NA()) -> #N/A
A56: Subsidy | B56: 0.4
A57: Subsidised capex | B57: =$B$12*(1-B56) -> 0
A58: Cashflow | B58: =-B57 -> 0 | C58: =$C$21 -> -538.99976 | D58: =$D$21 -> -538.99976 | E58: =$E$21 -> -538.99976 | F58: =$F$21 -> -538.99976 | G58: =$G$21 -> -3538.9998 | H58: =$H$21 -> -538.99976 | I58: =$I$21 -> -538.99976 | J58: =$J$21 -> -538.99976 | K58: =$K$21 -> -538.99976 | L58: =$L$21 -> -538.99976
A59: IRR | B59: =IFERROR(IRR(B58:L58),NA()) -> #N/A
A61: Subsidy | B61: 0.45
A62: Subsidised capex | B62: =$B$12*(1-B61) -> 0
A63: Cashflow | B63: =-B62 -> 0 | C63: =$C$21 -> -538.99976 | D63: =$D$21 -> -538.99976 | E63: =$E$21 -> -538.99976 | F63: =$F$21 -> -538.99976 | G63: =$G$21 -> -3538.9998 | H63: =$H$21 -> -538.99976 | I63: =$I$21 -> -538.99976 | J63: =$J$21 -> -538.99976 | K63: =$K$21 -> -538.99976 | L63: =$L$21 -> -538.99976
A64: IRR | B64: =IFERROR(IRR(B63:L63),NA()) -> #N/A
A66: Subsidy | B66: 0.5
A67: Subsidised capex | B67: =$B$12*(1-B66) -> 0
A68: Cashflow | B68: =-B67 -> 0 | C68: =$C$21 -> -538.99976 | D68: =$D$21 -> -538.99976 | E68: =$E$21 -> -538.99976 | F68: =$F$21 -> -538.99976 | G68: =$G$21 -> -3538.9998 | H68: =$H$21 -> -538.99976 | I68: =$I$21 -> -538.99976 | J68: =$J$21 -> -538.99976 | K68: =$K$21 -> -538.99976 | L68: =$L$21 -> -538.99976
A69: IRR | B69: =IFERROR(IRR(B68:L68),NA()) -> #N/A
A71: Subsidy | B71: 0.55
A72: Subsidised capex | B72: =$B$12*(1-B71) -> 0
A73: Cashflow | B73: =-B72 -> 0 | C73: =$C$21 -> -538.99976 | D73: =$D$21 -> -538.99976 | E73: =$E$21 -> -538.99976 | F73: =$F$21 -> -538.99976 | G73: =$G$21 -> -3538.9998 | H73: =$H$21 -> -538.99976 | I73: =$I$21 -> -538.99976 | J73: =$J$21 -> -538.99976 | K73: =$K$21 -> -538.99976 | L73: =$L$21 -> -538.99976
A74: IRR | B74: =IFERROR(IRR(B73:L73),NA()) -> #N/A
A76: Subsidy | B76: 0.6
A77: Subsidised capex | B77: =$B$12*(1-B76) -> 0
A78: Cashflow | B78: =-B77 -> 0 | C78: =$C$21 -> -538.99976 | D78: =$D$21 -> -538.99976 | E78: =$E$21 -> -538.99976 | F78: =$F$21 -> -538.99976 | G78: =$G$21 -> -3538.9998 | H78: =$H$21 -> -538.99976 | I78: =$I$21 -> -538.99976 | J78: =$J$21 -> -538.99976 | K78: =$K$21 -> -538.99976 | L78: =$L$21 -> -538.99976
A79: IRR | B79: =IFERROR(IRR(B78:L78),NA()) -> #N/A
A81: Subsidy | B81: 0.65
A82: Subsidised capex | B82: =$B$12*(1-B81) -> 0
A83: Cashflow | B83: =-B82 -> 0 | C83: =$C$21 -> -538.99976 | D83: =$D$21 -> -538.99976 | E83: =$E$21 -> -538.99976 | F83: =$F$21 -> -538.99976 | G83: =$G$21 -> -3538.9998 | H83: =$H$21 -> -538.99976 | I83: =$I$21 -> -538.99976 | J83: =$J$21 -> -538.99976 | K83: =$K$21 -> -538.99976 | L83: =$L$21 -> -538.99976
A84: IRR | B84: =IFERROR(IRR(B83:L83),NA()) -> #N/A
A86: Subsidy | B86: 0.7
A87: Subsidised capex | B87: =$B$12*(1-B86) -> 0
A88: Cashflow | B88: =-B87 -> 0 | C88: =$C$21 -> -538.99976 | D88: =$D$21 -> -538.99976 | E88: =$E$21 -> -538.99976 | F88: =$F$21 -> -538.99976 | G88: =$G$21 -> -3538.9998 | H88: =$H$21 -> -538.99976 | I88: =$I$21 -> -538.99976 | J88: =$J$21 -> -538.99976 | K88: =$K$21 -> -538.99976 | L88: =$L$21 -> -538.99976
A89: IRR | B89: =IFERROR(IRR(B88:L88),NA()) -> #N/A
A91: Subsidy | B91: 0.75
A92: Subsidised capex | B92: =$B$12*(1-B91) -> 0
A93: Cashflow | B93: =-B92 -> 0 | C93: =$C$21 -> -538.99976 | D93: =$D$21 -> -538.99976 | E93: =$E$21 -> -538.99976 | F93: =$F$21 -> -538.99976 | G93: =$G$21 -> -3538.9998 | H93: =$H$21 -> -538.99976 | I93: =$I$21 -> -538.99976 | J93: =$J$21 -> -538.99976 | K93: =$K$21 -> -538.99976 | L93: =$L$21 -> -538.99976
A94: IRR | B94: =IFERROR(IRR(B93:L93),NA()) -> #N/A
A96: Subsidy | B96: 0.8
A97: Subsidised capex | B97: =$B$12*(1-B96) -> 0
A98: Cashflow | B98: =-B97 -> 0 | C98: =$C$21 -> -538.99976 | D98: =$D$21 -> -538.99976 | E98: =$E$21 -> -538.99976 | F98: =$F$21 -> -538.99976 | G98: =$G$21 -> -3538.9998 | H98: =$H$21 -> -538.99976 | I98: =$I$21 -> -538.99976 | J98: =$J$21 -> -538.99976 | K98: =$K$21 -> -538.99976 | L98: =$L$21 -> -538.99976
A99: IRR | B99: =IFERROR(IRR(B98:L98),NA()) -> #N/A
A101: Subsidy | B101: 0.85
A102: Subsidised capex | B102: =$B$12*(1-B101) -> 0
A103: Cashflow | B103: =-B102 -> 0 | C103: =$C$21 -> -538.99976 | D103: =$D$21 -> -538.99976 | E103: =$E$21 -> -538.99976 | F103: =$F$21 -> -538.99976 | G103: =$G$21 -> -3538.9998 | H103: =$H$21 -> -538.99976 | I103: =$I$21 -> -538.99976 | J103: =$J$21 -> -538.99976 | K103: =$K$21 -> -538.99976 | L103: =$L$21 -> -538.99976
A104: IRR | B104: =IFERROR(IRR(B103:L103),NA()) -> #N/A
A106: Subsidy | B106: 0.9
A107: Subsidised capex | B107: =$B$12*(1-B106) -> 0
A108: Cashflow | B108: =-B107 -> 0 | C108: =$C$21 -> -538.99976 | D108: =$D$21 -> -538.99976 | E108: =$E$21 -> -538.99976 | F108: =$F$21 -> -538.99976 | G108: =$G$21 -> -3538.9998 | H108: =$H$21 -> -538.99976 | I108: =$I$21 -> -538.99976 | J108: =$J$21 -> -538.99976 | K108: =$K$21 -> -538.99976 | L108: =$L$21 -> -538.99976
A109: IRR | B109: =IFERROR(IRR(B108:L108),NA()) -> #N/A
A111: Subsidy | B111: 0.95
A112: Subsidised capex | B112: =$B$12*(1-B111) -> 0
A113: Cashflow | B113: =-B112 -> 0 | C113: =$C$21 -> -538.99976 | D113: =$D$21 -> -538.99976 | E113: =$E$21 -> -538.99976 | F113: =$F$21 -> -538.99976 | G113: =$G$21 -> -3538.9998 | H113: =$H$21 -> -538.99976 | I113: =$I$21 -> -538.99976 | J113: =$J$21 -> -538.99976 | K113: =$K$21 -> -538.99976 | L113: =$L$21 -> -538.99976
A114: IRR | B114: =IFERROR(IRR(B113:L113),NA()) -> #N/A
A116: Subsidy | B116: 1
A117: Subsidised capex | B117: =$B$12*(1-B116) -> 0
A118: Cashflow | B118: =-B117 -> 0 | C118: =$C$21 -> -538.99976 | D118: =$D$21 -> -538.99976 | E118: =$E$21 -> -538.99976 | F118: =$F$21 -> -538.99976 | G118: =$G$21 -> -3538.9998 | H118: =$H$21 -> -538.99976 | I118: =$I$21 -> -538.99976 | J118: =$J$21 -> -538.99976 | K118: =$K$21 -> -538.99976 | L118: =$L$21 -> -538.99976
A119: IRR | B119: =IFERROR(IRR(B118:L118),NA()) -> #N/A
A122: Subsidy summary
B123: 0.1 | C123: 0.15 | D123: 0.2 | E123: 0.25 | F123: 0.3 | G123: 0.35 | H123: 0.4 | I123: 0.45 | J123: 0.5 | K123: 0.55 | L123: 0.6 | M123: 0.65 | N123: 0.7 | O123: 0.75 | P123: 0.8 | Q123: 0.85 | R123: 0.9 | S123: 0.95 | T123: 1
B124: =B29 -> #N/A | C124: =B34 -> #N/A | D124: =B39 -> #N/A | E124: =B44 -> #N/A | F124: =B49 -> #N/A | G124: =B54 -> #N/A | H124: =B59 -> #N/A | I124: =B64 -> #N/A | J124: =B69 -> #N/A | K124: =B74 -> #N/A | L124: =B79 -> #N/A | M124: =B84 -> #N/A | N124: =B89 -> #N/A | O124: =B94 -> #N/A | P124: =B99 -> #N/A | Q124: =B104 -> #N/A | R124: =B109 -> #N/A | S124: =B114 -> #N/A | T124: =B119 -> #N/A
A125: Min subsidy for DNSP | B125: =LOOKUP('IRR inputs & outputs'!B18, B124:P124, B123:P123) -> #N/A
A126: Min subsidy for CPO | B126: =LOOKUP('IRR inputs & outputs'!B19, B124:P124, B123:P123) -> #N/A

Sheet 7.5% utilisation
A1: Utilisation | B1: 0.075
A2: Hours in year | B2: =24*365 -> 8760
A3: Energy delivered | B3: =B2*B1*'IRR inputs & outputs'!B2*'IRR inputs & outputs'!B3*'IRR inputs & outputs'!$B$7 -> 7371.54 | C3: kWh p.a.
A5: Year | B5: 0 | C5: 1 | D5: 2 | E5: 3 | F5: 4 | G5: 5 | H5: 6 | I5: 7 | J5: 8 | K5: 9 | L5: 10
A6: Income
A7: Charging | C7: =$B$3*'IRR inputs & outputs'!$B$13 -> 3317.193 | D7: =$B$3*'IRR inputs & outputs'!$B$13 -> 3317.193 | E7: =$B$3*'IRR inputs & outputs'!$B$13 -> 3317.193 | F7: =$B$3*'IRR inputs & outputs'!$B$13 -> 3317.193 | G7: =$B$3*'IRR inputs & outputs'!$B$13 -> 3317.193 | H7: =$B$3*'IRR inputs & outputs'!$B$13 -> 3317.193 | I7: =$B$3*'IRR inputs & outputs'!$B$13 -> 3317.193 | J7: =$B$3*'IRR inputs & outputs'!$B$13 -> 3317.193 | ... L7: =$B$3*'IRR inputs & outputs'!$B$13 -> 3317.193
A9: Total income | C9: =SUM(C7:C8) -> 3317.193 | D9: =SUM(D7:D8) -> 3317.193 | E9: =SUM(E7:E8) -> 3317.193 | F9: =SUM(F7:F8) -> 3317.193 | G9: =SUM(G7:G8) -> 3317.193 | H9: =SUM(H7:H8) -> 3317.193 | I9: =SUM(I7:I8) -> 3317.193 | J9: =SUM(J7:J8) -> 3317.193 | ... L9: =SUM(L7:L8) -> 3317.193
A11: Outgoing
A12: Capex | B12: ='IRR inputs & outputs'!B6 -> 0 | G12: ='IRR inputs & outputs'!B15 -> 3000
A13: Site establishment | B13: ='IRR inputs & outputs'!B16 -> 500
A14: Site license | C14: ='IRR inputs & outputs'!$B$17 -> 750 | D14: ='IRR inputs & outputs'!$B$17 -> 750 | E14: ='IRR inputs & outputs'!$B$17 -> 750 | F14: ='IRR inputs & outputs'!$B$17 -> 750 | G14: ='IRR inputs & outputs'!$B$17 -> 750 | H14: ='IRR inputs & outputs'!$B$17 -> 750 | I14: ='IRR inputs & outputs'!$B$17 -> 750 | J14: ='IRR inputs & outputs'!$B$17 -> 750 | ... L14: ='IRR inputs & outputs'!$B$17 -> 750
A15: Maintenance | C15: ='IRR inputs & outputs'!B14 -> 500 | D15: ='IRR inputs & outputs'!B14 -> 500 | E15: ='IRR inputs & outputs'!B14 -> 500 | F15: ='IRR inputs & outputs'!B14 -> 500 | G15: ='IRR inputs & outputs'!B14 -> 500 | H15: ='IRR inputs & outputs'!B14 -> 500 | I15: ='IRR inputs & outputs'!B14 -> 500 | J15: ='IRR inputs & outputs'!B14 -> 500 | K15: ='IRR inputs & outputs'!B14 -> 500 | L15: ='IRR inputs & outputs'!B14 -> 500
A16: Electricity | C16: =(1/'IRR inputs & outputs'!$B$8)*$B$3*'IRR inputs & outputs'!$B$9+'IRR inputs & outputs'!$B$10 -> 1551.9032 | D16: =(1/'IRR inputs & outputs'!$B$8)*$B$3*'IRR inputs & outputs'!$B$9+'IRR inputs & outputs'!$B$10 -> 1551.9032 | E16: =(1/'IRR inputs & outputs'!$B$8)*$B$3*'IRR inputs & outputs'!$B$9+'IRR inputs & outputs'!$B$10 -> 1551.9032 | F16: =(1/'IRR inputs & outputs'!$B$8)*$B$3*'IRR inputs & outputs'!$B$9+'IRR inputs & outputs'!$B$10 -> 1551.9032 | G16: =(1/'IRR inputs & outputs'!$B$8)*$B$3*'IRR inputs & outputs'!$B$9+'IRR inputs & outputs'!$B$10 -> 1551.9032 | H16: =(1/'IRR inputs & outputs'!$B$8)*$B$3*'IRR inputs & outputs'!$B$9+'IRR inputs & outputs'!$B$10 -> 1551.9032 | I16: =(1/'IRR inputs & outputs'!$B$8)*$B$3*'IRR inputs & outputs'!$B$9+'IRR inputs & outputs'!$B$10 -> 1551.9032 | J16: =(1/'IRR inputs & outputs'!$B$8)*$B$3*'IRR inputs & outputs'!$B$9+'IRR inputs & outputs'!$B$10 -> 1551.9032 | ... L16: =(1/'IRR inputs & outputs'!$B$8)*$B$3*'IRR inputs & outputs'!$B$9+'IRR inputs & outputs'!$B$10 -> 1551.9032
A17: Software - fixed | C17: ='IRR inputs & outputs'!$B$12 -> 300 | D17: ='IRR inputs & outputs'!$B$12 -> 300 | E17: ='IRR inputs & outputs'!$B$12 -> 300 | F17: ='IRR inputs & outputs'!$B$12 -> 300 | G17: ='IRR inputs & outputs'!$B$12 -> 300 | H17: ='IRR inputs & outputs'!$B$12 -> 300 | I17: ='IRR inputs & outputs'!$B$12 -> 300 | J17: ='IRR inputs & outputs'!$B$12 -> 300 | ... L17: ='IRR inputs & outputs'!$B$12 -> 300
A18: Software - variable | C18: =$B$3*'IRR inputs & outputs'!$B$11*'IRR inputs & outputs'!$B$13 -> 248.78948 | D18: =$B$3*'IRR inputs & outputs'!$B$11*'IRR inputs & outputs'!$B$13 -> 248.78948 | E18: =$B$3*'IRR inputs & outputs'!$B$11*'IRR inputs & outputs'!$B$13 -> 248.78948 | F18: =$B$3*'IRR inputs & outputs'!$B$11*'IRR inputs & outputs'!$B$13 -> 248.78948 | G18: =$B$3*'IRR inputs & outputs'!$B$11*'IRR inputs & outputs'!$B$13 -> 248.78948 | H18: =$B$3*'IRR inputs & outputs'!$B$11*'IRR inputs & outputs'!$B$13 -> 248.78948 | I18: =$B$3*'IRR inputs & outputs'!$B$11*'IRR inputs & outputs'!$B$13 -> 248.78948 | J18: =$B$3*'IRR inputs & outputs'!$B$11*'IRR inputs & outputs'!$B$13 -> 248.78948 | ... L18: =$B$3*'IRR inputs & outputs'!$B$11*'IRR inputs & outputs'!$B$13 -> 248.78948
A19: Total outgoings | B19: =SUM(B12:B18) -> 500 | C19: =SUM(C12:C18) -> 3350.6926 | D19: =SUM(D12:D18) -> 3350.6926 | E19: =SUM(E12:E18) -> 3350.6926 | F19: =SUM(F12:F18) -> 3350.6926 | G19: =SUM(G12:G18) -> 6350.6926 | H19: =SUM(H12:H18) -> 3350.6926 | I19: =SUM(I12:I18) -> 3350.6926 | ... L19: =SUM(L12:L18) -> 3350.6926
A21: Total | B21: =B9-B19 -> -500 | C21: =C9-C19 -> -33.499633 | D21: =D9-D19 -> -33.499633 | E21: =E9-E19 -> -33.499633 | F21: =F9-F19 -> -33.499633 | G21: =G9-G19 -> -3033.4996 | H21: =H9-H19 -> -33.499633 | I21: =I9-I19 -> -33.499633 | ... L21: =L9-L19 -> -33.499633
A23: IRR | B23: =IFERROR(IRR(B21:L21),NA()) -> #N/A
A25: Subsidy effect
A26: Subsidy | B26: 0.1
A27: Subsidised capex | B27: =$B$12*(1-B26) -> 0
A28: Cashflow | B28: =-B27 -> 0 | C28: =$C$21 -> -33.499633 | D28: =$D$21 -> -33.499633 | E28: =$E$21 -> -33.499633 | F28: =$F$21 -> -33.499633 | G28: =$G$21 -> -3033.4996 | H28: =$H$21 -> -33.499633 | I28: =$I$21 -> -33.499633 | J28: =$J$21 -> -33.499633 | K28: =$K$21 -> -33.499633 | L28: =$L$21 -> -33.499633
A29: IRR | B29: =IFERROR(IRR(B28:L28),NA()) -> #N/A
A31: Subsidy | B31: 0.15
A32: Subsidised capex | B32: =$B$12*(1-B31) -> 0
A33: Cashflow | B33: =-B32 -> 0 | C33: =$C$21 -> -33.499633 | D33: =$D$21 -> -33.499633 | E33: =$E$21 -> -33.499633 | F33: =$F$21 -> -33.499633 | G33: =$G$21 -> -3033.4996 | H33: =$H$21 -> -33.499633 | I33: =$I$21 -> -33.499633 | J33: =$J$21 -> -33.499633 | K33: =$K$21 -> -33.499633 | L33: =$L$21 -> -33.499633
A34: IRR | B34: =IFERROR(IRR(B33:L33),NA()) -> #N/A
A36: Subsidy | B36: 0.2
A37: Subsidised capex | B37: =$B$12*(1-B36) -> 0
A38: Cashflow | B38: =-B37 -> 0 | C38: =$C$21 -> -33.499633 | D38: =$D$21 -> -33.499633 | E38: =$E$21 -> -33.499633 | F38: =$F$21 -> -33.499633 | G38: =$G$21 -> -3033.4996 | H38: =$H$21 -> -33.499633 | I38: =$I$21 -> -33.499633 | J38: =$J$21 -> -33.499633 | K38: =$K$21 -> -33.499633 | L38: =$L$21 -> -33.499633
A39: IRR | B39: =IFERROR(IRR(B38:L38),NA()) -> #N/A
A41: Subsidy | B41: 0.25
A42: Subsidised capex | B42: =$B$12*(1-B41) -> 0
A43: Cashflow | B43: =-B42 -> 0 | C43: =$C$21 -> -33.499633 | D43: =$D$21 -> -33.499633 | E43: =$E$21 -> -33.499633 | F43: =$F$21 -> -33.499633 | G43: =$G$21 -> -3033.4996 | H43: =$H$21 -> -33.499633 | I43: =$I$21 -> -33.499633 | J43: =$J$21 -> -33.499633 | K43: =$K$21 -> -33.499633 | L43: =$L$21 -> -33.499633
A44: IRR | B44: =IFERROR(IRR(B43:L43),NA()) -> #N/A
A46: Subsidy | B46: 0.3
A47: Subsidised capex | B47: =$B$12*(1-B46) -> 0
A48: Cashflow | B48: =-B47 -> 0 | C48: =$C$21 -> -33.499633 | D48: =$D$21 -> -33.499633 | E48: =$E$21 -> -33.499633 | F48: =$F$21 -> -33.499633 | G48: =$G$21 -> -3033.4996 | H48: =$H$21 -> -33.499633 | I48: =$I$21 -> -33.499633 | J48: =$J$21 -> -33.499633 | K48: =$K$21 -> -33.499633 | L48: =$L$21 -> -33.499633
A49: IRR | B49: =IFERROR(IRR(B48:L48),NA()) -> #N/A
A51: Subsidy | B51: 0.35
A52: Subsidised capex | B52: =$B$12*(1-B51) -> 0
A53: Cashflow | B53: =-B52 -> 0 | C53: =$C$21 -> -33.499633 | D53: =$D$21 -> -33.499633 | E53: =$E$21 -> -33.499633 | F53: =$F$21 -> -33.499633 | G53: =$G$21 -> -3033.4996 | H53: =$H$21 -> -33.499633 | I53: =$I$21 -> -33.499633 | J53: =$J$21 -> -33.499633 | K53: =$K$21 -> -33.499633 | L53: =$L$21 -> -33.499633
A54: IRR | B54: =IFERROR(IRR(B53:L53),NA()) -> #N/A
A56: Subsidy | B56: 0.4
A57: Subsidised capex | B57: =$B$12*(1-B56) -> 0
A58: Cashflow | B58: =-B57 -> 0 | C58: =$C$21 -> -33.499633 | D58: =$D$21 -> -33.499633 | E58: =$E$21 -> -33.499633 | F58: =$F$21 -> -33.499633 | G58: =$G$21 -> -3033.4996 | H58: =$H$21 -> -33.499633 | I58: =$I$21 -> -33.499633 | J58: =$J$21 -> -33.499633 | K58: =$K$21 -> -33.499633 | L58: =$L$21 -> -33.499633
A59: IRR | B59: =IFERROR(IRR(B58:L58),NA()) -> #N/A
A61: Subsidy | B61: 0.45
A62: Subsidised capex | B62: =$B$12*(1-B61) -> 0
A63: Cashflow | B63: =-B62 -> 0 | C63: =$C$21 -> -33.499633 | D63: =$D$21 -> -33.499633 | E63: =$E$21 -> -33.499633 | F63: =$F$21 -> -33.499633 | G63: =$G$21 -> -3033.4996 | H63: =$H$21 -> -33.499633 | I63: =$I$21 -> -33.499633 | J63: =$J$21 -> -33.499633 | K63: =$K$21 -> -33.499633 | L63: =$L$21 -> -33.499633
A64: IRR | B64: =IFERROR(IRR(B63:L63),NA()) -> #N/A
A66: Subsidy | B66: 0.5
A67: Subsidised capex | B67: =$B$12*(1-B66) -> 0
A68: Cashflow | B68: =-B67 -> 0 | C68: =$C$21 -> -33.499633 | D68: =$D$21 -> -33.499633 | E68: =$E$21 -> -33.499633 | F68: =$F$21 -> -33.499633 | G68: =$G$21 -> -3033.4996 | H68: =$H$21 -> -33.499633 | I68: =$I$21 -> -33.499633 | J68: =$J$21 -> -33.499633 | K68: =$K$21 -> -33.499633 | L68: =$L$21 -> -33.499633
A69: IRR | B69: =IFERROR(IRR(B68:L68),NA()) -> #N/A
A71: Subsidy | B71: 0.55
A72: Subsidised capex | B72: =$B$12*(1-B71) -> 0
A73: Cashflow | B73: =-B72 -> 0 | C73: =$C$21 -> -33.499633 | D73: =$D$21 -> -33.499633 | E73: =$E$21 -> -33.499633 | F73: =$F$21 -> -33.499633 | G73: =$G$21 -> -3033.4996 | H73: =$H$21 -> -33.499633 | I73: =$I$21 -> -33.499633 | J73: =$J$21 -> -33.499633 | K73: =$K$21 -> -33.499633 | L73: =$L$21 -> -33.499633
A74: IRR | B74: =IFERROR(IRR(B73:L73),NA()) -> #N/A
A76: Subsidy | B76: 0.6
A77: Subsidised capex | B77: =$B$12*(1-B76) -> 0
A78: Cashflow | B78: =-B77 -> 0 | C78: =$C$21 -> -33.499633 | D78: =$D$21 -> -33.499633 | E78: =$E$21 -> -33.499633 | F78: =$F$21 -> -33.499633 | G78: =$G$21 -> -3033.4996 | H78: =$H$21 -> -33.499633 | I78: =$I$21 -> -33.499633 | J78: =$J$21 -> -33.499633 | K78: =$K$21 -> -33.499633 | L78: =$L$21 -> -33.499633
A79: IRR | B79: =IFERROR(IRR(B78:L78),NA()) -> #N/A
A81: Subsidy | B81: 0.65
A82: Subsidised capex | B82: =$B$12*(1-B81) -> 0
A83: Cashflow | B83: =-B82 -> 0 | C83: =$C$21 -> -33.499633 | D83: =$D$21 -> -33.499633 | E83: =$E$21 -> -33.499633 | F83: =$F$21 -> -33.499633 | G83: =$G$21 -> -3033.4996 | H83: =$H$21 -> -33.499633 | I83: =$I$21 -> -33.499633 | J83: =$J$21 -> -33.499633 | K83: =$K$21 -> -33.499633 | L83: =$L$21 -> -33.499633
A84: IRR | B84: =IFERROR(IRR(B83:L83),NA()) -> #N/A
A86: Subsidy | B86: 0.7
A87: Subsidised capex | B87: =$B$12*(1-B86) -> 0
A88: Cashflow | B88: =-B87 -> 0 | C88: =$C$21 -> -33.499633 | D88: =$D$21 -> -33.499633 | E88: =$E$21 -> -33.499633 | F88: =$F$21 -> -33.499633 | G88: =$G$21 -> -3033.4996 | H88: =$H$21 -> -33.499633 | I88: =$I$21 -> -33.499633 | J88: =$J$21 -> -33.499633 | K88: =$K$21 -> -33.499633 | L88: =$L$21 -> -33.499633
A89: IRR | B89: =IFERROR(IRR(B88:L88),NA()) -> #N/A
A91: Subsidy | B91: 0.75
A92: Subsidised capex | B92: =$B$12*(1-B91) -> 0
A93: Cashflow | B93: =-B92 -> 0 | C93: =$C$21 -> -33.499633 | D93: =$D$21 -> -33.499633 | E93: =$E$21 -> -33.499633 | F93: =$F$21 -> -33.499633 | G93: =$G$21 -> -3033.4996 | H93: =$H$21 -> -33.499633 | I93: =$I$21 -> -33.499633 | J93: =$J$21 -> -33.499633 | K93: =$K$21 -> -33.499633 | L93: =$L$21 -> -33.499633
A94: IRR | B94: =IFERROR(IRR(B93:L93),NA()) -> #N/A
A96: Subsidy | B96: 0.8
A97: Subsidised capex | B97: =$B$12*(1-B96) -> 0
A98: Cashflow | B98: =-B97 -> 0 | C98: =$C$21 -> -33.499633 | D98: =$D$21 -> -33.499633 | E98: =$E$21 -> -33.499633 | F98: =$F$21 -> -33.499633 | G98: =$G$21 -> -3033.4996 | H98: =$H$21 -> -33.499633 | I98: =$I$21 -> -33.499633 | J98: =$J$21 -> -33.499633 | K98: =$K$21 -> -33.499633 | L98: =$L$21 -> -33.499633
A99: IRR | B99: =IFERROR(IRR(B98:L98),NA()) -> #N/A
A101: Subsidy | B101: 0.85
A102: Subsidised capex | B102: =$B$12*(1-B101) -> 0
A103: Cashflow | B103: =-B102 -> 0 | C103: =$C$21 -> -33.499633 | D103: =$D$21 -> -33.499633 | E103: =$E$21 -> -33.499633 | F103: =$F$21 -> -33.499633 | G103: =$G$21 -> -3033.4996 | H103: =$H$21 -> -33.499633 | I103: =$I$21 -> -33.499633 | J103: =$J$21 -> -33.499633 | K103: =$K$21 -> -33.499633 | L103: =$L$21 -> -33.499633
A104: IRR | B104: =IFERROR(IRR(B103:L103),NA()) -> #N/A
A106: Subsidy | B106: 0.9
A107: Subsidised capex | B107: =$B$12*(1-B106) -> 0
A108: Cashflow | B108: =-B107 -> 0 | C108: =$C$21 -> -33.499633 | D108: =$D$21 -> -33.499633 | E108: =$E$21 -> -33.499633 | F108: =$F$21 -> -33.499633 | G108: =$G$21 -> -3033.4996 | H108: =$H$21 -> -33.499633 | I108: =$I$21 -> -33.499633 | J108: =$J$21 -> -33.499633 | K108: =$K$21 -> -33.499633 | L108: =$L$21 -> -33.499633
A109: IRR | B109: =IFERROR(IRR(B108:L108),NA()) -> #N/A
A111: Subsidy | B111: 0.95
A112: Subsidised capex | B112: =$B$12*(1-B111) -> 0
A113: Cashflow | B113: =-B112 -> 0 | C113: =$C$21 -> -33.499633 | D113: =$D$21 -> -33.499633 | E113: =$E$21 -> -33.499633 | F113: =$F$21 -> -33.499633 | G113: =$G$21 -> -3033.4996 | H113: =$H$21 -> -33.499633 | I113: =$I$21 -> -33.499633 | J113: =$J$21 -> -33.499633 | K113: =$K$21 -> -33.499633 | L113: =$L$21 -> -33.499633
A114: IRR | B114: =IFERROR(IRR(B113:L113),NA()) -> #N/A
A116: Subsidy | B116: 1
A117: Subsidised capex | B117: =$B$12*(1-B116) -> 0
A118: Cashflow | B118: =-B117 -> 0 | C118: =$C$21 -> -33.499633 | D118: =$D$21 -> -33.499633 | E118: =$E$21 -> -33.499633 | F118: =$F$21 -> -33.499633 | G118: =$G$21 -> -3033.4996 | H118: =$H$21 -> -33.499633 | I118: =$I$21 -> -33.499633 | J118: =$J$21 -> -33.499633 | K118: =$K$21 -> -33.499633 | L118: =$L$21 -> -33.499633
A119: IRR | B119: =IFERROR(IRR(B118:L118),NA()) -> #N/A
A122: Subsidy summary
B123: 0.1 | C123: 0.15 | D123: 0.2 | E123: 0.25 | F123: 0.3 | G123: 0.35 | H123: 0.4 | I123: 0.45 | J123: 0.5 | K123: 0.55 | L123: 0.6 | M123: 0.65 | N123: 0.7 | O123: 0.75 | P123: 0.8 | Q123: 0.85 | R123: 0.9 | S123: 0.95 | T123: 1
B124: =B29 -> #N/A | C124: =B34 -> #N/A | D124: =B39 -> #N/A | E124: =B44 -> #N/A | F124: =B49 -> #N/A | G124: =B54 -> #N/A | H124: =B59 -> #N/A | I124: =B64 -> #N/A | J124: =B69 -> #N/A | K124: =B74 -> #N/A | L124: =B79 -> #N/A | M124: =B84 -> #N/A | N124: =B89 -> #N/A | O124: =B94 -> #N/A | P124: =B99 -> #N/A | Q124: =B104 -> #N/A | R124: =B109 -> #N/A | S124: =B114 -> #N/A | T124: =B119 -> #N/A
A125: Min subsidy for DNSP | B125: =LOOKUP('IRR inputs & outputs'!B18, B124:P124, B123:P123) -> #N/A
A126: Min subsidy for CPO | B126: =LOOKUP('IRR inputs & outputs'!B19, B124:P124, B123:P123) -> #N/A

Sheet 10% utilisation
A1: Utilisation | B1: 0.1
A2: Hours in year | B2: =24*365 -> 8760
A3: Energy delivered | B3: =B2*B1*'IRR inputs & outputs'!B2*'IRR inputs & outputs'!B3*'IRR inputs & outputs'!$B$7 -> 9828.72 | C3: kWh p.a.
A5: Year | B5: 0 | C5: 1 | D5: 2 | E5: 3 | F5: 4 | G5: 5 | H5: 6 | I5: 7 | J5: 8 | K5: 9 | L5: 10
A6: Income
A7: Charging | C7: =$B$3*'IRR inputs & outputs'!$B$13 -> 4422.924 | D7: =$B$3*'IRR inputs & outputs'!$B$13 -> 4422.924 | E7: =$B$3*'IRR inputs & outputs'!$B$13 -> 4422.924 | F7: =$B$3*'IRR inputs & outputs'!$B$13 -> 4422.924 | G7: =$B$3*'IRR inputs & outputs'!$B$13 -> 4422.924 | H7: =$B$3*'IRR inputs & outputs'!$B$13 -> 4422.924 | I7: =$B$3*'IRR inputs & outputs'!$B$13 -> 4422.924 | J7: =$B$3*'IRR inputs & outputs'!$B$13 -> 4422.924 | ... L7: =$B$3*'IRR inputs & outputs'!$B$13 -> 4422.924
A9: Total income | C9: =SUM(C7:C8) -> 4422.924 | D9: =SUM(D7:D8) -> 4422.924 | E9: =SUM(E7:E8) -> 4422.924 | F9: =SUM(F7:F8) -> 4422.924 | G9: =SUM(G7:G8) -> 4422.924 | H9: =SUM(H7:H8) -> 4422.924 | I9: =SUM(I7:I8) -> 4422.924 | J9: =SUM(J7:J8) -> 4422.924 | ... L9: =SUM(L7:L8) -> 4422.924
A11: Outgoing
A12: Capex | B12: ='IRR inputs & outputs'!B6 -> 0 | G12: ='IRR inputs & outputs'!B15 -> 3000
A13: Site establishment | B13: ='IRR inputs & outputs'!B16 -> 500
A14: Site license | C14: ='IRR inputs & outputs'!$B$17 -> 750 | D14: ='IRR inputs & outputs'!$B$17 -> 750 | E14: ='IRR inputs & outputs'!$B$17 -> 750 | F14: ='IRR inputs & outputs'!$B$17 -> 750 | G14: ='IRR inputs & outputs'!$B$17 -> 750 | H14: ='IRR inputs & outputs'!$B$17 -> 750 | I14: ='IRR inputs & outputs'!$B$17 -> 750 | J14: ='IRR inputs & outputs'!$B$17 -> 750 | ... L14: ='IRR inputs & outputs'!$B$17 -> 750
A15: Maintenance | C15: ='IRR inputs & outputs'!B14 -> 500 | D15: ='IRR inputs & outputs'!B14 -> 500 | E15: ='IRR inputs & outputs'!B14 -> 500 | F15: ='IRR inputs & outputs'!B14 -> 500 | G15: ='IRR inputs & outputs'!B14 -> 500 | H15: ='IRR inputs & outputs'!B14 -> 500 | I15: ='IRR inputs & outputs'!B14 -> 500 | J15: ='IRR inputs & outputs'!B14 -> 500 | K15: ='IRR inputs & outputs'!B14 -> 500 | L15: ='IRR inputs & outputs'!B14 -> 500
A16: Electricity | C16: =(1/'IRR inputs & outputs'!$B$8)*$B$3*'IRR inputs & outputs'!$B$9+'IRR inputs & outputs'!$B$10 -> 2069.2042 | D16: =(1/'IRR inputs & outputs'!$B$8)*$B$3*'IRR inputs & outputs'!$B$9+'IRR inputs & outputs'!$B$10 -> 2069.2042 | E16: =(1/'IRR inputs & outputs'!$B$8)*$B$3*'IRR inputs & outputs'!$B$9+'IRR inputs & outputs'!$B$10 -> 2069.2042 | F16: =(1/'IRR inputs & outputs'!$B$8)*$B$3*'IRR inputs & outputs'!$B$9+'IRR inputs & outputs'!$B$10 -> 2069.2042 | G16: =(1/'IRR inputs & outputs'!$B$8)*$B$3*'IRR inputs & outputs'!$B$9+'IRR inputs & outputs'!$B$10 -> 2069.2042 | H16: =(1/'IRR inputs & outputs'!$B$8)*$B$3*'IRR inputs & outputs'!$B$9+'IRR inputs & outputs'!$B$10 -> 2069.2042 | I16: =(1/'IRR inputs & outputs'!$B$8)*$B$3*'IRR inputs & outputs'!$B$9+'IRR inputs & outputs'!$B$10 -> 2069.2042 | J16: =(1/'IRR inputs & outputs'!$B$8)*$B$3*'IRR inputs & outputs'!$B$9+'IRR inputs & outputs'!$B$10 -> 2069.2042 | ... L16: =(1/'IRR inputs & outputs'!$B$8)*$B$3*'IRR inputs & outputs'!$B$9+'IRR inputs & outputs'!$B$10 -> 2069.2042
A17: Software - fixed | C17: ='IRR inputs & outputs'!$B$12 -> 300 | D17: ='IRR inputs & outputs'!$B$12 -> 300 | E17: ='IRR inputs & outputs'!$B$12 -> 300 | F17: ='IRR inputs & outputs'!$B$12 -> 300 | G17: ='IRR inputs & outputs'!$B$12 -> 300 | H17: ='IRR inputs & outputs'!$B$12 -> 300 | I17: ='IRR inputs & outputs'!$B$12 -> 300 | J17: ='IRR inputs & outputs'!$B$12 -> 300 | ... L17: ='IRR inputs & outputs'!$B$12 -> 300
A18: Software - variable | C18: =$B$3*'IRR inputs & outputs'!$B$11*'IRR inputs & outputs'!$B$13 -> 331.7193 | D18: =$B$3*'IRR inputs & outputs'!$B$11*'IRR inputs & outputs'!$B$13 -> 331.7193 | E18: =$B$3*'IRR inputs & outputs'!$B$11*'IRR inputs & outputs'!$B$13 -> 331.7193 | F18: =$B$3*'IRR inputs & outputs'!$B$11*'IRR inputs & outputs'!$B$13 -> 331.7193 | G18: =$B$3*'IRR inputs & outputs'!$B$11*'IRR inputs & outputs'!$B$13 -> 331.7193 | H18: =$B$3*'IRR inputs & outputs'!$B$11*'IRR inputs & outputs'!$B$13 -> 331.7193 | I18: =$B$3*'IRR inputs & outputs'!$B$11*'IRR inputs & outputs'!$B$13 -> 331.7193 | J18: =$B$3*'IRR inputs & outputs'!$B$11*'IRR inputs & outputs'!$B$13 -> 331.7193 | ... L18: =$B$3*'IRR inputs & outputs'!$B$11*'IRR inputs & outputs'!$B$13 -> 331.7193
A19: Total outgoings | B19: =SUM(B12:B18) -> 500 | C19: =SUM(C12:C18) -> 3950.9235 | D19: =SUM(D12:D18) -> 3950.9235 | E19: =SUM(E12:E18) -> 3950.9235 | F19: =SUM(F12:F18) -> 3950.9235 | G19: =SUM(G12:G18) -> 6950.9235 | H19: =SUM(H12:H18) -> 3950.9235 | I19: =SUM(I12:I18) -> 3950.9235 | ... L19: =SUM(L12:L18) -> 3950.9235
A21: Total | B21: =B9-B19 -> -500 | C21: =C9-C19 -> 472.00049 | D21: =D9-D19 -> 472.00049 | E21: =E9-E19 -> 472.00049 | F21: =F9-F19 -> 472.00049 | G21: =G9-G19 -> -2527.9995 | H21: =H9-H19 -> 472.00049 | I21: =I9-I19 -> 472.00049 | ... L21: =L9-L19 -> 472.00049
A23: IRR | B23: =IFERROR(IRR(B21:L21),NA()) -> 0.58195842
A25: Subsidy effect
A26: Subsidy | B26: 0.1
A27: Subsidised capex | B27: =$B$12*(1-B26) -> 0
A28: Cashflow | B28: =-B27 -> 0 | C28: =$C$21 -> 472.00049 | D28: =$D$21 -> 472.00049 | E28: =$E$21 -> 472.00049 | F28: =$F$21 -> 472.00049 | G28: =$G$21 -> -2527.9995 | H28: =$H$21 -> 472.00049 | I28: =$I$21 -> 472.00049 | J28: =$J$21 -> 472.00049 | K28: =$K$21 -> 472.00049 | L28: =$L$21 -> 472.00049
A29: IRR | B29: =IFERROR(IRR(B28:L28),NA()) -> #N/A
A31: Subsidy | B31: 0.15
A32: Subsidised capex | B32: =$B$12*(1-B31) -> 0
A33: Cashflow | B33: =-B32 -> 0 | C33: =$C$21 -> 472.00049 | D33: =$D$21 -> 472.00049 | E33: =$E$21 -> 472.00049 | F33: =$F$21 -> 472.00049 | G33: =$G$21 -> -2527.9995 | H33: =$H$21 -> 472.00049 | I33: =$I$21 -> 472.00049 | J33: =$J$21 -> 472.00049 | K33: =$K$21 -> 472.00049 | L33: =$L$21 -> 472.00049
A34: IRR | B34: =IFERROR(IRR(B33:L33),NA()) -> #N/A
A36: Subsidy | B36: 0.2
A37: Subsidised capex | B37: =$B$12*(1-B36) -> 0
A38: Cashflow | B38: =-B37 -> 0 | C38: =$C$21 -> 472.00049 | D38: =$D$21 -> 472.00049 | E38: =$E$21 -> 472.00049 | F38: =$F$21 -> 472.00049 | G38: =$G$21 -> -2527.9995 | H38: =$H$21 -> 472.00049 | I38: =$I$21 -> 472.00049 | J38: =$J$21 -> 472.00049 | K38: =$K$21 -> 472.00049 | L38: =$L$21 -> 472.00049
A39: IRR | B39: =IFERROR(IRR(B38:L38),NA()) -> #N/A
A41: Subsidy | B41: 0.25
A42: Subsidised capex | B42: =$B$12*(1-B41) -> 0
A43: Cashflow | B43: =-B42 -> 0 | C43: =$C$21 -> 472.00049 | D43: =$D$21 -> 472.00049 | E43: =$E$21 -> 472.00049 | F43: =$F$21 -> 472.00049 | G43: =$G$21 -> -2527.9995 | H43: =$H$21 -> 472.00049 | I43: =$I$21 -> 472.00049 | J43: =$J$21 -> 472.00049 | K43: =$K$21 -> 472.00049 | L43: =$L$21 -> 472.00049
A44: IRR | B44: =IFERROR(IRR(B43:L43),NA()) -> #N/A
A46: Subsidy | B46: 0.3
A47: Subsidised capex | B47: =$B$12*(1-B46) -> 0
A48: Cashflow | B48: =-B47 -> 0 | C48: =$C$21 -> 472.00049 | D48: =$D$21 -> 472.00049 | E48: =$E$21 -> 472.00049 | F48: =$F$21 -> 472.00049 | G48: =$G$21 -> -2527.9995 | H48: =$H$21 -> 472.00049 | I48: =$I$21 -> 472.00049 | J48: =$J$21 -> 472.00049 | K48: =$K$21 -> 472.00049 | L48: =$L$21 -> 472.00049
A49: IRR | B49: =IFERROR(IRR(B48:L48),NA()) -> #N/A
A51: Subsidy | B51: 0.35
A52: Subsidised capex | B52: =$B$12*(1-B51) -> 0
A53: Cashflow | B53: =-B52 -> 0 | C53: =$C$21 -> 472.00049 | D53: =$D$21 -> 472.00049 | E53: =$E$21 -> 472.00049 | F53: =$F$21 -> 472.00049 | G53: =$G$21 -> -2527.9995 | H53: =$H$21 -> 472.00049 | I53: =$I$21 -> 472.00049 | J53: =$J$21 -> 472.00049 | K53: =$K$21 -> 472.00049 | L53: =$L$21 -> 472.00049
A54: IRR | B54: =IFERROR(IRR(B53:L53),NA()) -> #N/A
A56: Subsidy | B56: 0.4
A57: Subsidised capex | B57: =$B$12*(1-B56) -> 0
A58: Cashflow | B58: =-B57 -> 0 | C58: =$C$21 -> 472.00049 | D58: =$D$21 -> 472.00049 | E58: =$E$21 -> 472.00049 | F58: =$F$21 -> 472.00049 | G58: =$G$21 -> -2527.9995 | H58: =$H$21 -> 472.00049 | I58: =$I$21 -> 472.00049 | J58: =$J$21 -> 472.00049 | K58: =$K$21 -> 472.00049 | L58: =$L$21 -> 472.00049
A59: IRR | B59: =IFERROR(IRR(B58:L58),NA()) -> #N/A
A61: Subsidy | B61: 0.45
A62: Subsidised capex | B62: =$B$12*(1-B61) -> 0
A63: Cashflow | B63: =-B62 -> 0 | C63: =$C$21 -> 472.00049 | D63: =$D$21 -> 472.00049 | E63: =$E$21 -> 472.00049 | F63: =$F$21 -> 472.00049 | G63: =$G$21 -> -2527.9995 | H63: =$H$21 -> 472.00049 | I63: =$I$21 -> 472.00049 | J63: =$J$21 -> 472.00049 | K63: =$K$21 -> 472.00049 | L63: =$L$21 -> 472.00049
A64: IRR | B64: =IFERROR(IRR(B63:L63),NA()) -> #N/A
A66: Subsidy | B66: 0.5
A67: Subsidised capex | B67: =$B$12*(1-B66) -> 0
A68: Cashflow | B68: =-B67 -> 0 | C68: =$C$21 -> 472.00049 | D68: =$D$21 -> 472.00049 | E68: =$E$21 -> 472.00049 | F68: =$F$21 -> 472.00049 | G68: =$G$21 -> -2527.9995 | H68: =$H$21 -> 472.00049 | I68: =$I$21 -> 472.00049 | J68: =$J$21 -> 472.00049 | K68: =$K$21 -> 472.00049 | L68: =$L$21 -> 472.00049
A69: IRR | B69: =IFERROR(IRR(B68:L68),NA()) -> #N/A
A71: Subsidy | B71: 0.55
A72: Subsidised capex | B72: =$B$12*(1-B71) -> 0
A73: Cashflow | B73: =-B72 -> 0 | C73: =$C$21 -> 472.00049 | D73: =$D$21 -> 472.00049 | E73: =$E$21 -> 472.00049 | F73: =$F$21 -> 472.00049 | G73: =$G$21 -> -2527.9995 | H73: =$H$21 -> 472.00049 | I73: =$I$21 -> 472.00049 | J73: =$J$21 -> 472.00049 | K73: =$K$21 -> 472.00049 | L73: =$L$21 -> 472.00049
A74: IRR | B74: =IFERROR(IRR(B73:L73),NA()) -> #N/A
A76: Subsidy | B76: 0.6
A77: Subsidised capex | B77: =$B$12*(1-B76) -> 0
A78: Cashflow | B78: =-B77 -> 0 | C78: =$C$21 -> 472.00049 | D78: =$D$21 -> 472.00049 | E78: =$E$21 -> 472.00049 | F78: =$F$21 -> 472.00049 | G78: =$G$21 -> -2527.9995 | H78: =$H$21 -> 472.00049 | I78: =$I$21 -> 472.00049 | J78: =$J$21 -> 472.00049 | K78: =$K$21 -> 472.00049 | L78: =$L$21 -> 472.00049
A79: IRR | B79: =IFERROR(IRR(B78:L78),NA()) -> #N/A
A81: Subsidy | B81: 0.65
A82: Subsidised capex | B82: =$B$12*(1-B81) -> 0
A83: Cashflow | B83: =-B82 -> 0 | C83: =$C$21 -> 472.00049 | D83: =$D$21 -> 472.00049 | E83: =$E$21 -> 472.00049 | F83: =$F$21 -> 472.00049 | G83: =$G$21 -> -2527.9995 | H83: =$H$21 -> 472.00049 | I83: =$I$21 -> 472.00049 | J83: =$J$21 -> 472.00049 | K83: =$K$21 -> 472.00049 | L83: =$L$21 -> 472.00049
A84: IRR | B84: =IFERROR(IRR(B83:L83),NA()) -> #N/A
A86: Subsidy | B86: 0.7
A87: Subsidised capex | B87: =$B$12*(1-B86) -> 0
A88: Cashflow | B88: =-B87 -> 0 | C88: =$C$21 -> 472.00049 | D88: =$D$21 -> 472.00049 | E88: =$E$21 -> 472.00049 | F88: =$F$21 -> 472.00049 | G88: =$G$21 -> -2527.9995 | H88: =$H$21 -> 472.00049 | I88: =$I$21 -> 472.00049 | J88: =$J$21 -> 472.00049 | K88: =$K$21 -> 472.00049 | L88: =$L$21 -> 472.00049
A89: IRR | B89: =IFERROR(IRR(B88:L88),NA()) -> #N/A
A91: Subsidy | B91: 0.75
A92: Subsidised capex | B92: =$B$12*(1-B91) -> 0
A93: Cashflow | B93: =-B92 -> 0 | C93: =$C$21 -> 472.00049 | D93: =$D$21 -> 472.00049 | E93: =$E$21 -> 472.00049 | F93: =$F$21 -> 472.00049 | G93: =$G$21 -> -2527.9995 | H93: =$H$21 -> 472.00049 | I93: =$I$21 -> 472.00049 | J93: =$J$21 -> 472.00049 | K93: =$K$21 -> 472.00049 | L93: =$L$21 -> 472.00049
A94: IRR | B94: =IFERROR(IRR(B93:L93),NA()) -> #N/A
A96: Subsidy | B96: 0.8
A97: Subsidised capex | B97: =$B$12*(1-B96) -> 0
A98: Cashflow | B98: =-B97 -> 0 | C98: =$C$21 -> 472.00049 | D98: =$D$21 -> 472.00049 | E98: =$E$21 -> 472.00049 | F98: =$F$21 -> 472.00049 | G98: =$G$21 -> -2527.9995 | H98: =$H$21 -> 472.00049 | I98: =$I$21 -> 472.00049 | J98: =$J$21 -> 472.00049 | K98: =$K$21 -> 472.00049 | L98: =$L$21 -> 472.00049
A99: IRR | B99: =IFERROR(IRR(B98:L98),NA()) -> #N/A
A101: Subsidy | B101: 0.85
A102: Subsidised capex | B102: =$B$12*(1-B101) -> 0
A103: Cashflow | B103: =-B102 -> 0 | C103: =$C$21 -> 472.00049 | D103: =$D$21 -> 472.00049 | E103: =$E$21 -> 472.00049 | F103: =$F$21 -> 472.00049 | G103: =$G$21 -> -2527.9995 | H103: =$H$21 -> 472.00049 | I103: =$I$21 -> 472.00049 | J103: =$J$21 -> 472.00049 | K103: =$K$21 -> 472.00049 | L103: =$L$21 -> 472.00049
A104: IRR | B104: =IFERROR(IRR(B103:L103),NA()) -> #N/A
A106: Subsidy | B106: 0.9
A107: Subsidised capex | B107: =$B$12*(1-B106) -> 0
A108: Cashflow | B108: =-B107 -> 0 | C108: =$C$21 -> 472.00049 | D108: =$D$21 -> 472.00049 | E108: =$E$21 -> 472.00049 | F108: =$F$21 -> 472.00049 | G108: =$G$21 -> -2527.9995 | H108: =$H$21 -> 472.00049 | I108: =$I$21 -> 472.00049 | J108: =$J$21 -> 472.00049 | K108: =$K$21 -> 472.00049 | L108: =$L$21 -> 472.00049
A109: IRR | B109: =IFERROR(IRR(B108:L108),NA()) -> #N/A
A111: Subsidy | B111: 0.95
A112: Subsidised capex | B112: =$B$12*(1-B111) -> 0
A113: Cashflow | B113: =-B112 -> 0 | C113: =$C$21 -> 472.00049 | D113: =$D$21 -> 472.00049 | E113: =$E$21 -> 472.00049 | F113: =$F$21 -> 472.00049 | G113: =$G$21 -> -2527.9995 | H113: =$H$21 -> 472.00049 | I113: =$I$21 -> 472.00049 | J113: =$J$21 -> 472.00049 | K113: =$K$21 -> 472.00049 | L113: =$L$21 -> 472.00049
A114: IRR | B114: =IFERROR(IRR(B113:L113),NA()) -> #N/A
A116: Subsidy | B116: 1
A117: Subsidised capex | B117: =$B$12*(1-B116) -> 0
A118: Cashflow | B118: =-B117 -> 0 | C118: =$C$21 -> 472.00049 | D118: =$D$21 -> 472.00049 | E118: =$E$21 -> 472.00049 | F118: =$F$21 -> 472.00049 | G118: =$G$21 -> -2527.9995 | H118: =$H$21 -> 472.00049 | I118: =$I$21 -> 472.00049 | J118: =$J$21 -> 472.00049 | K118: =$K$21 -> 472.00049 | L118: =$L$21 -> 472.00049
A119: IRR | B119: =IFERROR(IRR(B118:L118),NA()) -> #N/A
A122: Subsidy summary
B123: 0.1 | C123: 0.15 | D123: 0.2 | E123: 0.25 | F123: 0.3 | G123: 0.35 | H123: 0.4 | I123: 0.45 | J123: 0.5 | K123: 0.55 | L123: 0.6 | M123: 0.65 | N123: 0.7 | O123: 0.75 | P123: 0.8 | Q123: 0.85 | R123: 0.9 | S123: 0.95 | T123: 1
B124: =B29 -> #N/A | C124: =B34 -> #N/A | D124: =B39 -> #N/A | E124: =B44 -> #N/A | F124: =B49 -> #N/A | G124: =B54 -> #N/A | H124: =B59 -> #N/A | I124: =B64 -> #N/A | J124: =B69 -> #N/A | K124: =B74 -> #N/A | L124: =B79 -> #N/A | M124: =B84 -> #N/A | N124: =B89 -> #N/A | O124: =B94 -> #N/A | P124: =B99 -> #N/A | Q124: =B104 -> #N/A | R124: =B109 -> #N/A | S124: =B114 -> #N/A | T124: =B119 -> #N/A
A125: Min subsidy for DNSP | B125: =LOOKUP('IRR inputs & outputs'!B18, B124:P124, B123:P123) -> #N/A
A126: Min subsidy for CPO | B126: =LOOKUP('IRR inputs & outputs'!B19, B124:P124, B123:P123) -> #N/A

Sheet 12.5% utilisation
A1: Utilisation | B1: 0.125
A2: Hours in year | B2: =24*365 -> 8760
A3: Energy delivered | B3: =B2*B1*'IRR inputs & outputs'!B2*'IRR inputs & outputs'!B3*'IRR inputs & outputs'!$B$7 -> 12285.9 | C3: kWh p.a.
A5: Year | B5: 0 | C5: 1 | D5: 2 | E5: 3 | F5: 4 | G5: 5 | H5: 6 | I5: 7 | J5: 8 | K5: 9 | L5: 10
A6: Income
A7: Charging | C7: =$B$3*'IRR inputs & outputs'!$B$13 -> 5528.655 | D7: =$B$3*'IRR inputs & outputs'!$B$13 -> 5528.655 | E7: =$B$3*'IRR inputs & outputs'!$B$13 -> 5528.655 | F7: =$B$3*'IRR inputs & outputs'!$B$13 -> 5528.655 | G7: =$B$3*'IRR inputs & outputs'!$B$13 -> 5528.655 | H7: =$B$3*'IRR inputs & outputs'!$B$13 -> 5528.655 | I7: =$B$3*'IRR inputs & outputs'!$B$13 -> 5528.655 | J7: =$B$3*'IRR inputs & outputs'!$B$13 -> 5528.655 | ... L7: =$B$3*'IRR inputs & outputs'!$B$13 -> 5528.655
A9: Total income | C9: =SUM(C7:C8) -> 5528.655 | D9: =SUM(D7:D8) -> 5528.655 | E9: =SUM(E7:E8) -> 5528.655 | F9: =SUM(F7:F8) -> 5528.655 | G9: =SUM(G7:G8) -> 5528.655 | H9: =SUM(H7:H8) -> 5528.655 | I9: =SUM(I7:I8) -> 5528.655 | J9: =SUM(J7:J8) -> 5528.655 | ... L9: =SUM(L7:L8) -> 5528.655
A11: Outgoing
A12: Capex | B12: ='IRR inputs & outputs'!B6 -> 0 | G12: ='IRR inputs & outputs'!B15 -> 3000
A13: Site establishment | B13: ='IRR inputs & outputs'!B16 -> 500
A14: Site license | C14: ='IRR inputs & outputs'!$B$17 -> 750 | D14: ='IRR inputs & outputs'!$B$17 -> 750 | E14: ='IRR inputs & outputs'!$B$17 -> 750 | F14: ='IRR inputs & outputs'!$B$17 -> 750 | G14: ='IRR inputs & outputs'!$B$17 -> 750 | H14: ='IRR inputs & outputs'!$B$17 -> 750 | I14: ='IRR inputs & outputs'!$B$17 -> 750 | J14: ='IRR inputs & outputs'!$B$17 -> 750 | ... L14: ='IRR inputs & outputs'!$B$17 -> 750
A15: Maintenance | C15: ='IRR inputs & outputs'!B14 -> 500 | D15: ='IRR inputs & outputs'!B14 -> 500 | E15: ='IRR inputs & outputs'!B14 -> 500 | F15: ='IRR inputs & outputs'!B14 -> 500 | G15: ='IRR inputs & outputs'!B14 -> 500 | H15: ='IRR inputs & outputs'!B14 -> 500 | I15: ='IRR inputs & outputs'!B14 -> 500 | J15: ='IRR inputs & outputs'!B14 -> 500 | K15: ='IRR inputs & outputs'!B14 -> 500 | L15: ='IRR inputs & outputs'!B14 -> 500
A16: Electricity | C16: =(1/'IRR inputs & outputs'!$B$8)*$B$3*'IRR inputs & outputs'!$B$9+'IRR inputs & outputs'!$B$10 -> 2586.5053 | D16: =(1/'IRR inputs & outputs'!$B$8)*$B$3*'IRR inputs & outputs'!$B$9+'IRR inputs & outputs'!$B$10 -> 2586.5053 | E16: =(1/'IRR inputs & outputs'!$B$8)*$B$3*'IRR inputs & outputs'!$B$9+'IRR inputs & outputs'!$B$10 -> 2586.5053 | F16: =(1/'IRR inputs & outputs'!$B$8)*$B$3*'IRR inputs & outputs'!$B$9+'IRR inputs & outputs'!$B$10 -> 2586.5053 | G16: =(1/'IRR inputs & outputs'!$B$8)*$B$3*'IRR inputs & outputs'!$B$9+'IRR inputs & outputs'!$B$10 -> 2586.5053 | H16: =(1/'IRR inputs & outputs'!$B$8)*$B$3*'IRR inputs & outputs'!$B$9+'IRR inputs & outputs'!$B$10 -> 2586.5053 | I16: =(1/'IRR inputs & outputs'!$B$8)*$B$3*'IRR inputs & outputs'!$B$9+'IRR inputs & outputs'!$B$10 -> 2586.5053 | J16: =(1/'IRR inputs & outputs'!$B$8)*$B$3*'IRR inputs & outputs'!$B$9+'IRR inputs & outputs'!$B$10 -> 2586.5053 | ... L16: =(1/'IRR inputs & outputs'!$B$8)*$B$3*'IRR inputs & outputs'!$B$9+'IRR inputs & outputs'!$B$10 -> 2586.5053
A17: Software - fixed | C17: ='IRR inputs & outputs'!$B$12 -> 300 | D17: ='IRR inputs & outputs'!$B$12 -> 300 | E17: ='IRR inputs & outputs'!$B$12 -> 300 | F17: ='IRR inputs & outputs'!$B$12 -> 300 | G17: ='IRR inputs & outputs'!$B$12 -> 300 | H17: ='IRR inputs & outputs'!$B$12 -> 300 | I17: ='IRR inputs & outputs'!$B$12 -> 300 | J17: ='IRR inputs & outputs'!$B$12 -> 300 | ... L17: ='IRR inputs & outputs'!$B$12 -> 300
A18: Software - variable | C18: =$B$3*'IRR inputs & outputs'!$B$11*'IRR inputs & outputs'!$B$13 -> 414.64912 | D18: =$B$3*'IRR inputs & outputs'!$B$11*'IRR inputs & outputs'!$B$13 -> 414.64912 | E18: =$B$3*'IRR inputs & outputs'!$B$11*'IRR inputs & outputs'!$B$13 -> 414.64912 | F18: =$B$3*'IRR inputs & outputs'!$B$11*'IRR inputs & outputs'!$B$13 -> 414.64912 | G18: =$B$3*'IRR inputs & outputs'!$B$11*'IRR inputs & outputs'!$B$13 -> 414.64912 | H18: =$B$3*'IRR inputs & outputs'!$B$11*'IRR inputs & outputs'!$B$13 -> 414.64912 | I18: =$B$3*'IRR inputs & outputs'!$B$11*'IRR inputs & outputs'!$B$13 -> 414.64912 | J18: =$B$3*'IRR inputs & outputs'!$B$11*'IRR inputs & outputs'!$B$13 -> 414.64912 | ... L18: =$B$3*'IRR inputs & outputs'!$B$11*'IRR inputs & outputs'!$B$13 -> 414.64912
A19: Total outgoings | B19: =SUM(B12:B18) -> 500 | C19: =SUM(C12:C18) -> 4551.1544 | D19: =SUM(D12:D18) -> 4551.1544 | E19: =SUM(E12:E18) -> 4551.1544 | F19: =SUM(F12:F18) -> 4551.1544 | G19: =SUM(G12:G18) -> 7551.1544 | H19: =SUM(H12:H18) -> 4551.1544 | I19: =SUM(I12:I18) -> 4551.1544 | ... L19: =SUM(L12:L18) -> 4551.1544
A21: Total | B21: =B9-B19 -> -500 | C21: =C9-C19 -> 977.50061 | D21: =D9-D19 -> 977.50061 | E21: =E9-E19 -> 977.50061 | F21: =F9-F19 -> 977.50061 | G21: =G9-G19 -> -2022.4994 | H21: =H9-H19 -> 977.50061 | I21: =I9-I19 -> 977.50061 | ... L21: =L9-L19 -> 977.50061
A23: IRR | B23: =IFERROR(IRR(B21:L21),NA()) -> 1.8993305
A25: Subsidy effect
A26: Subsidy | B26: 0.1
A27: Subsidised capex | B27: =$B$12*(1-B26) -> 0
A28: Cashflow | B28: =-B27 -> 0 | C28: =$C$21 -> 977.50061 | D28: =$D$21 -> 977.50061 | E28: =$E$21 -> 977.50061 | F28: =$F$21 -> 977.50061 | G28: =$G$21 -> -2022.4994 | H28: =$H$21 -> 977.50061 | I28: =$I$21 -> 977.50061 | J28: =$J$21 -> 977.50061 | K28: =$K$21 -> 977.50061 | L28: =$L$21 -> 977.50061
A29: IRR | B29: =IFERROR(IRR(B28:L28),NA()) -> #N/A
A31: Subsidy | B31: 0.15
A32: Subsidised capex | B32: =$B$12*(1-B31) -> 0
A33: Cashflow | B33: =-B32 -> 0 | C33: =$C$21 -> 977.50061 | D33: =$D$21 -> 977.50061 | E33: =$E$21 -> 977.50061 | F33: =$F$21 -> 977.50061 | G33: =$G$21 -> -2022.4994 | H33: =$H$21 -> 977.50061 | I33: =$I$21 -> 977.50061 | J33: =$J$21 -> 977.50061 | K33: =$K$21 -> 977.50061 | L33: =$L$21 -> 977.50061
A34: IRR | B34: =IFERROR(IRR(B33:L33),NA()) -> #N/A
A36: Subsidy | B36: 0.2
A37: Subsidised capex | B37: =$B$12*(1-B36) -> 0
A38: Cashflow | B38: =-B37 -> 0 | C38: =$C$21 -> 977.50061 | D38: =$D$21 -> 977.50061 | E38: =$E$21 -> 977.50061 | F38: =$F$21 -> 977.50061 | G38: =$G$21 -> -2022.4994 | H38: =$H$21 -> 977.50061 | I38: =$I$21 -> 977.50061 | J38: =$J$21 -> 977.50061 | K38: =$K$21 -> 977.50061 | L38: =$L$21 -> 977.50061
A39: IRR | B39: =IFERROR(IRR(B38:L38),NA()) -> #N/A
A41: Subsidy | B41: 0.25
A42: Subsidised capex | B42: =$B$12*(1-B41) -> 0
A43: Cashflow | B43: =-B42 -> 0 | C43: =$C$21 -> 977.50061 | D43: =$D$21 -> 977.50061 | E43: =$E$21 -> 977.50061 | F43: =$F$21 -> 977.50061 | G43: =$G$21 -> -2022.4994 | H43: =$H$21 -> 977.50061 | I43: =$I$21 -> 977.50061 | J43: =$J$21 -> 977.50061 | K43: =$K$21 -> 977.50061 | L43: =$L$21 -> 977.50061
A44: IRR | B44: =IFERROR(IRR(B43:L43),NA()) -> #N/A
A46: Subsidy | B46: 0.3
A47: Subsidised capex | B47: =$B$12*(1-B46) -> 0
A48: Cashflow | B48: =-B47 -> 0 | C48: =$C$21 -> 977.50061 | D48: =$D$21 -> 977.50061 | E48: =$E$21 -> 977.50061 | F48: =$F$21 -> 977.50061 | G48: =$G$21 -> -2022.4994 | H48: =$H$21 -> 977.50061 | I48: =$I$21 -> 977.50061 | J48: =$J$21 -> 977.50061 | K48: =$K$21 -> 977.50061 | L48: =$L$21 -> 977.50061
A49: IRR | B49: =IFERROR(IRR(B48:L48),NA()) -> #N/A
A51: Subsidy | B51: 0.35
A52: Subsidised capex | B52: =$B$12*(1-B51) -> 0
A53: Cashflow | B53: =-B52 -> 0 | C53: =$C$21 -> 977.50061 | D53: =$D$21 -> 977.50061 | E53: =$E$21 -> 977.50061 | F53: =$F$21 -> 977.50061 | G53: =$G$21 -> -2022.4994 | H53: =$H$21 -> 977.50061 | I53: =$I$21 -> 977.50061 | J53: =$J$21 -> 977.50061 | K53: =$K$21 -> 977.50061 | L53: =$L$21 -> 977.50061
A54: IRR | B54: =IFERROR(IRR(B53:L53),NA()) -> #N/A
A56: Subsidy | B56: 0.4
A57: Subsidised capex | B57: =$B$12*(1-B56) -> 0
A58: Cashflow | B58: =-B57 -> 0 | C58: =$C$21 -> 977.50061 | D58: =$D$21 -> 977.50061 | E58: =$E$21 -> 977.50061 | F58: =$F$21 -> 977.50061 | G58: =$G$21 -> -2022.4994 | H58: =$H$21 -> 977.50061 | I58: =$I$21 -> 977.50061 | J58: =$J$21 -> 977.50061 | K58: =$K$21 -> 977.50061 | L58: =$L$21 -> 977.50061
A59: IRR | B59: =IFERROR(IRR(B58:L58),NA()) -> #N/A
A61: Subsidy | B61: 0.45
A62: Subsidised capex | B62: =$B$12*(1-B61) -> 0
A63: Cashflow | B63: =-B62 -> 0 | C63: =$C$21 -> 977.50061 | D63: =$D$21 -> 977.50061 | E63: =$E$21 -> 977.50061 | F63: =$F$21 -> 977.50061 | G63: =$G$21 -> -2022.4994 | H63: =$H$21 -> 977.50061 | I63: =$I$21 -> 977.50061 | J63: =$J$21 -> 977.50061 | K63: =$K$21 -> 977.50061 | L63: =$L$21 -> 977.50061
A64: IRR | B64: =IFERROR(IRR(B63:L63),NA()) -> #N/A
A66: Subsidy | B66: 0.5
A67: Subsidised capex | B67: =$B$12*(1-B66) -> 0
A68: Cashflow | B68: =-B67 -> 0 | C68: =$C$21 -> 977.50061 | D68: =$D$21 -> 977.50061 | E68: =$E$21 -> 977.50061 | F68: =$F$21 -> 977.50061 | G68: =$G$21 -> -2022.4994 | H68: =$H$21 -> 977.50061 | I68: =$I$21 -> 977.50061 | J68: =$J$21 -> 977.50061 | K68: =$K$21 -> 977.50061 | L68: =$L$21 -> 977.50061
A69: IRR | B69: =IFERROR(IRR(B68:L68),NA()) -> #N/A
A71: Subsidy | B71: 0.55
A72: Subsidised capex | B72: =$B$12*(1-B71) -> 0
A73: Cashflow | B73: =-B72 -> 0 | C73: =$C$21 -> 977.50061 | D73: =$D$21 -> 977.50061 | E73: =$E$21 -> 977.50061 | F73: =$F$21 -> 977.50061 | G73: =$G$21 -> -2022.4994 | H73: =$H$21 -> 977.50061 | I73: =$I$21 -> 977.50061 | J73: =$J$21 -> 977.50061 | K73: =$K$21 -> 977.50061 | L73: =$L$21 -> 977.50061
A74: IRR | B74: =IFERROR(IRR(B73:L73),NA()) -> #N/A
A76: Subsidy | B76: 0.6
A77: Subsidised capex | B77: =$B$12*(1-B76) -> 0
A78: Cashflow | B78: =-B77 -> 0 | C78: =$C$21 -> 977.50061 | D78: =$D$21 -> 977.50061 | E78: =$E$21 -> 977.50061 | F78: =$F$21 -> 977.50061 | G78: =$G$21 -> -2022.4994 | H78: =$H$21 -> 977.50061 | I78: =$I$21 -> 977.50061 | J78: =$J$21 -> 977.50061 | K78: =$K$21 -> 977.50061 | L78: =$L$21 -> 977.50061
A79: IRR | B79: =IFERROR(IRR(B78:L78),NA()) -> #N/A
A81: Subsidy | B81: 0.65
A82: Subsidised capex | B82: =$B$12*(1-B81) -> 0
A83: Cashflow | B83: =-B82 -> 0 | C83: =$C$21 -> 977.50061 | D83: =$D$21 -> 977.50061 | E83: =$E$21 -> 977.50061 | F83: =$F$21 -> 977.50061 | G83: =$G$21 -> -2022.4994 | H83: =$H$21 -> 977.50061 | I83: =$I$21 -> 977.50061 | J83: =$J$21 -> 977.50061 | K83: =$K$21 -> 977.50061 | L83: =$L$21 -> 977.50061
A84: IRR | B84: =IFERROR(IRR(B83:L83),NA()) -> #N/A
A86: Subsidy | B86: 0.7
A87: Subsidised capex | B87: =$B$12*(1-B86) -> 0
A88: Cashflow | B88: =-B87 -> 0 | C88: =$C$21 -> 977.50061 | D88: =$D$21 -> 977.50061 | E88: =$E$21 -> 977.50061 | F88: =$F$21 -> 977.50061 | G88: =$G$21 -> -2022.4994 | H88: =$H$21 -> 977.50061 | I88: =$I$21 -> 977.50061 | J88: =$J$21 -> 977.50061 | K88: =$K$21 -> 977.50061 | L88: =$L$21 -> 977.50061
A89: IRR | B89: =IFERROR(IRR(B88:L88),NA()) -> #N/A
A91: Subsidy | B91: 0.75
A92: Subsidised capex | B92: =$B$12*(1-B91) -> 0
A93: Cashflow | B93: =-B92 -> 0 | C93: =$C$21 -> 977.50061 | D93: =$D$21 -> 977.50061 | E93: =$E$21 -> 977.50061 | F93: =$F$21 -> 977.50061 | G93: =$G$21 -> -2022.4994 | H93: =$H$21 -> 977.50061 | I93: =$I$21 -> 977.50061 | J93: =$J$21 -> 977.50061 | K93: =$K$21 -> 977.50061 | L93: =$L$21 -> 977.50061
A94: IRR | B94: =IFERROR(IRR(B93:L93),NA()) -> #N/A
A96: Subsidy | B96: 0.8
A97: Subsidised capex | B97: =$B$12*(1-B96) -> 0
A98: Cashflow | B98: =-B97 -> 0 | C98: =$C$21 -> 977.50061 | D98: =$D$21 -> 977.50061 | E98: =$E$21 -> 977.50061 | F98: =$F$21 -> 977.50061 | G98: =$G$21 -> -2022.4994 | H98: =$H$21 -> 977.50061 | I98: =$I$21 -> 977.50061 | J98: =$J$21 -> 977.50061 | K98: =$K$21 -> 977.50061 | L98: =$L$21 -> 977.50061
A99: IRR | B99: =IFERROR(IRR(B98:L98),NA()) -> #N/A
A101: Subsidy | B101: 0.85
A102: Subsidised capex | B102: =$B$12*(1-B101) -> 0
A103: Cashflow | B103: =-B102 -> 0 | C103: =$C$21 -> 977.50061 | D103: =$D$21 -> 977.50061 | E103: =$E$21 -> 977.50061 | F103: =$F$21 -> 977.50061 | G103: =$G$21 -> -2022.4994 | H103: =$H$21 -> 977.50061 | I103: =$I$21 -> 977.50061 | J103: =$J$21 -> 977.50061 | K103: =$K$21 -> 977.50061 | L103: =$L$21 -> 977.50061
A104: IRR | B104: =IFERROR(IRR(B103:L103),NA()) -> #N/A
A106: Subsidy | B106: 0.9
A107: Subsidised capex | B107: =$B$12*(1-B106) -> 0
A108: Cashflow | B108: =-B107 -> 0 | C108: =$C$21 -> 977.50061 | D108: =$D$21 -> 977.50061 | E108: =$E$21 -> 977.50061 | F108: =$F$21 -> 977.50061 | G108: =$G$21 -> -2022.4994 | H108: =$H$21 -> 977.50061 | I108: =$I$21 -> 977.50061 | J108: =$J$21 -> 977.50061 | K108: =$K$21 -> 977.50061 | L108: =$L$21 -> 977.50061
A109: IRR | B109: =IFERROR(IRR(B108:L108),NA()) -> #N/A
A111: Subsidy | B111: 0.95
A112: Subsidised capex | B112: =$B$12*(1-B111) -> 0
A113: Cashflow | B113: =-B112 -> 0 | C113: =$C$21 -> 977.50061 | D113: =$D$21 -> 977.50061 | E113: =$E$21 -> 977.50061 | F113: =$F$21 -> 977.50061 | G113: =$G$21 -> -2022.4994 | H113: =$H$21 -> 977.50061 | I113: =$I$21 -> 977.50061 | J113: =$J$21 -> 977.50061 | K113: =$K$21 -> 977.50061 | L113: =$L$21 -> 977.50061
A114: IRR | B114: =IFERROR(IRR(B113:L113),NA()) -> #N/A
A116: Subsidy | B116: 1
A117: Subsidised capex | B117: =$B$12*(1-B116) -> 0
A118: Cashflow | B118: =-B117 -> 0 | C118: =$C$21 -> 977.50061 | D118: =$D$21 -> 977.50061 | E118: =$E$21 -> 977.50061 | F118: =$F$21 -> 977.50061 | G118: =$G$21 -> -2022.4994 | H118: =$H$21 -> 977.50061 | I118: =$I$21 -> 977.50061 | J118: =$J$21 -> 977.50061 | K118: =$K$21 -> 977.50061 | L118: =$L$21 -> 977.50061
A119: IRR | B119: =IFERROR(IRR(B118:L118),NA()) -> #N/A
A122: Subsidy summary
B123: 0.1 | C123: 0.15 | D123: 0.2 | E123: 0.25 | F123: 0.3 | G123: 0.35 | H123: 0.4 | I123: 0.45 | J123: 0.5 | K123: 0.55 | L123: 0.6 | M123: 0.65 | N123: 0.7 | O123: 0.75 | P123: 0.8 | Q123: 0.85 | R123: 0.9 | S123: 0.95 | T123: 1
B124: =B29 -> #N/A | C124: =B34 -> #N/A | D124: =B39 -> #N/A | E124: =B44 -> #N/A | F124: =B49 -> #N/A | G124: =B54 -> #N/A | H124: =B59 -> #N/A | I124: =B64 -> #N/A | J124: =B69 -> #N/A | K124: =B74 -> #N/A | L124: =B79 -> #N/A | M124: =B84 -> #N/A | N124: =B89 -> #N/A | O124: =B94 -> #N/A | P124: =B99 -> #N/A | Q124: =B104 -> #N/A | R124: =B109 -> #N/A | S124: =B114 -> #N/A | T124: =B119 -> #N/A
A125: Min subsidy for DNSP | B125: =LOOKUP('IRR inputs & outputs'!B18, B124:P124, B123:P123) -> #N/A
A126: Min subsidy for CPO | B126: =LOOKUP('IRR inputs & outputs'!B19, B124:P124, B123:P123) -> #N/A

Sheet 15% utilisation
A1: Utilisation | B1: 0.15
A2: Hours in year | B2: =24*365 -> 8760
A3: Energy delivered | B3: =B2*B1*'IRR inputs & outputs'!B2*'IRR inputs & outputs'!B3*'IRR inputs & outputs'!$B$7 -> 14743.08 | C3: kWh p.a.
A5: Year | B5: 0 | C5: 1 | D5: 2 | E5: 3 | F5: 4 | G5: 5 | H5: 6 | I5: 7 | J5: 8 | K5: 9 | L5: 10
A6: Income
A7: Charging | C7: =$B$3*'IRR inputs & outputs'!$B$13 -> 6634.386 | D7: =$B$3*'IRR inputs & outputs'!$B$13 -> 6634.386 | E7: =$B$3*'IRR inputs & outputs'!$B$13 -> 6634.386 | F7: =$B$3*'IRR inputs & outputs'!$B$13 -> 6634.386 | G7: =$B$3*'IRR inputs & outputs'!$B$13 -> 6634.386 | H7: =$B$3*'IRR inputs & outputs'!$B$13 -> 6634.386 | I7: =$B$3*'IRR inputs & outputs'!$B$13 -> 6634.386 | J7: =$B$3*'IRR inputs & outputs'!$B$13 -> 6634.386 | ... L7: =$B$3*'IRR inputs & outputs'!$B$13 -> 6634.386
A9: Total income | C9: =SUM(C7:C8) -> 6634.386 | D9: =SUM(D7:D8) -> 6634.386 | E9: =SUM(E7:E8) -> 6634.386 | F9: =SUM(F7:F8) -> 6634.386 | G9: =SUM(G7:G8) -> 6634.386 | H9: =SUM(H7:H8) -> 6634.386 | I9: =SUM(I7:I8) -> 6634.386 | J9: =SUM(J7:J8) -> 6634.386 | ... L9: =SUM(L7:L8) -> 6634.386
A11: Outgoing
A12: Capex | B12: ='IRR inputs & outputs'!B6 -> 0 | G12: ='IRR inputs & outputs'!B15 -> 3000
A13: Site establishment | B13: ='IRR inputs & outputs'!B16 -> 500
A14: Site license | C14: ='IRR inputs & outputs'!$B$17 -> 750 | D14: ='IRR inputs & outputs'!$B$17 -> 750 | E14: ='IRR inputs & outputs'!$B$17 -> 750 | F14: ='IRR inputs & outputs'!$B$17 -> 750 | G14: ='IRR inputs & outputs'!$B$17 -> 750 | H14: ='IRR inputs & outputs'!$B$17 -> 750 | I14: ='IRR inputs & outputs'!$B$17 -> 750 | J14: ='IRR inputs & outputs'!$B$17 -> 750 | ... L14: ='IRR inputs & outputs'!$B$17 -> 750
A15: Maintenance | C15: ='IRR inputs & outputs'!B14 -> 500 | D15: ='IRR inputs & outputs'!B14 -> 500 | E15: ='IRR inputs & outputs'!B14 -> 500 | F15: ='IRR inputs & outputs'!B14 -> 500 | G15: ='IRR inputs & outputs'!B14 -> 500 | H15: ='IRR inputs & outputs'!B14 -> 500 | I15: ='IRR inputs & outputs'!B14 -> 500 | J15: ='IRR inputs & outputs'!B14 -> 500 | K15: ='IRR inputs & outputs'!B14 -> 500 | L15: ='IRR inputs & outputs'!B14 -> 500
A16: Electricity | C16: =(1/'IRR inputs & outputs'!$B$8)*$B$3*'IRR inputs & outputs'!$B$9+'IRR inputs & outputs'!$B$10 -> 3103.8063 | D16: =(1/'IRR inputs & outputs'!$B$8)*$B$3*'IRR inputs & outputs'!$B$9+'IRR inputs & outputs'!$B$10 -> 3103.8063 | E16: =(1/'IRR inputs & outputs'!$B$8)*$B$3*'IRR inputs & outputs'!$B$9+'IRR inputs & outputs'!$B$10 -> 3103.8063 | F16: =(1/'IRR inputs & outputs'!$B$8)*$B$3*'IRR inputs & outputs'!$B$9+'IRR inputs & outputs'!$B$10 -> 3103.8063 | G16: =(1/'IRR inputs & outputs'!$B$8)*$B$3*'IRR inputs & outputs'!$B$9+'IRR inputs & outputs'!$B$10 -> 3103.8063 | H16: =(1/'IRR inputs & outputs'!$B$8)*$B$3*'IRR inputs & outputs'!$B$9+'IRR inputs & outputs'!$B$10 -> 3103.8063 | I16: =(1/'IRR inputs & outputs'!$B$8)*$B$3*'IRR inputs & outputs'!$B$9+'IRR inputs & outputs'!$B$10 -> 3103.8063 | J16: =(1/'IRR inputs & outputs'!$B$8)*$B$3*'IRR inputs & outputs'!$B$9+'IRR inputs & outputs'!$B$10 -> 3103.8063 | ... L16: =(1/'IRR inputs & outputs'!$B$8)*$B$3*'IRR inputs & outputs'!$B$9+'IRR inputs & outputs'!$B$10 -> 3103.8063
A17: Software - fixed | C17: ='IRR inputs & outputs'!$B$12 -> 300 | D17: ='IRR inputs & outputs'!$B$12 -> 300 | E17: ='IRR inputs & outputs'!$B$12 -> 300 | F17: ='IRR inputs & outputs'!$B$12 -> 300 | G17: ='IRR inputs & outputs'!$B$12 -> 300 | H17: ='IRR inputs & outputs'!$B$12 -> 300 | I17: ='IRR inputs & outputs'!$B$12 -> 300 | J17: ='IRR inputs & outputs'!$B$12 -> 300 | ... L17: ='IRR inputs & outputs'!$B$12 -> 300
A18: Software - variable | C18: =$B$3*'IRR inputs & outputs'!$B$11*'IRR inputs & outputs'!$B$13 -> 497.57895 | D18: =$B$3*'IRR inputs & outputs'!$B$11*'IRR inputs & outputs'!$B$13 -> 497.57895 | E18: =$B$3*'IRR inputs & outputs'!$B$11*'IRR inputs & outputs'!$B$13 -> 497.57895 | F18: =$B$3*'IRR inputs & outputs'!$B$11*'IRR inputs & outputs'!$B$13 -> 497.57895 | G18: =$B$3*'IRR inputs & outputs'!$B$11*'IRR inputs & outputs'!$B$13 -> 497.57895 | H18: =$B$3*'IRR inputs & outputs'!$B$11*'IRR inputs & outputs'!$B$13 -> 497.57895 | I18: =$B$3*'IRR inputs & outputs'!$B$11*'IRR inputs & outputs'!$B$13 -> 497.57895 | J18: =$B$3*'IRR inputs & outputs'!$B$11*'IRR inputs & outputs'!$B$13 -> 497.57895 | ... L18: =$B$3*'IRR inputs & outputs'!$B$11*'IRR inputs & outputs'!$B$13 -> 497.57895
A19: Total outgoings | B19: =SUM(B12:B18) -> 500 | C19: =SUM(C12:C18) -> 5151.3853 | D19: =SUM(D12:D18) -> 5151.3853 | E19: =SUM(E12:E18) -> 5151.3853 | F19: =SUM(F12:F18) -> 5151.3853 | G19: =SUM(G12:G18) -> 8151.3853 | H19: =SUM(H12:H18) -> 5151.3853 | I19: =SUM(I12:I18) -> 5151.3853 | ... L19: =SUM(L12:L18) -> 5151.3853
A21: Total | B21: =B9-B19 -> -500 | C21: =C9-C19 -> 1483.0007 | D21: =D9-D19 -> 1483.0007 | E21: =E9-E19 -> 1483.0007 | F21: =F9-F19 -> 1483.0007 | G21: =G9-G19 -> -1516.9993 | H21: =H9-H19 -> 1483.0007 | I21: =I9-I19 -> 1483.0007 | ... L21: =L9-L19 -> 1483.0007
A23: IRR | B23: =IFERROR(IRR(B21:L21),NA()) -> 2.9475492
A25: Subsidy effect
A26: Subsidy | B26: 0.1
A27: Subsidised capex | B27: =$B$12*(1-B26) -> 0
A28: Cashflow | B28: =-B27 -> 0 | C28: =$C$21 -> 1483.0007 | D28: =$D$21 -> 1483.0007 | E28: =$E$21 -> 1483.0007 | F28: =$F$21 -> 1483.0007 | G28: =$G$21 -> -1516.9993 | H28: =$H$21 -> 1483.0007 | I28: =$I$21 -> 1483.0007 | J28: =$J$21 -> 1483.0007 | K28: =$K$21 -> 1483.0007 | L28: =$L$21 -> 1483.0007
A29: IRR | B29: =IFERROR(IRR(B28:L28),NA()) -> #N/A
A31: Subsidy | B31: 0.15
A32: Subsidised capex | B32: =$B$12*(1-B31) -> 0
A33: Cashflow | B33: =-B32 -> 0 | C33: =$C$21 -> 1483.0007 | D33: =$D$21 -> 1483.0007 | E33: =$E$21 -> 1483.0007 | F33: =$F$21 -> 1483.0007 | G33: =$G$21 -> -1516.9993 | H33: =$H$21 -> 1483.0007 | I33: =$I$21 -> 1483.0007 | J33: =$J$21 -> 1483.0007 | K33: =$K$21 -> 1483.0007 | L33: =$L$21 -> 1483.0007
A34: IRR | B34: =IFERROR(IRR(B33:L33),NA()) -> #N/A
A36: Subsidy | B36: 0.2
A37: Subsidised capex | B37: =$B$12*(1-B36) -> 0
A38: Cashflow | B38: =-B37 -> 0 | C38: =$C$21 -> 1483.0007 | D38: =$D$21 -> 1483.0007 | E38: =$E$21 -> 1483.0007 | F38: =$F$21 -> 1483.0007 | G38: =$G$21 -> -1516.9993 | H38: =$H$21 -> 1483.0007 | I38: =$I$21 -> 1483.0007 | J38: =$J$21 -> 1483.0007 | K38: =$K$21 -> 1483.0007 | L38: =$L$21 -> 1483.0007
A39: IRR | B39: =IFERROR(IRR(B38:L38),NA()) -> #N/A
A41: Subsidy | B41: 0.25
A42: Subsidised capex | B42: =$B$12*(1-B41) -> 0
A43: Cashflow | B43: =-B42 -> 0 | C43: =$C$21 -> 1483.0007 | D43: =$D$21 -> 1483.0007 | E43: =$E$21 -> 1483.0007 | F43: =$F$21 -> 1483.0007 | G43: =$G$21 -> -1516.9993 | H43: =$H$21 -> 1483.0007 | I43: =$I$21 -> 1483.0007 | J43: =$J$21 -> 1483.0007 | K43: =$K$21 -> 1483.0007 | L43: =$L$21 -> 1483.0007
A44: IRR | B44: =IFERROR(IRR(B43:L43),NA()) -> #N/A
A46: Subsidy | B46: 0.3
A47: Subsidised capex | B47: =$B$12*(1-B46) -> 0
A48: Cashflow | B48: =-B47 -> 0 | C48: =$C$21 -> 1483.0007 | D48: =$D$21 -> 1483.0007 | E48: =$E$21 -> 1483.0007 | F48: =$F$21 -> 1483.0007 | G48: =$G$21 -> -1516.9993 | H48: =$H$21 -> 1483.0007 | I48: =$I$21 -> 1483.0007 | J48: =$J$21 -> 1483.0007 | K48: =$K$21 -> 1483.0007 | L48: =$L$21 -> 1483.0007
A49: IRR | B49: =IFERROR(IRR(B48:L48),NA()) -> #N/A
A51: Subsidy | B51: 0.35
A52: Subsidised capex | B52: =$B$12*(1-B51) -> 0
A53: Cashflow | B53: =-B52 -> 0 | C53: =$C$21 -> 1483.0007 | D53: =$D$21 -> 1483.0007 | E53: =$E$21 -> 1483.0007 | F53: =$F$21 -> 1483.0007 | G53: =$G$21 -> -1516.9993 | H53: =$H$21 -> 1483.0007 | I53: =$I$21 -> 1483.0007 | J53: =$J$21 -> 1483.0007 | K53: =$K$21 -> 1483.0007 | L53: =$L$21 -> 1483.0007
A54: IRR | B54: =IFERROR(IRR(B53:L53),NA()) -> #N/A
A56: Subsidy | B56: 0.4
A57: Subsidised capex | B57: =$B$12*(1-B56) -> 0
A58: Cashflow | B58: =-B57 -> 0 | C58: =$C$21 -> 1483.0007 | D58: =$D$21 -> 1483.0007 | E58: =$E$21 -> 1483.0007 | F58: =$F$21 -> 1483.0007 | G58: =$G$21 -> -1516.9993 | H58: =$H$21 -> 1483.0007 | I58: =$I$21 -> 1483.0007 | J58: =$J$21 -> 1483.0007 | K58: =$K$21 -> 1483.0007 | L58: =$L$21 -> 1483.0007
A59: IRR | B59: =IFERROR(IRR(B58:L58),NA()) -> #N/A
A61: Subsidy | B61: 0.45
A62: Subsidised capex | B62: =$B$12*(1-B61) -> 0
A63: Cashflow | B63: =-B62 -> 0 | C63: =$C$21 -> 1483.0007 | D63: =$D$21 -> 1483.0007 | E63: =$E$21 -> 1483.0007 | F63: =$F$21 -> 1483.0007 | G63: =$G$21 -> -1516.9993 | H63: =$H$21 -> 1483.0007 | I63: =$I$21 -> 1483.0007 | J63: =$J$21 -> 1483.0007 | K63: =$K$21 -> 1483.0007 | L63: =$L$21 -> 1483.0007
A64: IRR | B64: =IFERROR(IRR(B63:L63),NA()) -> #N/A
A66: Subsidy | B66: 0.5
A67: Subsidised capex | B67: =$B$12*(1-B66) -> 0
A68: Cashflow | B68: =-B67 -> 0 | C68: =$C$21 -> 1483.0007 | D68: =$D$21 -> 1483.0007 | E68: =$E$21 -> 1483.0007 | F68: =$F$21 -> 1483.0007 | G68: =$G$21 -> -1516.9993 | H68: =$H$21 -> 1483.0007 | I68: =$I$21 -> 1483.0007 | J68: =$J$21 -> 1483.0007 | K68: =$K$21 -> 1483.0007 | L68: =$L$21 -> 1483.0007
A69: IRR | B69: =IFERROR(IRR(B68:L68),NA()) -> #N/A
A71: Subsidy | B71: 0.55
A72: Subsidised capex | B72: =$B$12*(1-B71) -> 0
A73: Cashflow | B73: =-B72 -> 0 | C73: =$C$21 -> 1483.0007 | D73: =$D$21 -> 1483.0007 | E73: =$E$21 -> 1483.0007 | F73: =$F$21 -> 1483.0007 | G73: =$G$21 -> -1516.9993 | H73: =$H$21 -> 1483.0007 | I73: =$I$21 -> 1483.0007 | J73: =$J$21 -> 1483.0007 | K73: =$K$21 -> 1483.0007 | L73: =$L$21 -> 1483.0007
A74: IRR | B74: =IFERROR(IRR(B73:L73),NA()) -> #N/A
A76: Subsidy | B76: 0.6
A77: Subsidised capex | B77: =$B$12*(1-B76) -> 0
A78: Cashflow | B78: =-B77 -> 0 | C78: =$C$21 -> 1483.0007 | D78: =$D$21 -> 1483.0007 | E78: =$E$21 -> 1483.0007 | F78: =$F$21 -> 1483.0007 | G78: =$G$21 -> -1516.9993 | H78: =$H$21 -> 1483.0007 | I78: =$I$21 -> 1483.0007 | J78: =$J$21 -> 1483.0007 | K78: =$K$21 -> 1483.0007 | L78: =$L$21 -> 1483.0007
A79: IRR | B79: =IFERROR(IRR(B78:L78),NA()) -> #N/A
A81: Subsidy | B81: 0.65
A82: Subsidised capex | B82: =$B$12*(1-B81) -> 0
A83: Cashflow | B83: =-B82 -> 0 | C83: =$C$21 -> 1483.0007 | D83: =$D$21 -> 1483.0007 | E83: =$E$21 -> 1483.0007 | F83: =$F$21 -> 1483.0007 | G83: =$G$21 -> -1516.9993 | H83: =$H$21 -> 1483.0007 | I83: =$I$21 -> 1483.0007 | J83: =$J$21 -> 1483.0007 | K83: =$K$21 -> 1483.0007 | L83: =$L$21 -> 1483.0007
A84: IRR | B84: =IFERROR(IRR(B83:L83),NA()) -> #N/A
A86: Subsidy | B86: 0.7
A87: Subsidised capex | B87: =$B$12*(1-B86) -> 0
A88: Cashflow | B88: =-B87 -> 0 | C88: =$C$21 -> 1483.0007 | D88: =$D$21 -> 1483.0007 | E88: =$E$21 -> 1483.0007 | F88: =$F$21 -> 1483.0007 | G88: =$G$21 -> -1516.9993 | H88: =$H$21 -> 1483.0007 | I88: =$I$21 -> 1483.0007 | J88: =$J$21 -> 1483.0007 | K88: =$K$21 -> 1483.0007 | L88: =$L$21 -> 1483.0007
A89: IRR | B89: =IFERROR(IRR(B88:L88),NA()) -> #N/A
A91: Subsidy | B91: 0.75
A92: Subsidised capex | B92: =$B$12*(1-B91) -> 0
A93: Cashflow | B93: =-B92 -> 0 | C93: =$C$21 -> 1483.0007 | D93: =$D$21 -> 1483.0007 | E93: =$E$21 -> 1483.0007 | F93: =$F$21 -> 1483.0007 | G93: =$G$21 -> -1516.9993 | H93: =$H$21 -> 1483.0007 | I93: =$I$21 -> 1483.0007 | J93: =$J$21 -> 1483.0007 | K93: =$K$21 -> 1483.0007 | L93: =$L$21 -> 1483.0007
A94: IRR | B94: =IFERROR(IRR(B93:L93),NA()) -> #N/A
A96: Subsidy | B96: 0.8
A97: Subsidised capex | B97: =$B$12*(1-B96) -> 0
A98: Cashflow | B98: =-B97 -> 0 | C98: =$C$21 -> 1483.0007 | D98: =$D$21 -> 1483.0007 | E98: =$E$21 -> 1483.0007 | F98: =$F$21 -> 1483.0007 | G98: =$G$21 -> -1516.9993 | H98: =$H$21 -> 1483.0007 | I98: =$I$21 -> 1483.0007 | J98: =$J$21 -> 1483.0007 | K98: =$K$21 -> 1483.0007 | L98: =$L$21 -> 1483.0007
A99: IRR | B99: =IFERROR(IRR(B98:L98),NA()) -> #N/A
A101: Subsidy | B101: 0.85
A102: Subsidised capex | B102: =$B$12*(1-B101) -> 0
A103: Cashflow | B103: =-B102 -> 0 | C103: =$C$21 -> 1483.0007 | D103: =$D$21 -> 1483.0007 | E103: =$E$21 -> 1483.0007 | F103: =$F$21 -> 1483.0007 | G103: =$G$21 -> -1516.9993 | H103: =$H$21 -> 1483.0007 | I103: =$I$21 -> 1483.0007 | J103: =$J$21 -> 1483.0007 | K103: =$K$21 -> 1483.0007 | L103: =$L$21 -> 1483.0007
A104: IRR | B104: =IFERROR(IRR(B103:L103),NA()) -> #N/A
A106: Subsidy | B106: 0.9
A107: Subsidised capex | B107: =$B$12*(1-B106) -> 0
A108: Cashflow | B108: =-B107 -> 0 | C108: =$C$21 -> 1483.0007 | D108: =$D$21 -> 1483.0007 | E108: =$E$21 -> 1483.0007 | F108: =$F$21 -> 1483.0007 | G108: =$G$21 -> -1516.9993 | H108: =$H$21 -> 1483.0007 | I108: =$I$21 -> 1483.0007 | J108: =$J$21 -> 1483.0007 | K108: =$K$21 -> 1483.0007 | L108: =$L$21 -> 1483.0007
A109: IRR | B109: =IFERROR(IRR(B108:L108),NA()) -> #N/A
A111: Subsidy | B111: 0.95
A112: Subsidised capex | B112: =$B$12*(1-B111) -> 0
A113: Cashflow | B113: =-B112 -> 0 | C113: =$C$21 -> 1483.0007 | D113: =$D$21 -> 1483.0007 | E113: =$E$21 -> 1483.0007 | F113: =$F$21 -> 1483.0007 | G113: =$G$21 -> -1516.9993 | H113: =$H$21 -> 1483.0007 | I113: =$I$21 -> 1483.0007 | J113: =$J$21 -> 1483.0007 | K113: =$K$21 -> 1483.0007 | L113: =$L$21 -> 1483.0007
A114: IRR | B114: =IFERROR(IRR(B113:L113),NA()) -> #N/A
A116: Subsidy | B116: 1
A117: Subsidised capex | B117: =$B$12*(1-B116) -> 0
A118: Cashflow | B118: =-B117 -> 0 | C118: =$C$21 -> 1483.0007 | D118: =$D$21 -> 1483.0007 | E118: =$E$21 -> 1483.0007 | F118: =$F$21 -> 1483.0007 | G118: =$G$21 -> -1516.9993 | H118: =$H$21 -> 1483.0007 | I118: =$I$21 -> 1483.0007 | J118: =$J$21 -> 1483.0007 | K118: =$K$21 -> 1483.0007 | L118: =$L$21 -> 1483.0007
A119: IRR | B119: =IFERROR(IRR(B118:L118),NA()) -> #N/A
A122: Subsidy summary
B123: 0.1 | C123: 0.15 | D123: 0.2 | E123: 0.25 | F123: 0.3 | G123: 0.35 | H123: 0.4 | I123: 0.45 | J123: 0.5 | K123: 0.55 | L123: 0.6 | M123: 0.65 | N123: 0.7 | O123: 0.75 | P123: 0.8 | Q123: 0.85 | R123: 0.9 | S123: 0.95 | T123: 1
B124: =B29 -> #N/A | C124: =B34 -> #N/A | D124: =B39 -> #N/A | E124: =B44 -> #N/A | F124: =B49 -> #N/A | G124: =B54 -> #N/A | H124: =B59 -> #N/A | I124: =B64 -> #N/A | J124: =B69 -> #N/A | K124: =B74 -> #N/A | L124: =B79 -> #N/A | M124: =B84 -> #N/A | N124: =B89 -> #N/A | O124: =B94 -> #N/A | P124: =B99 -> #N/A | Q124: =B104 -> #N/A | R124: =B109 -> #N/A | S124: =B114 -> #N/A | T124: =B119 -> #N/A
A125: Min subsidy for DNSP | B125: =LOOKUP('IRR inputs & outputs'!B18, B124:P124, B123:P123) -> #N/A
A126: Min subsidy for CPO | B126: =LOOKUP('IRR inputs & outputs'!B19, B124:P124, B123:P123) -> #N/A

Sheet 17.5% utilisation
A1: Utilisation | B1: 0.175
A2: Hours in year | B2: =24*365 -> 8760
A3: Energy delivered | B3: =B2*B1*'IRR inputs & outputs'!B2*'IRR inputs & outputs'!B3*'IRR inputs & outputs'!$B$7 -> 17200.26 | C3: kWh p.a.
A5: Year | B5: 0 | C5: 1 | D5: 2 | E5: 3 | F5: 4 | G5: 5 | H5: 6 | I5: 7 | J5: 8 | K5: 9 | L5: 10
A6: Income
A7: Charging | C7: =$B$3*'IRR inputs & outputs'!$B$13 -> 7740.117 | D7: =$B$3*'IRR inputs & outputs'!$B$13 -> 7740.117 | E7: =$B$3*'IRR inputs & outputs'!$B$13 -> 7740.117 | F7: =$B$3*'IRR inputs & outputs'!$B$13 -> 7740.117 | G7: =$B$3*'IRR inputs & outputs'!$B$13 -> 7740.117 | H7: =$B$3*'IRR inputs & outputs'!$B$13 -> 7740.117 | I7: =$B$3*'IRR inputs & outputs'!$B$13 -> 7740.117 | J7: =$B$3*'IRR inputs & outputs'!$B$13 -> 7740.117 | ... L7: =$B$3*'IRR inputs & outputs'!$B$13 -> 7740.117
A9: Total income | C9: =SUM(C7:C8) -> 7740.117 | D9: =SUM(D7:D8) -> 7740.117 | E9: =SUM(E7:E8) -> 7740.117 | F9: =SUM(F7:F8) -> 7740.117 | G9: =SUM(G7:G8) -> 7740.117 | H9: =SUM(H7:H8) -> 7740.117 | I9: =SUM(I7:I8) -> 7740.117 | J9: =SUM(J7:J8) -> 7740.117 | ... L9: =SUM(L7:L8) -> 7740.117
A11: Outgoing
A12: Capex | B12: ='IRR inputs & outputs'!B6 -> 0 | G12: ='IRR inputs & outputs'!B15 -> 3000
A13: Site establishment | B13: ='IRR inputs & outputs'!B16 -> 500
A14: Site license | C14: ='IRR inputs & outputs'!$B$17 -> 750 | D14: ='IRR inputs & outputs'!$B$17 -> 750 | E14: ='IRR inputs & outputs'!$B$17 -> 750 | F14: ='IRR inputs & outputs'!$B$17 -> 750 | G14: ='IRR inputs & outputs'!$B$17 -> 750 | H14: ='IRR inputs & outputs'!$B$17 -> 750 | I14: ='IRR inputs & outputs'!$B$17 -> 750 | J14: ='IRR inputs & outputs'!$B$17 -> 750 | ... L14: ='IRR inputs & outputs'!$B$17 -> 750
A15: Maintenance | C15: ='IRR inputs & outputs'!B14 -> 500 | D15: ='IRR inputs & outputs'!B14 -> 500 | E15: ='IRR inputs & outputs'!B14 -> 500 | F15: ='IRR inputs & outputs'!B14 -> 500 | G15: ='IRR inputs & outputs'!B14 -> 500 | H15: ='IRR inputs & outputs'!B14 -> 500 | I15: ='IRR inputs & outputs'!B14 -> 500 | J15: ='IRR inputs & outputs'!B14 -> 500 | K15: ='IRR inputs & outputs'!B14 -> 500 | L15: ='IRR inputs & outputs'!B14 -> 500
A16: Electricity | C16: =(1/'IRR inputs & outputs'!$B$8)*$B$3*'IRR inputs & outputs'!$B$9+'IRR inputs & outputs'!$B$10 -> 3621.1074 | D16: =(1/'IRR inputs & outputs'!$B$8)*$B$3*'IRR inputs & outputs'!$B$9+'IRR inputs & outputs'!$B$10 -> 3621.1074 | E16: =(1/'IRR inputs & outputs'!$B$8)*$B$3*'IRR inputs & outputs'!$B$9+'IRR inputs & outputs'!$B$10 -> 3621.1074 | F16: =(1/'IRR inputs & outputs'!$B$8)*$B$3*'IRR inputs & outputs'!$B$9+'IRR inputs & outputs'!$B$10 -> 3621.1074 | G16: =(1/'IRR inputs & outputs'!$B$8)*$B$3*'IRR inputs & outputs'!$B$9+'IRR inputs & outputs'!$B$10 -> 3621.1074 | H16: =(1/'IRR inputs & outputs'!$B$8)*$B$3*'IRR inputs & outputs'!$B$9+'IRR inputs & outputs'!$B$10 -> 3621.1074 | I16: =(1/'IRR inputs & outputs'!$B$8)*$B$3*'IRR inputs & outputs'!$B$9+'IRR inputs & outputs'!$B$10 -> 3621.1074 | J16: =(1/'IRR inputs & outputs'!$B$8)*$B$3*'IRR inputs & outputs'!$B$9+'IRR inputs & outputs'!$B$10 -> 3621.1074 | ... L16: =(1/'IRR inputs & outputs'!$B$8)*$B$3*'IRR inputs & outputs'!$B$9+'IRR inputs & outputs'!$B$10 -> 3621.1074
A17: Software - fixed | C17: ='IRR inputs & outputs'!$B$12 -> 300 | D17: ='IRR inputs & outputs'!$B$12 -> 300 | E17: ='IRR inputs & outputs'!$B$12 -> 300 | F17: ='IRR inputs & outputs'!$B$12 -> 300 | G17: ='IRR inputs & outputs'!$B$12 -> 300 | H17: ='IRR inputs & outputs'!$B$12 -> 300 | I17: ='IRR inputs & outputs'!$B$12 -> 300 | J17: ='IRR inputs & outputs'!$B$12 -> 300 | ... L17: ='IRR inputs & outputs'!$B$12 -> 300
A18: Software - variable | C18: =$B$3*'IRR inputs & outputs'!$B$11*'IRR inputs & outputs'!$B$13 -> 580.50878 | D18: =$B$3*'IRR inputs & outputs'!$B$11*'IRR inputs & outputs'!$B$13 -> 580.50878 | E18: =$B$3*'IRR inputs & outputs'!$B$11*'IRR inputs & outputs'!$B$13 -> 580.50878 | F18: =$B$3*'IRR inputs & outputs'!$B$11*'IRR inputs & outputs'!$B$13 -> 580.50878 | G18: =$B$3*'IRR inputs & outputs'!$B$11*'IRR inputs & outputs'!$B$13 -> 580.50878 | H18: =$B$3*'IRR inputs & outputs'!$B$11*'IRR inputs & outputs'!$B$13 -> 580.50878 | I18: =$B$3*'IRR inputs & outputs'!$B$11*'IRR inputs & outputs'!$B$13 -> 580.50878 | J18: =$B$3*'IRR inputs & outputs'!$B$11*'IRR inputs & outputs'!$B$13 -> 580.50878 | ... L18: =$B$3*'IRR inputs & outputs'!$B$11*'IRR inputs & outputs'!$B$13 -> 580.50878
A19: Total outgoings | B19: =SUM(B12:B18) -> 500 | C19: =SUM(C12:C18) -> 5751.6161 | D19: =SUM(D12:D18) -> 5751.6161 | E19: =SUM(E12:E18) -> 5751.6161 | F19: =SUM(F12:F18) -> 5751.6161 | G19: =SUM(G12:G18) -> 8751.6161 | H19: =SUM(H12:H18) -> 5751.6161 | I19: =SUM(I12:I18) -> 5751.6161 | ... L19: =SUM(L12:L18) -> 5751.6161
A21: Total | B21: =B9-B19 -> -500 | C21: =C9-C19 -> 1988.5009 | D21: =D9-D19 -> 1988.5009 | E21: =E9-E19 -> 1988.5009 | F21: =F9-F19 -> 1988.5009 | G21: =G9-G19 -> -1011.4991 | H21: =H9-H19 -> 1988.5009 | I21: =I9-I19 -> 1988.5009 | ... L21: =L9-L19 -> 1988.5009
A23: IRR | B23: =IFERROR(IRR(B21:L21),NA()) -> 3.9691409
A25: Subsidy effect
A26: Subsidy | B26: 0.1
A27: Subsidised capex | B27: =$B$12*(1-B26) -> 0
A28: Cashflow | B28: =-B27 -> 0 | C28: =$C$21 -> 1988.5009 | D28: =$D$21 -> 1988.5009 | E28: =$E$21 -> 1988.5009 | F28: =$F$21 -> 1988.5009 | G28: =$G$21 -> -1011.4991 | H28: =$H$21 -> 1988.5009 | I28: =$I$21 -> 1988.5009 | J28: =$J$21 -> 1988.5009 | K28: =$K$21 -> 1988.5009 | L28: =$L$21 -> 1988.5009
A29: IRR | B29: =IFERROR(IRR(B28:L28),NA()) -> #N/A
A31: Subsidy | B31: 0.15
A32: Subsidised capex | B32: =$B$12*(1-B31) -> 0
A33: Cashflow | B33: =-B32 -> 0 | C33: =$C$21 -> 1988.5009 | D33: =$D$21 -> 1988.5009 | E33: =$E$21 -> 1988.5009 | F33: =$F$21 -> 1988.5009 | G33: =$G$21 -> -1011.4991 | H33: =$H$21 -> 1988.5009 | I33: =$I$21 -> 1988.5009 | J33: =$J$21 -> 1988.5009 | K33: =$K$21 -> 1988.5009 | L33: =$L$21 -> 1988.5009
A34: IRR | B34: =IFERROR(IRR(B33:L33),NA()) -> #N/A
A36: Subsidy | B36: 0.2
A37: Subsidised capex | B37: =$B$12*(1-B36) -> 0
A38: Cashflow | B38: =-B37 -> 0 | C38: =$C$21 -> 1988.5009 | D38: =$D$21 -> 1988.5009 | E38: =$E$21 -> 1988.5009 | F38: =$F$21 -> 1988.5009 | G38: =$G$21 -> -1011.4991 | H38: =$H$21 -> 1988.5009 | I38: =$I$21 -> 1988.5009 | J38: =$J$21 -> 1988.5009 | K38: =$K$21 -> 1988.5009 | L38: =$L$21 -> 1988.5009
A39: IRR | B39: =IFERROR(IRR(B38:L38),NA()) -> #N/A
A41: Subsidy | B41: 0.25
A42: Subsidised capex | B42: =$B$12*(1-B41) -> 0
A43: Cashflow | B43: =-B42 -> 0 | C43: =$C$21 -> 1988.5009 | D43: =$D$21 -> 1988.5009 | E43: =$E$21 -> 1988.5009 | F43: =$F$21 -> 1988.5009 | G43: =$G$21 -> -1011.4991 | H43: =$H$21 -> 1988.5009 | I43: =$I$21 -> 1988.5009 | J43: =$J$21 -> 1988.5009 | K43: =$K$21 -> 1988.5009 | L43: =$L$21 -> 1988.5009
A44: IRR | B44: =IFERROR(IRR(B43:L43),NA()) -> #N/A
A46: Subsidy | B46: 0.3
A47: Subsidised capex | B47: =$B$12*(1-B46) -> 0
A48: Cashflow | B48: =-B47 -> 0 | C48: =$C$21 -> 1988.5009 | D48: =$D$21 -> 1988.5009 | E48: =$E$21 -> 1988.5009 | F48: =$F$21 -> 1988.5009 | G48: =$G$21 -> -1011.4991 | H48: =$H$21 -> 1988.5009 | I48: =$I$21 -> 1988.5009 | J48: =$J$21 -> 1988.5009 | K48: =$K$21 -> 1988.5009 | L48: =$L$21 -> 1988.5009
A49: IRR | B49: =IFERROR(IRR(B48:L48),NA()) -> #N/A
A51: Subsidy | B51: 0.35
A52: Subsidised capex | B52: =$B$12*(1-B51) -> 0
A53: Cashflow | B53: =-B52 -> 0 | C53: =$C$21 -> 1988.5009 | D53: =$D$21 -> 1988.5009 | E53: =$E$21 -> 1988.5009 | F53: =$F$21 -> 1988.5009 | G53: =$G$21 -> -1011.4991 | H53: =$H$21 -> 1988.5009 | I53: =$I$21 -> 1988.5009 | J53: =$J$21 -> 1988.5009 | K53: =$K$21 -> 1988.5009 | L53: =$L$21 -> 1988.5009
A54: IRR | B54: =IFERROR(IRR(B53:L53),NA()) -> #N/A
A56: Subsidy | B56: 0.4
A57: Subsidised capex | B57: =$B$12*(1-B56) -> 0
A58: Cashflow | B58: =-B57 -> 0 | C58: =$C$21 -> 1988.5009 | D58: =$D$21 -> 1988.5009 | E58: =$E$21 -> 1988.5009 | F58: =$F$21 -> 1988.5009 | G58: =$G$21 -> -1011.4991 | H58: =$H$21 -> 1988.5009 | I58: =$I$21 -> 1988.5009 | J58: =$J$21 -> 1988.5009 | K58: =$K$21 -> 1988.5009 | L58: =$L$21 -> 1988.5009
A59: IRR | B59: =IFERROR(IRR(B58:L58),NA()) -> #N/A
A61: Subsidy | B61: 0.45
A62: Subsidised capex | B62: =$B$12*(1-B61) -> 0
A63: Cashflow | B63: =-B62 -> 0 | C63: =$C$21 -> 1988.5009 | D63: =$D$21 -> 1988.5009 | E63: =$E$21 -> 1988.5009 | F63: =$F$21 -> 1988.5009 | G63: =$G$21 -> -1011.4991 | H63: =$H$21 -> 1988.5009 | I63: =$I$21 -> 1988.5009 | J63: =$J$21 -> 1988.5009 | K63: =$K$21 -> 1988.5009 | L63: =$L$21 -> 1988.5009
A64: IRR | B64: =IFERROR(IRR(B63:L63),NA()) -> #N/A
A66: Subsidy | B66: 0.5
A67: Subsidised capex | B67: =$B$12*(1-B66) -> 0
A68: Cashflow | B68: =-B67 -> 0 | C68: =$C$21 -> 1988.5009 | D68: =$D$21 -> 1988.5009 | E68: =$E$21 -> 1988.5009 | F68: =$F$21 -> 1988.5009 | G68: =$G$21 -> -1011.4991 | H68: =$H$21 -> 1988.5009 | I68: =$I$21 -> 1988.5009 | J68: =$J$21 -> 1988.5009 | K68: =$K$21 -> 1988.5009 | L68: =$L$21 -> 1988.5009
A69: IRR | B69: =IFERROR(IRR(B68:L68),NA()) -> #N/A
A71: Subsidy | B71: 0.55
A72: Subsidised capex | B72: =$B$12*(1-B71) -> 0
A73: Cashflow | B73: =-B72 -> 0 | C73: =$C$21 -> 1988.5009 | D73: =$D$21 -> 1988.5009 | E73: =$E$21 -> 1988.5009 | F73: =$F$21 -> 1988.5009 | G73: =$G$21 -> -1011.4991 | H73: =$H$21 -> 1988.5009 | I73: =$I$21 -> 1988.5009 | J73: =$J$21 -> 1988.5009 | K73: =$K$21 -> 1988.5009 | L73: =$L$21 -> 1988.5009
A74: IRR | B74: =IFERROR(IRR(B73:L73),NA()) -> #N/A
A76: Subsidy | B76: 0.6
A77: Subsidised capex | B77: =$B$12*(1-B76) -> 0
A78: Cashflow | B78: =-B77 -> 0 | C78: =$C$21 -> 1988.5009 | D78: =$D$21 -> 1988.5009 | E78: =$E$21 -> 1988.5009 | F78: =$F$21 -> 1988.5009 | G78: =$G$21 -> -1011.4991 | H78: =$H$21 -> 1988.5009 | I78: =$I$21 -> 1988.5009 | J78: =$J$21 -> 1988.5009 | K78: =$K$21 -> 1988.5009 | L78: =$L$21 -> 1988.5009
A79: IRR | B79: =IFERROR(IRR(B78:L78),NA()) -> #N/A
A81: Subsidy | B81: 0.65
A82: Subsidised capex | B82: =$B$12*(1-B81) -> 0
A83: Cashflow | B83: =-B82 -> 0 | C83: =$C$21 -> 1988.5009 | D83: =$D$21 -> 1988.5009 | E83: =$E$21 -> 1988.5009 | F83: =$F$21 -> 1988.5009 | G83: =$G$21 -> -1011.4991 | H83: =$H$21 -> 1988.5009 | I83: =$I$21 -> 1988.5009 | J83: =$J$21 -> 1988.5009 | K83: =$K$21 -> 1988.5009 | L83: =$L$21 -> 1988.5009
A84: IRR | B84: =IFERROR(IRR(B83:L83),NA()) -> #N/A
A86: Subsidy | B86: 0.7
A87: Subsidised capex | B87: =$B$12*(1-B86) -> 0
A88: Cashflow | B88: =-B87 -> 0 | C88: =$C$21 -> 1988.5009 | D88: =$D$21 -> 1988.5009 | E88: =$E$21 -> 1988.5009 | F88: =$F$21 -> 1988.5009 | G88: =$G$21 -> -1011.4991 | H88: =$H$21 -> 1988.5009 | I88: =$I$21 -> 1988.5009 | J88: =$J$21 -> 1988.5009 | K88: =$K$21 -> 1988.5009 | L88: =$L$21 -> 1988.5009
A89: IRR | B89: =IFERROR(IRR(B88:L88),NA()) -> #N/A
A91: Subsidy | B91: 0.75
A92: Subsidised capex | B92: =$B$12*(1-B91) -> 0
A93: Cashflow | B93: =-B92 -> 0 | C93: =$C$21 -> 1988.5009 | D93: =$D$21 -> 1988.5009 | E93: =$E$21 -> 1988.5009 | F93: =$F$21 -> 1988.5009 | G93: =$G$21 -> -1011.4991 | H93: =$H$21 -> 1988.5009 | I93: =$I$21 -> 1988.5009 | J93: =$J$21 -> 1988.5009 | K93: =$K$21 -> 1988.5009 | L93: =$L$21 -> 1988.5009
A94: IRR | B94: =IFERROR(IRR(B93:L93),NA()) -> #N/A
A96: Subsidy | B96: 0.8
A97: Subsidised capex | B97: =$B$12*(1-B96) -> 0
A98: Cashflow | B98: =-B97 -> 0 | C98: =$C$21 -> 1988.5009 | D98: =$D$21 -> 1988.5009 | E98: =$E$21 -> 1988.5009 | F98: =$F$21 -> 1988.5009 | G98: =$G$21 -> -1011.4991 | H98: =$H$21 -> 1988.5009 | I98: =$I$21 -> 1988.5009 | J98: =$J$21 -> 1988.5009 | K98: =$K$21 -> 1988.5009 | L98: =$L$21 -> 1988.5009
A99: IRR | B99: =IFERROR(IRR(B98:L98),NA()) -> #N/A
A101: Subsidy | B101: 0.85
A102: Subsidised capex | B102: =$B$12*(1-B101) -> 0
A103: Cashflow | B103: =-B102 -> 0 | C103: =$C$21 -> 1988.5009 | D103: =$D$21 -> 1988.5009 | E103: =$E$21 -> 1988.5009 | F103: =$F$21 -> 1988.5009 | G103: =$G$21 -> -1011.4991 | H103: =$H$21 -> 1988.5009 | I103: =$I$21 -> 1988.5009 | J103: =$J$21 -> 1988.5009 | K103: =$K$21 -> 1988.5009 | L103: =$L$21 -> 1988.5009
A104: IRR | B104: =IFERROR(IRR(B103:L103),NA()) -> #N/A
A106: Subsidy | B106: 0.9
A107: Subsidised capex | B107: =$B$12*(1-B106) -> 0
A108: Cashflow | B108: =-B107 -> 0 | C108: =$C$21 -> 1988.5009 | D108: =$D$21 -> 1988.5009 | E108: =$E$21 -> 1988.5009 | F108: =$F$21 -> 1988.5009 | G108: =$G$21 -> -1011.4991 | H108: =$H$21 -> 1988.5009 | I108: =$I$21 -> 1988.5009 | J108: =$J$21 -> 1988.5009 | K108: =$K$21 -> 1988.5009 | L108: =$L$21 -> 1988.5009
A109: IRR | B109: =IFERROR(IRR(B108:L108),NA()) -> #N/A
A111: Subsidy | B111: 0.95
A112: Subsidised capex | B112: =$B$12*(1-B111) -> 0
A113: Cashflow | B113: =-B112 -> 0 | C113: =$C$21 -> 1988.5009 | D113: =$D$21 -> 1988.5009 | E113: =$E$21 -> 1988.5009 | F113: =$F$21 -> 1988.5009 | G113: =$G$21 -> -1011.4991 | H113: =$H$21 -> 1988.5009 | I113: =$I$21 -> 1988.5009 | J113: =$J$21 -> 1988.5009 | K113: =$K$21 -> 1988.5009 | L113: =$L$21 -> 1988.5009
A114: IRR | B114: =IFERROR(IRR(B113:L113),NA()) -> #N/A
A116: Subsidy | B116: 1
A117: Subsidised capex | B117: =$B$12*(1-B116) -> 0
A118: Cashflow | B118: =-B117 -> 0 | C118: =$C$21 -> 1988.5009 | D118: =$D$21 -> 1988.5009 | E118: =$E$21 -> 1988.5009 | F118: =$F$21 -> 1988.5009 | G118: =$G$21 -> -1011.4991 | H118: =$H$21 -> 1988.5009 | I118: =$I$21 -> 1988.5009 | J118: =$J$21 -> 1988.5009 | K118: =$K$21 -> 1988.5009 | L118: =$L$21 -> 1988.5009
A119: IRR | B119: =IFERROR(IRR(B118:L118),NA()) -> #N/A
A122: Subsidy summary
B123: 0.1 | C123: 0.15 | D123: 0.2 | E123: 0.25 | F123: 0.3 | G123: 0.35 | H123: 0.4 | I123: 0.45 | J123: 0.5 | K123: 0.55 | L123: 0.6 | M123: 0.65 | N123: 0.7 | O123: 0.75 | P123: 0.8 | Q123: 0.85 | R123: 0.9 | S123: 0.95 | T123: 1
B124: =B29 -> #N/A | C124: =B34 -> #N/A | D124: =B39 -> #N/A | E124: =B44 -> #N/A | F124: =B49 -> #N/A | G124: =B54 -> #N/A | H124: =B59 -> #N/A | I124: =B64 -> #N/A | J124: =B69 -> #N/A | K124: =B74 -> #N/A | L124: =B79 -> #N/A | M124: =B84 -> #N/A | N124: =B89 -> #N/A | O124: =B94 -> #N/A | P124: =B99 -> #N/A | Q124: =B104 -> #N/A | R124: =B109 -> #N/A | S124: =B114 -> #N/A | T124: =B119 -> #N/A
A125: Min subsidy for DNSP | B125: =LOOKUP('IRR inputs & outputs'!B18, B124:P124, B123:P123) -> #N/A
A126: Min subsidy for CPO | B126: =LOOKUP('IRR inputs & outputs'!B19, B124:P124, B123:P123) -> #N/A

Sheet 20% utilisation
A1: Utilisation | B1: 0.2
A2: Hours in year | B2: =24*365 -> 8760
A3: Energy delivered | B3: =B2*B1*'IRR inputs & outputs'!B2*'IRR inputs & outputs'!B3*'IRR inputs & outputs'!$B$7 -> 19657.44 | C3: kWh p.a.
A5: Year | B5: 0 | C5: 1 | D5: 2 | E5: 3 | F5: 4 | G5: 5 | H5: 6 | I5: 7 | J5: 8 | K5: 9 | L5: 10
A6: Income
A7: Charging | C7: =$B$3*'IRR inputs & outputs'!$B$13 -> 8845.848 | D7: =$B$3*'IRR inputs & outputs'!$B$13 -> 8845.848 | E7: =$B$3*'IRR inputs & outputs'!$B$13 -> 8845.848 | F7: =$B$3*'IRR inputs & outputs'!$B$13 -> 8845.848 | G7: =$B$3*'IRR inputs & outputs'!$B$13 -> 8845.848 | H7: =$B$3*'IRR inputs & outputs'!$B$13 -> 8845.848 | I7: =$B$3*'IRR inputs & outputs'!$B$13 -> 8845.848 | J7: =$B$3*'IRR inputs & outputs'!$B$13 -> 8845.848 | ... L7: =$B$3*'IRR inputs & outputs'!$B$13 -> 8845.848
A9: Total income | C9: =SUM(C7:C8) -> 8845.848 | D9: =SUM(D7:D8) -> 8845.848 | E9: =SUM(E7:E8) -> 8845.848 | F9: =SUM(F7:F8) -> 8845.848 | G9: =SUM(G7:G8) -> 8845.848 | H9: =SUM(H7:H8) -> 8845.848 | I9: =SUM(I7:I8) -> 8845.848 | J9: =SUM(J7:J8) -> 8845.848 | ... L9: =SUM(L7:L8) -> 8845.848
A11: Outgoing
A12: Capex | B12: ='IRR inputs & outputs'!B6 -> 0 | G12: ='IRR inputs & outputs'!B15 -> 3000
A13: Site establishment | B13: ='IRR inputs & outputs'!B16 -> 500
A14: Site license | C14: ='IRR inputs & outputs'!$B$17 -> 750 | D14: ='IRR inputs & outputs'!$B$17 -> 750 | E14: ='IRR inputs & outputs'!$B$17 -> 750 | F14: ='IRR inputs & outputs'!$B$17 -> 750 | G14: ='IRR inputs & outputs'!$B$17 -> 750 | H14: ='IRR inputs & outputs'!$B$17 -> 750 | I14: ='IRR inputs & outputs'!$B$17 -> 750 | J14: ='IRR inputs & outputs'!$B$17 -> 750 | ... L14: ='IRR inputs & outputs'!$B$17 -> 750
A15: Maintenance | C15: ='IRR inputs & outputs'!B14 -> 500 | D15: ='IRR inputs & outputs'!B14 -> 500 | E15: ='IRR inputs & outputs'!B14 -> 500 | F15: ='IRR inputs & outputs'!B14 -> 500 | G15: ='IRR inputs & outputs'!B14 -> 500 | H15: ='IRR inputs & outputs'!B14 -> 500 | I15: ='IRR inputs & outputs'!B14 -> 500 | J15: ='IRR inputs & outputs'!B14 -> 500 | K15: ='IRR inputs & outputs'!B14 -> 500 | L15: ='IRR inputs & outputs'!B14 -> 500
A16: Electricity | C16: =(1/'IRR inputs & outputs'!$B$8)*$B$3*'IRR inputs & outputs'!$B$9+'IRR inputs & outputs'!$B$10 -> 4138.4084 | D16: =(1/'IRR inputs & outputs'!$B$8)*$B$3*'IRR inputs & outputs'!$B$9+'IRR inputs & outputs'!$B$10 -> 4138.4084 | E16: =(1/'IRR inputs & outputs'!$B$8)*$B$3*'IRR inputs & outputs'!$B$9+'IRR inputs & outputs'!$B$10 -> 4138.4084 | F16: =(1/'IRR inputs & outputs'!$B$8)*$B$3*'IRR inputs & outputs'!$B$9+'IRR inputs & outputs'!$B$10 -> 4138.4084 | G16: =(1/'IRR inputs & outputs'!$B$8)*$B$3*'IRR inputs & outputs'!$B$9+'IRR inputs & outputs'!$B$10 -> 4138.4084 | H16: =(1/'IRR inputs & outputs'!$B$8)*$B$3*'IRR inputs & outputs'!$B$9+'IRR inputs & outputs'!$B$10 -> 4138.4084 | I16: =(1/'IRR inputs & outputs'!$B$8)*$B$3*'IRR inputs & outputs'!$B$9+'IRR inputs & outputs'!$B$10 -> 4138.4084 | J16: =(1/'IRR inputs & outputs'!$B$8)*$B$3*'IRR inputs & outputs'!$B$9+'IRR inputs & outputs'!$B$10 -> 4138.4084 | ... L16: =(1/'IRR inputs & outputs'!$B$8)*$B$3*'IRR inputs & outputs'!$B$9+'IRR inputs & outputs'!$B$10 -> 4138.4084
A17: Software - fixed | C17: ='IRR inputs & outputs'!$B$12 -> 300 | D17: ='IRR inputs & outputs'!$B$12 -> 300 | E17: ='IRR inputs & outputs'!$B$12 -> 300 | F17: ='IRR inputs & outputs'!$B$12 -> 300 | G17: ='IRR inputs & outputs'!$B$12 -> 300 | H17: ='IRR inputs & outputs'!$B$12 -> 300 | I17: ='IRR inputs & outputs'!$B$12 -> 300 | J17: ='IRR inputs & outputs'!$B$12 -> 300 | ... L17: ='IRR inputs & outputs'!$B$12 -> 300
A18: Software - variable | C18: =$B$3*'IRR inputs & outputs'!$B$11*'IRR inputs & outputs'!$B$13 -> 663.4386 | D18: =$B$3*'IRR inputs & outputs'!$B$11*'IRR inputs & outputs'!$B$13 -> 663.4386 | E18: =$B$3*'IRR inputs & outputs'!$B$11*'IRR inputs & outputs'!$B$13 -> 663.4386 | F18: =$B$3*'IRR inputs & outputs'!$B$11*'IRR inputs & outputs'!$B$13 -> 663.4386 | G18: =$B$3*'IRR inputs & outputs'!$B$11*'IRR inputs & outputs'!$B$13 -> 663.4386 | H18: =$B$3*'IRR inputs & outputs'!$B$11*'IRR inputs & outputs'!$B$13 -> 663.4386 | I18: =$B$3*'IRR inputs & outputs'!$B$11*'IRR inputs & outputs'!$B$13 -> 663.4386 | J18: =$B$3*'IRR inputs & outputs'!$B$11*'IRR inputs & outputs'!$B$13 -> 663.4386 | ... L18: =$B$3*'IRR inputs & outputs'!$B$11*'IRR inputs & outputs'!$B$13 -> 663.4386
A19: Total outgoings | B19: =SUM(B12:B18) -> 500 | C19: =SUM(C12:C18) -> 6351.847 | D19: =SUM(D12:D18) -> 6351.847 | E19: =SUM(E12:E18) -> 6351.847 | F19: =SUM(F12:F18) -> 6351.847 | G19: =SUM(G12:G18) -> 9351.847 | H19: =SUM(H12:H18) -> 6351.847 | I19: =SUM(I12:I18) -> 6351.847 | ... L19: =SUM(L12:L18) -> 6351.847
A21: Total | B21: =B9-B19 -> -500 | C21: =C9-C19 -> 2494.001 | D21: =D9-D19 -> 2494.001 | E21: =E9-E19 -> 2494.001 | F21: =F9-F19 -> 2494.001 | G21: =G9-G19 -> -505.99902 | H21: =H9-H19 -> 2494.001 | I21: =I9-I19 -> 2494.001 | ... L21: =L9-L19 -> 2494.001
A23: IRR | B23: =IFERROR(IRR(B21:L21),NA()) -> 4.9841048
A25: Subsidy effect
A26: Subsidy | B26: 0.1
A27: Subsidised capex | B27: =$B$12*(1-B26) -> 0
A28: Cashflow | B28: =-B27 -> 0 | C28: =$C$21 -> 2494.001 | D28: =$D$21 -> 2494.001 | E28: =$E$21 -> 2494.001 | F28: =$F$21 -> 2494.001 | G28: =$G$21 -> -505.99902 | H28: =$H$21 -> 2494.001 | I28: =$I$21 -> 2494.001 | J28: =$J$21 -> 2494.001 | K28: =$K$21 -> 2494.001 | L28: =$L$21 -> 2494.001
A29: IRR | B29: =IFERROR(IRR(B28:L28),NA()) -> #N/A
A31: Subsidy | B31: 0.15
A32: Subsidised capex | B32: =$B$12*(1-B31) -> 0
A33: Cashflow | B33: =-B32 -> 0 | C33: =$C$21 -> 2494.001 | D33: =$D$21 -> 2494.001 | E33: =$E$21 -> 2494.001 | F33: =$F$21 -> 2494.001 | G33: =$G$21 -> -505.99902 | H33: =$H$21 -> 2494.001 | I33: =$I$21 -> 2494.001 | J33: =$J$21 -> 2494.001 | K33: =$K$21 -> 2494.001 | L33: =$L$21 -> 2494.001
A34: IRR | B34: =IFERROR(IRR(B33:L33),NA()) -> #N/A
A36: Subsidy | B36: 0.2
A37: Subsidised capex | B37: =$B$12*(1-B36) -> 0
A38: Cashflow | B38: =-B37 -> 0 | C38: =$C$21 -> 2494.001 | D38: =$D$21 -> 2494.001 | E38: =$E$21 -> 2494.001 | F38: =$F$21 -> 2494.001 | G38: =$G$21 -> -505.99902 | H38: =$H$21 -> 2494.001 | I38: =$I$21 -> 2494.001 | J38: =$J$21 -> 2494.001 | K38: =$K$21 -> 2494.001 | L38: =$L$21 -> 2494.001
A39: IRR | B39: =IFERROR(IRR(B38:L38),NA()) -> #N/A
A41: Subsidy | B41: 0.25
A42: Subsidised capex | B42: =$B$12*(1-B41) -> 0
A43: Cashflow | B43: =-B42 -> 0 | C43: =$C$21 -> 2494.001 | D43: =$D$21 -> 2494.001 | E43: =$E$21 -> 2494.001 | F43: =$F$21 -> 2494.001 | G43: =$G$21 -> -505.99902 | H43: =$H$21 -> 2494.001 | I43: =$I$21 -> 2494.001 | J43: =$J$21 -> 2494.001 | K43: =$K$21 -> 2494.001 | L43: =$L$21 -> 2494.001
A44: IRR | B44: =IFERROR(IRR(B43:L43),NA()) -> #N/A
A46: Subsidy | B46: 0.3
A47: Subsidised capex | B47: =$B$12*(1-B46) -> 0
A48: Cashflow | B48: =-B47 -> 0 | C48: =$C$21 -> 2494.001 | D48: =$D$21 -> 2494.001 | E48: =$E$21 -> 2494.001 | F48: =$F$21 -> 2494.001 | G48: =$G$21 -> -505.99902 | H48: =$H$21 -> 2494.001 | I48: =$I$21 -> 2494.001 | J48: =$J$21 -> 2494.001 | K48: =$K$21 -> 2494.001 | L48: =$L$21 -> 2494.001
A49: IRR | B49: =IFERROR(IRR(B48:L48),NA()) -> #N/A
A51: Subsidy | B51: 0.35
A52: Subsidised capex | B52: =$B$12*(1-B51) -> 0
A53: Cashflow | B53: =-B52 -> 0 | C53: =$C$21 -> 2494.001 | D53: =$D$21 -> 2494.001 | E53: =$E$21 -> 2494.001 | F53: =$F$21 -> 2494.001 | G53: =$G$21 -> -505.99902 | H53: =$H$21 -> 2494.001 | I53: =$I$21 -> 2494.001 | J53: =$J$21 -> 2494.001 | K53: =$K$21 -> 2494.001 | L53: =$L$21 -> 2494.001
A54: IRR | B54: =IFERROR(IRR(B53:L53),NA()) -> #N/A
A56: Subsidy | B56: 0.4
A57: Subsidised capex | B57: =$B$12*(1-B56) -> 0
A58: Cashflow | B58: =-B57 -> 0 | C58: =$C$21 -> 2494.001 | D58: =$D$21 -> 2494.001 | E58: =$E$21 -> 2494.001 | F58: =$F$21 -> 2494.001 | G58: =$G$21 -> -505.99902 | H58: =$H$21 -> 2494.001 | I58: =$I$21 -> 2494.001 | J58: =$J$21 -> 2494.001 | K58: =$K$21 -> 2494.001 | L58: =$L$21 -> 2494.001
A59: IRR | B59: =IFERROR(IRR(B58:L58),NA()) -> #N/A
A61: Subsidy | B61: 0.45
A62: Subsidised capex | B62: =$B$12*(1-B61) -> 0
A63: Cashflow | B63: =-B62 -> 0 | C63: =$C$21 -> 2494.001 | D63: =$D$21 -> 2494.001 | E63: =$E$21 -> 2494.001 | F63: =$F$21 -> 2494.001 | G63: =$G$21 -> -505.99902 | H63: =$H$21 -> 2494.001 | I63: =$I$21 -> 2494.001 | J63: =$J$21 -> 2494.001 | K63: =$K$21 -> 2494.001 | L63: =$L$21 -> 2494.001
A64: IRR | B64: =IFERROR(IRR(B63:L63),NA()) -> #N/A
A66: Subsidy | B66: 0.5
A67: Subsidised capex | B67: =$B$12*(1-B66) -> 0
A68: Cashflow | B68: =-B67 -> 0 | C68: =$C$21 -> 2494.001 | D68: =$D$21 -> 2494.001 | E68: =$E$21 -> 2494.001 | F68: =$F$21 -> 2494.001 | G68: =$G$21 -> -505.99902 | H68: =$H$21 -> 2494.001 | I68: =$I$21 -> 2494.001 | J68: =$J$21 -> 2494.001 | K68: =$K$21 -> 2494.001 | L68: =$L$21 -> 2494.001
A69: IRR | B69: =IFERROR(IRR(B68:L68),NA()) -> #N/A
A71: Subsidy | B71: 0.55
A72: Subsidised capex | B72: =$B$12*(1-B71) -> 0
A73: Cashflow | B73: =-B72 -> 0 | C73: =$C$21 -> 2494.001 | D73: =$D$21 -> 2494.001 | E73: =$E$21 -> 2494.001 | F73: =$F$21 -> 2494.001 | G73: =$G$21 -> -505.99902 | H73: =$H$21 -> 2494.001 | I73: =$I$21 -> 2494.001 | J73: =$J$21 -> 2494.001 | K73: =$K$21 -> 2494.001 | L73: =$L$21 -> 2494.001
A74: IRR | B74: =IFERROR(IRR(B73:L73),NA()) -> #N/A
A76: Subsidy | B76: 0.6
A77: Subsidised capex | B77: =$B$12*(1-B76) -> 0
A78: Cashflow | B78: =-B77 -> 0 | C78: =$C$21 -> 2494.001 | D78: =$D$21 -> 2494.001 | E78: =$E$21 -> 2494.001 | F78: =$F$21 -> 2494.001 | G78: =$G$21 -> -505.99902 | H78: =$H$21 -> 2494.001 | I78: =$I$21 -> 2494.001 | J78: =$J$21 -> 2494.001 | K78: =$K$21 -> 2494.001 | L78: =$L$21 -> 2494.001
A79: IRR | B79: =IFERROR(IRR(B78:L78),NA()) -> #N/A
A81: Subsidy | B81: 0.65
A82: Subsidised capex | B82: =$B$12*(1-B81) -> 0
A83: Cashflow | B83: =-B82 -> 0 | C83: =$C$21 -> 2494.001 | D83: =$D$21 -> 2494.001 | E83: =$E$21 -> 2494.001 | F83: =$F$21 -> 2494.001 | G83: =$G$21 -> -505.99902 | H83: =$H$21 -> 2494.001 | I83: =$I$21 -> 2494.001 | J83: =$J$21 -> 2494.001 | K83: =$K$21 -> 2494.001 | L83: =$L$21 -> 2494.001
A84: IRR | B84: =IFERROR(IRR(B83:L83),NA()) -> #N/A
A86: Subsidy | B86: 0.7
A87: Subsidised capex | B87: =$B$12*(1-B86) -> 0
A88: Cashflow | B88: =-B87 -> 0 | C88: =$C$21 -> 2494.001 | D88: =$D$21 -> 2494.001 | E88: =$E$21 -> 2494.001 | F88: =$F$21 -> 2494.001 | G88: =$G$21 -> -505.99902 | H88: =$H$21 -> 2494.001 | I88: =$I$21 -> 2494.001 | J88: =$J$21 -> 2494.001 | K88: =$K$21 -> 2494.001 | L88: =$L$21 -> 2494.001
A89: IRR | B89: =IFERROR(IRR(B88:L88),NA()) -> #N/A
A91: Subsidy | B91: 0.75
A92: Subsidised capex | B92: =$B$12*(1-B91) -> 0
A93: Cashflow | B93: =-B92 -> 0 | C93: =$C$21 -> 2494.001 | D93: =$D$21 -> 2494.001 | E93: =$E$21 -> 2494.001 | F93: =$F$21 -> 2494.001 | G93: =$G$21 -> -505.99902 | H93: =$H$21 -> 2494.001 | I93: =$I$21 -> 2494.001 | J93: =$J$21 -> 2494.001 | K93: =$K$21 -> 2494.001 | L93: =$L$21 -> 2494.001
A94: IRR | B94: =IFERROR(IRR(B93:L93),NA()) -> #N/A
A96: Subsidy | B96: 0.8
A97: Subsidised capex | B97: =$B$12*(1-B96) -> 0
A98: Cashflow | B98: =-B97 -> 0 | C98: =$C$21 -> 2494.001 | D98: =$D$21 -> 2494.001 | E98: =$E$21 -> 2494.001 | F98: =$F$21 -> 2494.001 | G98: =$G$21 -> -505.99902 | H98: =$H$21 -> 2494.001 | I98: =$I$21 -> 2494.001 | J98: =$J$21 -> 2494.001 | K98: =$K$21 -> 2494.001 | L98: =$L$21 -> 2494.001
A99: IRR | B99: =IFERROR(IRR(B98:L98),NA()) -> #N/A
A101: Subsidy | B101: 0.85
A102: Subsidised capex | B102: =$B$12*(1-B101) -> 0
A103: Cashflow | B103: =-B102 -> 0 | C103: =$C$21 -> 2494.001 | D103: =$D$21 -> 2494.001 | E103: =$E$21 -> 2494.001 | F103: =$F$21 -> 2494.001 | G103: =$G$21 -> -505.99902 | H103: =$H$21 -> 2494.001 | I103: =$I$21 -> 2494.001 | J103: =$J$21 -> 2494.001 | K103: =$K$21 -> 2494.001 | L103: =$L$21 -> 2494.001
A104: IRR | B104: =IFERROR(IRR(B103:L103),NA()) -> #N/A
A106: Subsidy | B106: 0.9
A107: Subsidised capex | B107: =$B$12*(1-B106) -> 0
A108: Cashflow | B108: =-B107 -> 0 | C108: =$C$21 -> 2494.001 | D108: =$D$21 -> 2494.001 | E108: =$E$21 -> 2494.001 | F108: =$F$21 -> 2494.001 | G108: =$G$21 -> -505.99902 | H108: =$H$21 -> 2494.001 | I108: =$I$21 -> 2494.001 | J108: =$J$21 -> 2494.001 | K108: =$K$21 -> 2494.001 | L108: =$L$21 -> 2494.001
A109: IRR | B109: =IFERROR(IRR(B108:L108),NA()) -> #N/A
A111: Subsidy | B111: 0.95
A112: Subsidised capex | B112: =$B$12*(1-B111) -> 0
A113: Cashflow | B113: =-B112 -> 0 | C113: =$C$21 -> 2494.001 | D113: =$D$21 -> 2494.001 | E113: =$E$21 -> 2494.001 | F113: =$F$21 -> 2494.001 | G113: =$G$21 -> -505.99902 | H113: =$H$21 -> 2494.001 | I113: =$I$21 -> 2494.001 | J113: =$J$21 -> 2494.001 | K113: =$K$21 -> 2494.001 | L113: =$L$21 -> 2494.001
A114: IRR | B114: =IFERROR(IRR(B113:L113),NA()) -> #N/A
A116: Subsidy | B116: 1
A117: Subsidised capex | B117: =$B$12*(1-B116) -> 0
A118: Cashflow | B118: =-B117 -> 0 | C118: =$C$21 -> 2494.001 | D118: =$D$21 -> 2494.001 | E118: =$E$21 -> 2494.001 | F118: =$F$21 -> 2494.001 | G118: =$G$21 -> -505.99902 | H118: =$H$21 -> 2494.001 | I118: =$I$21 -> 2494.001 | J118: =$J$21 -> 2494.001 | K118: =$K$21 -> 2494.001 | L118: =$L$21 -> 2494.001
A119: IRR | B119: =IFERROR(IRR(B118:L118),NA()) -> #N/A
A122: Subsidy summary
B123: 0.1 | C123: 0.15 | D123: 0.2 | E123: 0.25 | F123: 0.3 | G123: 0.35 | H123: 0.4 | I123: 0.45 | J123: 0.5 | K123: 0.55 | L123: 0.6 | M123: 0.65 | N123: 0.7 | O123: 0.75 | P123: 0.8 | Q123: 0.85 | R123: 0.9 | S123: 0.95 | T123: 1
B124: =B29 -> #N/A | C124: =B34 -> #N/A | D124: =B39 -> #N/A | E124: =B44 -> #N/A | F124: =B49 -> #N/A | G124: =B54 -> #N/A | H124: =B59 -> #N/A | I124: =B64 -> #N/A | J124: =B69 -> #N/A | K124: =B74 -> #N/A | L124: =B79 -> #N/A | M124: =B84 -> #N/A | N124: =B89 -> #N/A | O124: =B94 -> #N/A | P124: =B99 -> #N/A | Q124: =B104 -> #N/A | R124: =B109 -> #N/A | S124: =B114 -> #N/A | T124: =B119 -> #N/A
A125: Min subsidy for DNSP | B125: =LOOKUP('IRR inputs & outputs'!B18, B124:P124, B123:P123) -> #N/A
A126: Min subsidy for CPO | B126: =LOOKUP('IRR inputs & outputs'!B19, B124:P124, B123:P123) -> #N/A

Sheet 22.5% utilisation
A1: Utilisation | B1: 0.225
A2: Hours in year | B2: =24*365 -> 8760
A3: Energy delivered | B3: =B2*B1*'IRR inputs & outputs'!B2*'IRR inputs & outputs'!B3*'IRR inputs & outputs'!$B$7 -> 22114.62 | C3: kWh p.a.
A5: Year | B5: 0 | C5: 1 | D5: 2 | E5: 3 | F5: 4 | G5: 5 | H5: 6 | I5: 7 | J5: 8 | K5: 9 | L5: 10
A6: Income
A7: Charging | C7: =$B$3*'IRR inputs & outputs'!$B$13 -> 9951.579 | D7: =$B$3*'IRR inputs & outputs'!$B$13 -> 9951.579 | E7: =$B$3*'IRR inputs & outputs'!$B$13 -> 9951.579 | F7: =$B$3*'IRR inputs & outputs'!$B$13 -> 9951.579 | G7: =$B$3*'IRR inputs & outputs'!$B$13 -> 9951.579 | H7: =$B$3*'IRR inputs & outputs'!$B$13 -> 9951.579 | I7: =$B$3*'IRR inputs & outputs'!$B$13 -> 9951.579 | J7: =$B$3*'IRR inputs & outputs'!$B$13 -> 9951.579 | ... L7: =$B$3*'IRR inputs & outputs'!$B$13 -> 9951.579
A9: Total income | C9: =SUM(C7:C8) -> 9951.579 | D9: =SUM(D7:D8) -> 9951.579 | E9: =SUM(E7:E8) -> 9951.579 | F9: =SUM(F7:F8) -> 9951.579 | G9: =SUM(G7:G8) -> 9951.579 | H9: =SUM(H7:H8) -> 9951.579 | I9: =SUM(I7:I8) -> 9951.579 | J9: =SUM(J7:J8) -> 9951.579 | ... L9: =SUM(L7:L8) -> 9951.579
A11: Outgoing
A12: Capex | B12: ='IRR inputs & outputs'!B6 -> 0 | G12: ='IRR inputs & outputs'!B15 -> 3000
A13: Site establishment | B13: ='IRR inputs & outputs'!B16 -> 500
A14: Site license | C14: ='IRR inputs & outputs'!$B$17 -> 750 | D14: ='IRR inputs & outputs'!$B$17 -> 750 | E14: ='IRR inputs & outputs'!$B$17 -> 750 | F14: ='IRR inputs & outputs'!$B$17 -> 750 | G14: ='IRR inputs & outputs'!$B$17 -> 750 | H14: ='IRR inputs & outputs'!$B$17 -> 750 | I14: ='IRR inputs & outputs'!$B$17 -> 750 | J14: ='IRR inputs & outputs'!$B$17 -> 750 | ... L14: ='IRR inputs & outputs'!$B$17 -> 750
A15: Maintenance | C15: ='IRR inputs & outputs'!B14 -> 500 | D15: ='IRR inputs & outputs'!B14 -> 500 | E15: ='IRR inputs & outputs'!B14 -> 500 | F15: ='IRR inputs & outputs'!B14 -> 500 | G15: ='IRR inputs & outputs'!B14 -> 500 | H15: ='IRR inputs & outputs'!B14 -> 500 | I15: ='IRR inputs & outputs'!B14 -> 500 | J15: ='IRR inputs & outputs'!B14 -> 500 | K15: ='IRR inputs & outputs'!B14 -> 500 | L15: ='IRR inputs & outputs'!B14 -> 500
A16: Electricity | C16: =(1/'IRR inputs & outputs'!$B$8)*$B$3*'IRR inputs & outputs'!$B$9+'IRR inputs & outputs'!$B$10 -> 4655.7095 | D16: =(1/'IRR inputs & outputs'!$B$8)*$B$3*'IRR inputs & outputs'!$B$9+'IRR inputs & outputs'!$B$10 -> 4655.7095 | E16: =(1/'IRR inputs & outputs'!$B$8)*$B$3*'IRR inputs & outputs'!$B$9+'IRR inputs & outputs'!$B$10 -> 4655.7095 | F16: =(1/'IRR inputs & outputs'!$B$8)*$B$3*'IRR inputs & outputs'!$B$9+'IRR inputs & outputs'!$B$10 -> 4655.7095 | G16: =(1/'IRR inputs & outputs'!$B$8)*$B$3*'IRR inputs & outputs'!$B$9+'IRR inputs & outputs'!$B$10 -> 4655.7095 | H16: =(1/'IRR inputs & outputs'!$B$8)*$B$3*'IRR inputs & outputs'!$B$9+'IRR inputs & outputs'!$B$10 -> 4655.7095 | I16: =(1/'IRR inputs & outputs'!$B$8)*$B$3*'IRR inputs & outputs'!$B$9+'IRR inputs & outputs'!$B$10 -> 4655.7095 | J16: =(1/'IRR inputs & outputs'!$B$8)*$B$3*'IRR inputs & outputs'!$B$9+'IRR inputs & outputs'!$B$10 -> 4655.7095 | ... L16: =(1/'IRR inputs & outputs'!$B$8)*$B$3*'IRR inputs & outputs'!$B$9+'IRR inputs & outputs'!$B$10 -> 4655.7095
A17: Software - fixed | C17: ='IRR inputs & outputs'!$B$12 -> 300 | D17: ='IRR inputs & outputs'!$B$12 -> 300 | E17: ='IRR inputs & outputs'!$B$12 -> 300 | F17: ='IRR inputs & outputs'!$B$12 -> 300 | G17: ='IRR inputs & outputs'!$B$12 -> 300 | H17: ='IRR inputs & outputs'!$B$12 -> 300 | I17: ='IRR inputs & outputs'!$B$12 -> 300 | J17: ='IRR inputs & outputs'!$B$12 -> 300 | ... L17: ='IRR inputs & outputs'!$B$12 -> 300
A18: Software - variable | C18: =$B$3*'IRR inputs & outputs'!$B$11*'IRR inputs & outputs'!$B$13 -> 746.36843 | D18: =$B$3*'IRR inputs & outputs'!$B$11*'IRR inputs & outputs'!$B$13 -> 746.36843 | E18: =$B$3*'IRR inputs & outputs'!$B$11*'IRR inputs & outputs'!$B$13 -> 746.36843 | F18: =$B$3*'IRR inputs & outputs'!$B$11*'IRR inputs & outputs'!$B$13 -> 746.36843 | G18: =$B$3*'IRR inputs & outputs'!$B$11*'IRR inputs & outputs'!$B$13 -> 746.36843 | H18: =$B$3*'IRR inputs & outputs'!$B$11*'IRR inputs & outputs'!$B$13 -> 746.36843 | I18: =$B$3*'IRR inputs & outputs'!$B$11*'IRR inputs & outputs'!$B$13 -> 746.36843 | J18: =$B$3*'IRR inputs & outputs'!$B$11*'IRR inputs & outputs'!$B$13 -> 746.36843 | ... L18: =$B$3*'IRR inputs & outputs'!$B$11*'IRR inputs & outputs'!$B$13 -> 746.36843
A19: Total outgoings | B19: =SUM(B12:B18) -> 500 | C19: =SUM(C12:C18) -> 6952.0779 | D19: =SUM(D12:D18) -> 6952.0779 | E19: =SUM(E12:E18) -> 6952.0779 | F19: =SUM(F12:F18) -> 6952.0779 | G19: =SUM(G12:G18) -> 9952.0779 | H19: =SUM(H12:H18) -> 6952.0779 | I19: =SUM(I12:I18) -> 6952.0779 | ... L19: =SUM(L12:L18) -> 6952.0779
A21: Total | B21: =B9-B19 -> -500 | C21: =C9-C19 -> 2999.5011 | D21: =D9-D19 -> 2999.5011 | E21: =E9-E19 -> 2999.5011 | F21: =F9-F19 -> 2999.5011 | G21: =G9-G19 -> -0.49889868 | H21: =H9-H19 -> 2999.5011 | I21: =I9-I19 -> 2999.5011 | ... L21: =L9-L19 -> 2999.5011
A23: IRR | B23: =IFERROR(IRR(B21:L21),NA()) -> 5.9968565
A25: Subsidy effect
A26: Subsidy | B26: 0.1
A27: Subsidised capex | B27: =$B$12*(1-B26) -> 0
A28: Cashflow | B28: =-B27 -> 0 | C28: =$C$21 -> 2999.5011 | D28: =$D$21 -> 2999.5011 | E28: =$E$21 -> 2999.5011 | F28: =$F$21 -> 2999.5011 | G28: =$G$21 -> -0.49889868 | H28: =$H$21 -> 2999.5011 | I28: =$I$21 -> 2999.5011 | J28: =$J$21 -> 2999.5011 | K28: =$K$21 -> 2999.5011 | L28: =$L$21 -> 2999.5011
A29: IRR | B29: =IFERROR(IRR(B28:L28),NA()) -> #N/A
A31: Subsidy | B31: 0.15
A32: Subsidised capex | B32: =$B$12*(1-B31) -> 0
A33: Cashflow | B33: =-B32 -> 0 | C33: =$C$21 -> 2999.5011 | D33: =$D$21 -> 2999.5011 | E33: =$E$21 -> 2999.5011 | F33: =$F$21 -> 2999.5011 | G33: =$G$21 -> -0.49889868 | H33: =$H$21 -> 2999.5011 | I33: =$I$21 -> 2999.5011 | J33: =$J$21 -> 2999.5011 | K33: =$K$21 -> 2999.5011 | L33: =$L$21 -> 2999.5011
A34: IRR | B34: =IFERROR(IRR(B33:L33),NA()) -> #N/A
A36: Subsidy | B36: 0.2
A37: Subsidised capex | B37: =$B$12*(1-B36) -> 0
A38: Cashflow | B38: =-B37 -> 0 | C38: =$C$21 -> 2999.5011 | D38: =$D$21 -> 2999.5011 | E38: =$E$21 -> 2999.5011 | F38: =$F$21 -> 2999.5011 | G38: =$G$21 -> -0.49889868 | H38: =$H$21 -> 2999.5011 | I38: =$I$21 -> 2999.5011 | J38: =$J$21 -> 2999.5011 | K38: =$K$21 -> 2999.5011 | L38: =$L$21 -> 2999.5011
A39: IRR | B39: =IFERROR(IRR(B38:L38),NA()) -> #N/A
A41: Subsidy | B41: 0.25
A42: Subsidised capex | B42: =$B$12*(1-B41) -> 0
A43: Cashflow | B43: =-B42 -> 0 | C43: =$C$21 -> 2999.5011 | D43: =$D$21 -> 2999.5011 | E43: =$E$21 -> 2999.5011 | F43: =$F$21 -> 2999.5011 | G43: =$G$21 -> -0.49889868 | H43: =$H$21 -> 2999.5011 | I43: =$I$21 -> 2999.5011 | J43: =$J$21 -> 2999.5011 | K43: =$K$21 -> 2999.5011 | L43: =$L$21 -> 2999.5011
A44: IRR | B44: =IFERROR(IRR(B43:L43),NA()) -> #N/A
A46: Subsidy | B46: 0.3
A47: Subsidised capex | B47: =$B$12*(1-B46) -> 0
A48: Cashflow | B48: =-B47 -> 0 | C48: =$C$21 -> 2999.5011 | D48: =$D$21 -> 2999.5011 | E48: =$E$21 -> 2999.5011 | F48: =$F$21 -> 2999.5011 | G48: =$G$21 -> -0.49889868 | H48: =$H$21 -> 2999.5011 | I48: =$I$21 -> 2999.5011 | J48: =$J$21 -> 2999.5011 | K48: =$K$21 -> 2999.5011 | L48: =$L$21 -> 2999.5011
A49: IRR | B49: =IFERROR(IRR(B48:L48),NA()) -> #N/A
A51: Subsidy | B51: 0.35
A52: Subsidised capex | B52: =$B$12*(1-B51) -> 0
A53: Cashflow | B53: =-B52 -> 0 | C53: =$C$21 -> 2999.5011 | D53: =$D$21 -> 2999.5011 | E53: =$E$21 -> 2999.5011 | F53: =$F$21 -> 2999.5011 | G53: =$G$21 -> -0.49889868 | H53: =$H$21 -> 2999.5011 | I53: =$I$21 -> 2999.5011 | J53: =$J$21 -> 2999.5011 | K53: =$K$21 -> 2999.5011 | L53: =$L$21 -> 2999.5011
A54: IRR | B54: =IFERROR(IRR(B53:L53),NA()) -> #N/A
A56: Subsidy | B56: 0.4
A57: Subsidised capex | B57: =$B$12*(1-B56) -> 0
A58: Cashflow | B58: =-B57 -> 0 | C58: =$C$21 -> 2999.5011 | D58: =$D$21 -> 2999.5011 | E58: =$E$21 -> 2999.5011 | F58: =$F$21 -> 2999.5011 | G58: =$G$21 -> -0.49889868 | H58: =$H$21 -> 2999.5011 | I58: =$I$21 -> 2999.5011 | J58: =$J$21 -> 2999.5011 | K58: =$K$21 -> 2999.5011 | L58: =$L$21 -> 2999.5011
A59: IRR | B59: =IFERROR(IRR(B58:L58),NA()) -> #N/A
A61: Subsidy | B61: 0.45
A62: Subsidised capex | B62: =$B$12*(1-B61) -> 0
A63: Cashflow | B63: =-B62 -> 0 | C63: =$C$21 -> 2999.5011 | D63: =$D$21 -> 2999.5011 | E63: =$E$21 -> 2999.5011 | F63: =$F$21 -> 2999.5011 | G63: =$G$21 -> -0.49889868 | H63: =$H$21 -> 2999.5011 | I63: =$I$21 -> 2999.5011 | J63: =$J$21 -> 2999.5011 | K63: =$K$21 -> 2999.5011 | L63: =$L$21 -> 2999.5011
A64: IRR | B64: =IFERROR(IRR(B63:L63),NA()) -> #N/A
A66: Subsidy | B66: 0.5
A67: Subsidised capex | B67: =$B$12*(1-B66) -> 0
A68: Cashflow | B68: =-B67 -> 0 | C68: =$C$21 -> 2999.5011 | D68: =$D$21 -> 2999.5011 | E68: =$E$21 -> 2999.5011 | F68: =$F$21 -> 2999.5011 | G68: =$G$21 -> -0.49889868 | H68: =$H$21 -> 2999.5011 | I68: =$I$21 -> 2999.5011 | J68: =$J$21 -> 2999.5011 | K68: =$K$21 -> 2999.5011 | L68: =$L$21 -> 2999.5011
A69: IRR | B69: =IFERROR(IRR(B68:L68),NA()) -> #N/A
A71: Subsidy | B71: 0.55
A72: Subsidised capex | B72: =$B$12*(1-B71) -> 0
A73: Cashflow | B73: =-B72 -> 0 | C73: =$C$21 -> 2999.5011 | D73: =$D$21 -> 2999.5011 | E73: =$E$21 -> 2999.5011 | F73: =$F$21 -> 2999.5011 | G73: =$G$21 -> -0.49889868 | H73: =$H$21 -> 2999.5011 | I73: =$I$21 -> 2999.5011 | J73: =$J$21 -> 2999.5011 | K73: =$K$21 -> 2999.5011 | L73: =$L$21 -> 2999.5011
A74: IRR | B74: =IFERROR(IRR(B73:L73),NA()) -> #N/A
A76: Subsidy | B76: 0.6
A77: Subsidised capex | B77: =$B$12*(1-B76) -> 0
A78: Cashflow | B78: =-B77 -> 0 | C78: =$C$21 -> 2999.5011 | D78: =$D$21 -> 2999.5011 | E78: =$E$21 -> 2999.5011 | F78: =$F$21 -> 2999.5011 | G78: =$G$21 -> -0.49889868 | H78: =$H$21 -> 2999.5011 | I78: =$I$21 -> 2999.5011 | J78: =$J$21 -> 2999.5011 | K78: =$K$21 -> 2999.5011 | L78: =$L$21 -> 2999.5011
A79: IRR | B79: =IFERROR(IRR(B78:L78),NA()) -> #N/A
A81: Subsidy | B81: 0.65
A82: Subsidised capex | B82: =$B$12*(1-B81) -> 0
A83: Cashflow | B83: =-B82 -> 0 | C83: =$C$21 -> 2999.5011 | D83: =$D$21 -> 2999.5011 | E83: =$E$21 -> 2999.5011 | F83: =$F$21 -> 2999.5011 | G83: =$G$21 -> -0.49889868 | H83: =$H$21 -> 2999.5011 | I83: =$I$21 -> 2999.5011 | J83: =$J$21 -> 2999.5011 | K83: =$K$21 -> 2999.5011 | L83: =$L$21 -> 2999.5011
A84: IRR | B84: =IFERROR(IRR(B83:L83),NA()) -> #N/A
A86: Subsidy | B86: 0.7
A87: Subsidised capex | B87: =$B$12*(1-B86) -> 0
A88: Cashflow | B88: =-B87 -> 0 | C88: =$C$21 -> 2999.5011 | D88: =$D$21 -> 2999.5011 | E88: =$E$21 -> 2999.5011 | F88: =$F$21 -> 2999.5011 | G88: =$G$21 -> -0.49889868 | H88: =$H$21 -> 2999.5011 | I88: =$I$21 -> 2999.5011 | J88: =$J$21 -> 2999.5011 | K88: =$K$21 -> 2999.5011 | L88: =$L$21 -> 2999.5011
A89: IRR | B89: =IFERROR(IRR(B88:L88),NA()) -> #N/A
A91: Subsidy | B91: 0.75
A92: Subsidised capex | B92: =$B$12*(1-B91) -> 0
A93: Cashflow | B93: =-B92 -> 0 | C93: =$C$21 -> 2999.5011 | D93: =$D$21 -> 2999.5011 | E93: =$E$21 -> 2999.5011 | F93: =$F$21 -> 2999.5011 | G93: =$G$21 -> -0.49889868 | H93: =$H$21 -> 2999.5011 | I93: =$I$21 -> 2999.5011 | J93: =$J$21 -> 2999.5011 | K93: =$K$21 -> 2999.5011 | L93: =$L$21 -> 2999.5011
A94: IRR | B94: =IFERROR(IRR(B93:L93),NA()) -> #N/A
A96: Subsidy | B96: 0.8
A97: Subsidised capex | B97: =$B$12*(1-B96) -> 0
A98: Cashflow | B98: =-B97 -> 0 | C98: =$C$21 -> 2999.5011 | D98: =$D$21 -> 2999.5011 | E98: =$E$21 -> 2999.5011 | F98: =$F$21 -> 2999.5011 | G98: =$G$21 -> -0.49889868 | H98: =$H$21 -> 2999.5011 | I98: =$I$21 -> 2999.5011 | J98: =$J$21 -> 2999.5011 | K98: =$K$21 -> 2999.5011 | L98: =$L$21 -> 2999.5011
A99: IRR | B99: =IFERROR(IRR(B98:L98),NA()) -> #N/A
A101: Subsidy | B101: 0.85
A102: Subsidised capex | B102: =$B$12*(1-B101) -> 0
A103: Cashflow | B103: =-B102 -> 0 | C103: =$C$21 -> 2999.5011 | D103: =$D$21 -> 2999.5011 | E103: =$E$21 -> 2999.5011 | F103: =$F$21 -> 2999.5011 | G103: =$G$21 -> -0.49889868 | H103: =$H$21 -> 2999.5011 | I103: =$I$21 -> 2999.5011 | J103: =$J$21 -> 2999.5011 | K103: =$K$21 -> 2999.5011 | L103: =$L$21 -> 2999.5011
A104: IRR | B104: =IFERROR(IRR(B103:L103),NA()) -> #N/A
A106: Subsidy | B106: 0.9
A107: Subsidised capex | B107: =$B$12*(1-B106) -> 0
A108: Cashflow | B108: =-B107 -> 0 | C108: =$C$21 -> 2999.5011 | D108: =$D$21 -> 2999.5011 | E108: =$E$21 -> 2999.5011 | F108: =$F$21 -> 2999.5011 | G108: =$G$21 -> -0.49889868 | H108: =$H$21 -> 2999.5011 | I108: =$I$21 -> 2999.5011 | J108: =$J$21 -> 2999.5011 | K108: =$K$21 -> 2999.5011 | L108: =$L$21 -> 2999.5011
A109: IRR | B109: =IFERROR(IRR(B108:L108),NA()) -> #N/A
A111: Subsidy | B111: 0.95
A112: Subsidised capex | B112: =$B$12*(1-B111) -> 0
A113: Cashflow | B113: =-B112 -> 0 | C113: =$C$21 -> 2999.5011 | D113: =$D$21 -> 2999.5011 | E113: =$E$21 -> 2999.5011 | F113: =$F$21 -> 2999.5011 | G113: =$G$21 -> -0.49889868 | H113: =$H$21 -> 2999.5011 | I113: =$I$21 -> 2999.5011 | J113: =$J$21 -> 2999.5011 | K113: =$K$21 -> 2999.5011 | L113: =$L$21 -> 2999.5011
A114: IRR | B114: =IFERROR(IRR(B113:L113),NA()) -> #N/A
A116: Subsidy | B116: 1
A117: Subsidised capex | B117: =$B$12*(1-B116) -> 0
A118: Cashflow | B118: =-B117 -> 0 | C118: =$C$21 -> 2999.5011 | D118: =$D$21 -> 2999.5011 | E118: =$E$21 -> 2999.5011 | F118: =$F$21 -> 2999.5011 | G118: =$G$21 -> -0.49889868 | H118: =$H$21 -> 2999.5011 | I118: =$I$21 -> 2999.5011 | J118: =$J$21 -> 2999.5011 | K118: =$K$21 -> 2999.5011 | L118: =$L$21 -> 2999.5011
A119: IRR | B119: =IFERROR(IRR(B118:L118),NA()) -> #N/A
A122: Subsidy summary
B123: 0.1 | C123: 0.15 | D123: 0.2 | E123: 0.25 | F123: 0.3 | G123: 0.35 | H123: 0.4 | I123: 0.45 | J123: 0.5 | K123: 0.55 | L123: 0.6 | M123: 0.65 | N123: 0.7 | O123: 0.75 | P123: 0.8 | Q123: 0.85 | R123: 0.9 | S123: 0.95 | T123: 1
B124: =B29 -> #N/A | C124: =B34 -> #N/A | D124: =B39 -> #N/A | E124: =B44 -> #N/A | F124: =B49 -> #N/A | G124: =B54 -> #N/A | H124: =B59 -> #N/A | I124: =B64 -> #N/A | J124: =B69 -> #N/A | K124: =B74 -> #N/A | L124: =B79 -> #N/A | M124: =B84 -> #N/A | N124: =B89 -> #N/A | O124: =B94 -> #N/A | P124: =B99 -> #N/A | Q124: =B104 -> #N/A | R124: =B109 -> #N/A | S124: =B114 -> #N/A | T124: =B119 -> #N/A
A125: Min subsidy for DNSP | B125: =LOOKUP('IRR inputs & outputs'!B18, B124:P124, B123:P123) -> #N/A
A126: Min subsidy for CPO | B126: =LOOKUP('IRR inputs & outputs'!B19, B124:P124, B123:P123) -> #N/A

Sheet 25% utilisation
A1: Utilisation | B1: 0.25
A2: Hours in year | B2: =24*365 -> 8760
A3: Energy delivered | B3: =B2*B1*'IRR inputs & outputs'!B2*'IRR inputs & outputs'!B3*'IRR inputs & outputs'!$B$7 -> 24571.8 | C3: kWh p.a.
A5: Year | B5: 0 | C5: 1 | D5: 2 | E5: 3 | F5: 4 | G5: 5 | H5: 6 | I5: 7 | J5: 8 | K5: 9 | L5: 10
A6: Income
A7: Charging | C7: =$B$3*'IRR inputs & outputs'!$B$13 -> 11057.31 | D7: =$B$3*'IRR inputs & outputs'!$B$13 -> 11057.31 | E7: =$B$3*'IRR inputs & outputs'!$B$13 -> 11057.31 | F7: =$B$3*'IRR inputs & outputs'!$B$13 -> 11057.31 | G7: =$B$3*'IRR inputs & outputs'!$B$13 -> 11057.31 | H7: =$B$3*'IRR inputs & outputs'!$B$13 -> 11057.31 | I7: =$B$3*'IRR inputs & outputs'!$B$13 -> 11057.31 | J7: =$B$3*'IRR inputs & outputs'!$B$13 -> 11057.31 | ... L7: =$B$3*'IRR inputs & outputs'!$B$13 -> 11057.31
A9: Total income | C9: =SUM(C7:C8) -> 11057.31 | D9: =SUM(D7:D8) -> 11057.31 | E9: =SUM(E7:E8) -> 11057.31 | F9: =SUM(F7:F8) -> 11057.31 | G9: =SUM(G7:G8) -> 11057.31 | H9: =SUM(H7:H8) -> 11057.31 | I9: =SUM(I7:I8) -> 11057.31 | J9: =SUM(J7:J8) -> 11057.31 | ... L9: =SUM(L7:L8) -> 11057.31
A11: Outgoing
A12: Capex | B12: ='IRR inputs & outputs'!B6 -> 0 | G12: ='IRR inputs & outputs'!B15 -> 3000
A13: Site establishment | B13: ='IRR inputs & outputs'!B16 -> 500
A14: Site license | C14: ='IRR inputs & outputs'!$B$17 -> 750 | D14: ='IRR inputs & outputs'!$B$17 -> 750 | E14: ='IRR inputs & outputs'!$B$17 -> 750 | F14: ='IRR inputs & outputs'!$B$17 -> 750 | G14: ='IRR inputs & outputs'!$B$17 -> 750 | H14: ='IRR inputs & outputs'!$B$17 -> 750 | I14: ='IRR inputs & outputs'!$B$17 -> 750 | J14: ='IRR inputs & outputs'!$B$17 -> 750 | ... L14: ='IRR inputs & outputs'!$B$17 -> 750
A15: Maintenance | C15: ='IRR inputs & outputs'!B14 -> 500 | D15: ='IRR inputs & outputs'!B14 -> 500 | E15: ='IRR inputs & outputs'!B14 -> 500 | F15: ='IRR inputs & outputs'!B14 -> 500 | G15: ='IRR inputs & outputs'!B14 -> 500 | H15: ='IRR inputs & outputs'!B14 -> 500 | I15: ='IRR inputs & outputs'!B14 -> 500 | J15: ='IRR inputs & outputs'!B14 -> 500 | K15: ='IRR inputs & outputs'!B14 -> 500 | L15: ='IRR inputs & outputs'!B14 -> 500
A16: Electricity | C16: =(1/'IRR inputs & outputs'!$B$8)*$B$3*'IRR inputs & outputs'!$B$9+'IRR inputs & outputs'!$B$10 -> 5173.0105 | D16: =(1/'IRR inputs & outputs'!$B$8)*$B$3*'IRR inputs & outputs'!$B$9+'IRR inputs & outputs'!$B$10 -> 5173.0105 | E16: =(1/'IRR inputs & outputs'!$B$8)*$B$3*'IRR inputs & outputs'!$B$9+'IRR inputs & outputs'!$B$10 -> 5173.0105 | F16: =(1/'IRR inputs & outputs'!$B$8)*$B$3*'IRR inputs & outputs'!$B$9+'IRR inputs & outputs'!$B$10 -> 5173.0105 | G16: =(1/'IRR inputs & outputs'!$B$8)*$B$3*'IRR inputs & outputs'!$B$9+'IRR inputs & outputs'!$B$10 -> 5173.0105 | H16: =(1/'IRR inputs & outputs'!$B$8)*$B$3*'IRR inputs & outputs'!$B$9+'IRR inputs & outputs'!$B$10 -> 5173.0105 | I16: =(1/'IRR inputs & outputs'!$B$8)*$B$3*'IRR inputs & outputs'!$B$9+'IRR inputs & outputs'!$B$10 -> 5173.0105 | J16: =(1/'IRR inputs & outputs'!$B$8)*$B$3*'IRR inputs & outputs'!$B$9+'IRR inputs & outputs'!$B$10 -> 5173.0105 | ... L16: =(1/'IRR inputs & outputs'!$B$8)*$B$3*'IRR inputs & outputs'!$B$9+'IRR inputs & outputs'!$B$10 -> 5173.0105
A17: Software - fixed | C17: ='IRR inputs & outputs'!$B$12 -> 300 | D17: ='IRR inputs & outputs'!$B$12 -> 300 | E17: ='IRR inputs & outputs'!$B$12 -> 300 | F17: ='IRR inputs & outputs'!$B$12 -> 300 | G17: ='IRR inputs & outputs'!$B$12 -> 300 | H17: ='IRR inputs & outputs'!$B$12 -> 300 | I17: ='IRR inputs & outputs'!$B$12 -> 300 | J17: ='IRR inputs & outputs'!$B$12 -> 300 | ... L17: ='IRR inputs & outputs'!$B$12 -> 300
A18: Software - variable | C18: =$B$3*'IRR inputs & outputs'!$B$11*'IRR inputs & outputs'!$B$13 -> 829.29825 | D18: =$B$3*'IRR inputs & outputs'!$B$11*'IRR inputs & outputs'!$B$13 -> 829.29825 | E18: =$B$3*'IRR inputs & outputs'!$B$11*'IRR inputs & outputs'!$B$13 -> 829.29825 | F18: =$B$3*'IRR inputs & outputs'!$B$11*'IRR inputs & outputs'!$B$13 -> 829.29825 | G18: =$B$3*'IRR inputs & outputs'!$B$11*'IRR inputs & outputs'!$B$13 -> 829.29825 | H18: =$B$3*'IRR inputs & outputs'!$B$11*'IRR inputs & outputs'!$B$13 -> 829.29825 | I18: =$B$3*'IRR inputs & outputs'!$B$11*'IRR inputs & outputs'!$B$13 -> 829.29825 | J18: =$B$3*'IRR inputs & outputs'!$B$11*'IRR inputs & outputs'!$B$13 -> 829.29825 | ... L18: =$B$3*'IRR inputs & outputs'!$B$11*'IRR inputs & outputs'!$B$13 -> 829.29825
A19: Total outgoings | B19: =SUM(B12:B18) -> 500 | C19: =SUM(C12:C18) -> 7552.3088 | D19: =SUM(D12:D18) -> 7552.3088 | E19: =SUM(E12:E18) -> 7552.3088 | F19: =SUM(F12:F18) -> 7552.3088 | G19: =SUM(G12:G18) -> 10552.309 | H19: =SUM(H12:H18) -> 7552.3088 | I19: =SUM(I12:I18) -> 7552.3088 | ... L19: =SUM(L12:L18) -> 7552.3088
A21: Total | B21: =B9-B19 -> -500 | C21: =C9-C19 -> 3505.0012 | D21: =D9-D19 -> 3505.0012 | E21: =E9-E19 -> 3505.0012 | F21: =F9-F19 -> 3505.0012 | G21: =G9-G19 -> 505.00122 | H21: =H9-H19 -> 3505.0012 | I21: =I9-I19 -> 3505.0012 | ... L21: =L9-L19 -> 3505.0012
A23: IRR | B23: =IFERROR(IRR(B21:L21),NA()) -> 7.0087261
A25: Subsidy effect
A26: Subsidy | B26: 0.1
A27: Subsidised capex | B27: =$B$12*(1-B26) -> 0
A28: Cashflow | B28: =-B27 -> 0 | C28: =$C$21 -> 3505.0012 | D28: =$D$21 -> 3505.0012 | E28: =$E$21 -> 3505.0012 | F28: =$F$21 -> 3505.0012 | G28: =$G$21 -> 505.00122 | H28: =$H$21 -> 3505.0012 | I28: =$I$21 -> 3505.0012 | J28: =$J$21 -> 3505.0012 | K28: =$K$21 -> 3505.0012 | L28: =$L$21 -> 3505.0012
A29: IRR | B29: =IFERROR(IRR(B28:L28),NA()) -> #N/A
A31: Subsidy | B31: 0.15
A32: Subsidised capex | B32: =$B$12*(1-B31) -> 0
A33: Cashflow | B33: =-B32 -> 0 | C33: =$C$21 -> 3505.0012 | D33: =$D$21 -> 3505.0012 | E33: =$E$21 -> 3505.0012 | F33: =$F$21 -> 3505.0012 | G33: =$G$21 -> 505.00122 | H33: =$H$21 -> 3505.0012 | I33: =$I$21 -> 3505.0012 | J33: =$J$21 -> 3505.0012 | K33: =$K$21 -> 3505.0012 | L33: =$L$21 -> 3505.0012
A34: IRR | B34: =IFERROR(IRR(B33:L33),NA()) -> #N/A
A36: Subsidy | B36: 0.2
A37: Subsidised capex | B37: =$B$12*(1-B36) -> 0
A38: Cashflow | B38: =-B37 -> 0 | C38: =$C$21 -> 3505.0012 | D38: =$D$21 -> 3505.0012 | E38: =$E$21 -> 3505.0012 | F38: =$F$21 -> 3505.0012 | G38: =$G$21 -> 505.00122 | H38: =$H$21 -> 3505.0012 | I38: =$I$21 -> 3505.0012 | J38: =$J$21 -> 3505.0012 | K38: =$K$21 -> 3505.0012 | L38: =$L$21 -> 3505.0012
A39: IRR | B39: =IFERROR(IRR(B38:L38),NA()) -> #N/A
A41: Subsidy | B41: 0.25
A42: Subsidised capex | B42: =$B$12*(1-B41) -> 0
A43: Cashflow | B43: =-B42 -> 0 | C43: =$C$21 -> 3505.0012 | D43: =$D$21 -> 3505.0012 | E43: =$E$21 -> 3505.0012 | F43: =$F$21 -> 3505.0012 | G43: =$G$21 -> 505.00122 | H43: =$H$21 -> 3505.0012 | I43: =$I$21 -> 3505.0012 | J43: =$J$21 -> 3505.0012 | K43: =$K$21 -> 3505.0012 | L43: =$L$21 -> 3505.0012
A44: IRR | B44: =IFERROR(IRR(B43:L43),NA()) -> #N/A
A46: Subsidy | B46: 0.3
A47: Subsidised capex | B47: =$B$12*(1-B46) -> 0
A48: Cashflow | B48: =-B47 -> 0 | C48: =$C$21 -> 3505.0012 | D48: =$D$21 -> 3505.0012 | E48: =$E$21 -> 3505.0012 | F48: =$F$21 -> 3505.0012 | G48: =$G$21 -> 505.00122 | H48: =$H$21 -> 3505.0012 | I48: =$I$21 -> 3505.0012 | J48: =$J$21 -> 3505.0012 | K48: =$K$21 -> 3505.0012 | L48: =$L$21 -> 3505.0012
A49: IRR | B49: =IFERROR(IRR(B48:L48),NA()) -> #N/A
A51: Subsidy | B51: 0.35
A52: Subsidised capex | B52: =$B$12*(1-B51) -> 0
A53: Cashflow | B53: =-B52 -> 0 | C53: =$C$21 -> 3505.0012 | D53: =$D$21 -> 3505.0012 | E53: =$E$21 -> 3505.0012 | F53: =$F$21 -> 3505.0012 | G53: =$G$21 -> 505.00122 | H53: =$H$21 -> 3505.0012 | I53: =$I$21 -> 3505.0012 | J53: =$J$21 -> 3505.0012 | K53: =$K$21 -> 3505.0012 | L53: =$L$21 -> 3505.0012
A54: IRR | B54: =IFERROR(IRR(B53:L53),NA()) -> #N/A
A56: Subsidy | B56: 0.4
A57: Subsidised capex | B57: =$B$12*(1-B56) -> 0
A58: Cashflow | B58: =-B57 -> 0 | C58: =$C$21 -> 3505.0012 | D58: =$D$21 -> 3505.0012 | E58: =$E$21 -> 3505.0012 | F58: =$F$21 -> 3505.0012 | G58: =$G$21 -> 505.00122 | H58: =$H$21 -> 3505.0012 | I58: =$I$21 -> 3505.0012 | J58: =$J$21 -> 3505.0012 | K58: =$K$21 -> 3505.0012 | L58: =$L$21 -> 3505.0012
A59: IRR | B59: =IFERROR(IRR(B58:L58),NA()) -> #N/A
A61: Subsidy | B61: 0.45
A62: Subsidised capex | B62: =$B$12*(1-B61) -> 0
A63: Cashflow | B63: =-B62 -> 0 | C63: =$C$21 -> 3505.0012 | D63: =$D$21 -> 3505.0012 | E63: =$E$21 -> 3505.0012 | F63: =$F$21 -> 3505.0012 | G63: =$G$21 -> 505.00122 | H63: =$H$21 -> 3505.0012 | I63: =$I$21 -> 3505.0012 | J63: =$J$21 -> 3505.0012 | K63: =$K$21 -> 3505.0012 | L63: =$L$21 -> 3505.0012
A64: IRR | B64: =IFERROR(IRR(B63:L63),NA()) -> #N/A
A66: Subsidy | B66: 0.5
A67: Subsidised capex | B67: =$B$12*(1-B66) -> 0
A68: Cashflow | B68: =-B67 -> 0 | C68: =$C$21 -> 3505.0012 | D68: =$D$21 -> 3505.0012 | E68: =$E$21 -> 3505.0012 | F68: =$F$21 -> 3505.0012 | G68: =$G$21 -> 505.00122 | H68: =$H$21 -> 3505.0012 | I68: =$I$21 -> 3505.0012 | J68: =$J$21 -> 3505.0012 | K68: =$K$21 -> 3505.0012 | L68: =$L$21 -> 3505.0012
A69: IRR | B69: =IFERROR(IRR(B68:L68),NA()) -> #N/A
A71: Subsidy | B71: 0.55
A72: Subsidised capex | B72: =$B$12*(1-B71) -> 0
A73: Cashflow | B73: =-B72 -> 0 | C73: =$C$21 -> 3505.0012 | D73: =$D$21 -> 3505.0012 | E73: =$E$21 -> 3505.0012 | F73: =$F$21 -> 3505.0012 | G73: =$G$21 -> 505.00122 | H73: =$H$21 -> 3505.0012 | I73: =$I$21 -> 3505.0012 | J73: =$J$21 -> 3505.0012 | K73: =$K$21 -> 3505.0012 | L73: =$L$21 -> 3505.0012
A74: IRR | B74: =IFERROR(IRR(B73:L73),NA()) -> #N/A
A76: Subsidy | B76: 0.6
A77: Subsidised capex | B77: =$B$12*(1-B76) -> 0
A78: Cashflow | B78: =-B77 -> 0 | C78: =$C$21 -> 3505.0012 | D78: =$D$21 -> 3505.0012 | E78: =$E$21 -> 3505.0012 | F78: =$F$21 -> 3505.0012 | G78: =$G$21 -> 505.00122 | H78: =$H$21 -> 3505.0012 | I78: =$I$21 -> 3505.0012 | J78: =$J$21 -> 3505.0012 | K78: =$K$21 -> 3505.0012 | L78: =$L$21 -> 3505.0012
A79: IRR | B79: =IFERROR(IRR(B78:L78),NA()) -> #N/A
A81: Subsidy | B81: 0.65
A82: Subsidised capex | B82: =$B$12*(1-B81) -> 0
A83: Cashflow | B83: =-B82 -> 0 | C83: =$C$21 -> 3505.0012 | D83: =$D$21 -> 3505.0012 | E83: =$E$21 -> 3505.0012 | F83: =$F$21 -> 3505.0012 | G83: =$G$21 -> 505.00122 | H83: =$H$21 -> 3505.0012 | I83: =$I$21 -> 3505.0012 | J83: =$J$21 -> 3505.0012 | K83: =$K$21 -> 3505.0012 | L83: =$L$21 -> 3505.0012
A84: IRR | B84: =IFERROR(IRR(B83:L83),NA()) -> #N/A
A86: Subsidy | B86: 0.7
A87: Subsidised capex | B87: =$B$12*(1-B86) -> 0
A88: Cashflow | B88: =-B87 -> 0 | C88: =$C$21 -> 3505.0012 | D88: =$D$21 -> 3505.0012 | E88: =$E$21 -> 3505.0012 | F88: =$F$21 -> 3505.0012 | G88: =$G$21 -> 505.00122 | H88: =$H$21 -> 3505.0012 | I88: =$I$21 -> 3505.0012 | J88: =$J$21 -> 3505.0012 | K88: =$K$21 -> 3505.0012 | L88: =$L$21 -> 3505.0012
A89: IRR | B89: =IFERROR(IRR(B88:L88),NA()) -> #N/A
A91: Subsidy | B91: 0.75
A92: Subsidised capex | B92: =$B$12*(1-B91) -> 0
A93: Cashflow | B93: =-B92 -> 0 | C93: =$C$21 -> 3505.0012 | D93: =$D$21 -> 3505.0012 | E93: =$E$21 -> 3505.0012 | F93: =$F$21 -> 3505.0012 | G93: =$G$21 -> 505.00122 | H93: =$H$21 -> 3505.0012 | I93: =$I$21 -> 3505.0012 | J93: =$J$21 -> 3505.0012 | K93: =$K$21 -> 3505.0012 | L93: =$L$21 -> 3505.0012
A94: IRR | B94: =IFERROR(IRR(B93:L93),NA()) -> #N/A
A96: Subsidy | B96: 0.8
A97: Subsidised capex | B97: =$B$12*(1-B96) -> 0
A98: Cashflow | B98: =-B97 -> 0 | C98: =$C$21 -> 3505.0012 | D98: =$D$21 -> 3505.0012 | E98: =$E$21 -> 3505.0012 | F98: =$F$21 -> 3505.0012 | G98: =$G$21 -> 505.00122 | H98: =$H$21 -> 3505.0012 | I98: =$I$21 -> 3505.0012 | J98: =$J$21 -> 3505.0012 | K98: =$K$21 -> 3505.0012 | L98: =$L$21 -> 3505.0012
A99: IRR | B99: =IFERROR(IRR(B98:L98),NA()) -> #N/A
A101: Subsidy | B101: 0.85
A102: Subsidised capex | B102: =$B$12*(1-B101) -> 0
A103: Cashflow | B103: =-B102 -> 0 | C103: =$C$21 -> 3505.0012 | D103: =$D$21 -> 3505.0012 | E103: =$E$21 -> 3505.0012 | F103: =$F$21 -> 3505.0012 | G103: =$G$21 -> 505.00122 | H103: =$H$21 -> 3505.0012 | I103: =$I$21 -> 3505.0012 | J103: =$J$21 -> 3505.0012 | K103: =$K$21 -> 3505.0012 | L103: =$L$21 -> 3505.0012
A104: IRR | B104: =IFERROR(IRR(B103:L103),NA()) -> #N/A
A106: Subsidy | B106: 0.9
A107: Subsidised capex | B107: =$B$12*(1-B106) -> 0
A108: Cashflow | B108: =-B107 -> 0 | C108: =$C$21 -> 3505.0012 | D108: =$D$21 -> 3505.0012 | E108: =$E$21 -> 3505.0012 | F108: =$F$21 -> 3505.0012 | G108: =$G$21 -> 505.00122 | H108: =$H$21 -> 3505.0012 | I108: =$I$21 -> 3505.0012 | J108: =$J$21 -> 3505.0012 | K108: =$K$21 -> 3505.0012 | L108: =$L$21 -> 3505.0012
A109: IRR | B109: =IFERROR(IRR(B108:L108),NA()) -> #N/A
A111: Subsidy | B111: 0.95
A112: Subsidised capex | B112: =$B$12*(1-B111) -> 0
A113: Cashflow | B113: =-B112 -> 0 | C113: =$C$21 -> 3505.0012 | D113: =$D$21 -> 3505.0012 | E113: =$E$21 -> 3505.0012 | F113: =$F$21 -> 3505.0012 | G113: =$G$21 -> 505.00122 | H113: =$H$21 -> 3505.0012 | I113: =$I$21 -> 3505.0012 | J113: =$J$21 -> 3505.0012 | K113: =$K$21 -> 3505.0012 | L113: =$L$21 -> 3505.0012
A114: IRR | B114: =IFERROR(IRR(B113:L113),NA()) -> #N/A
A116: Subsidy | B116: 1
A117: Subsidised capex | B117: =$B$12*(1-B116) -> 0
A118: Cashflow | B118: =-B117 -> 0 | C118: =$C$21 -> 3505.0012 | D118: =$D$21 -> 3505.0012 | E118: =$E$21 -> 3505.0012 | F118: =$F$21 -> 3505.0012 | G118: =$G$21 -> 505.00122 | H118: =$H$21 -> 3505.0012 | I118: =$I$21 -> 3505.0012 | J118: =$J$21 -> 3505.0012 | K118: =$K$21 -> 3505.0012 | L118: =$L$21 -> 3505.0012
A119: IRR | B119: =IFERROR(IRR(B118:L118),NA()) -> #N/A
A122: Subsidy summary
B123: 0.1 | C123: 0.15 | D123: 0.2 | E123: 0.25 | F123: 0.3 | G123: 0.35 | H123: 0.4 | I123: 0.45 | J123: 0.5 | K123: 0.55 | L123: 0.6 | M123: 0.65 | N123: 0.7 | O123: 0.75 | P123: 0.8 | Q123: 0.85 | R123: 0.9 | S123: 0.95 | T123: 1
B124: =B29 -> #N/A | C124: =B34 -> #N/A | D124: =B39 -> #N/A | E124: =B44 -> #N/A | F124: =B49 -> #N/A | G124: =B54 -> #N/A | H124: =B59 -> #N/A | I124: =B64 -> #N/A | J124: =B69 -> #N/A | K124: =B74 -> #N/A | L124: =B79 -> #N/A | M124: =B84 -> #N/A | N124: =B89 -> #N/A | O124: =B94 -> #N/A | P124: =B99 -> #N/A | Q124: =B104 -> #N/A | R124: =B109 -> #N/A | S124: =B114 -> #N/A | T124: =B119 -> #N/A
A125: Min subsidy for DNSP | B125: =LOOKUP('IRR inputs & outputs'!B18, B124:P124, B123:P123) -> #N/A
A126: Min subsidy for CPO | B126: =LOOKUP('IRR inputs & outputs'!B19, B124:P124, B123:P123) -> #N/A

Sheet 30% utilisation
A1: Utilisation | B1: 0.3
A2: Hours in year | B2: =24*365 -> 8760
A3: Energy delivered | B3: =B2*B1*'IRR inputs & outputs'!B2*'IRR inputs & outputs'!B3*'IRR inputs & outputs'!$B$7 -> 29486.16 | C3: kWh p.a.
A5: Year | B5: 0 | C5: 1 | D5: 2 | E5: 3 | F5: 4 | G5: 5 | H5: 6 | I5: 7 | J5: 8 | K5: 9 | L5: 10
A6: Income
A7: Charging | C7: =$B$3*'IRR inputs & outputs'!$B$13 -> 13268.772 | D7: =$B$3*'IRR inputs & outputs'!$B$13 -> 13268.772 | E7: =$B$3*'IRR inputs & outputs'!$B$13 -> 13268.772 | F7: =$B$3*'IRR inputs & outputs'!$B$13 -> 13268.772 | G7: =$B$3*'IRR inputs & outputs'!$B$13 -> 13268.772 | H7: =$B$3*'IRR inputs & outputs'!$B$13 -> 13268.772 | I7: =$B$3*'IRR inputs & outputs'!$B$13 -> 13268.772 | J7: =$B$3*'IRR inputs & outputs'!$B$13 -> 13268.772 | ... L7: =$B$3*'IRR inputs & outputs'!$B$13 -> 13268.772
A9: Total income | C9: =SUM(C7:C8) -> 13268.772 | D9: =SUM(D7:D8) -> 13268.772 | E9: =SUM(E7:E8) -> 13268.772 | F9: =SUM(F7:F8) -> 13268.772 | G9: =SUM(G7:G8) -> 13268.772 | H9: =SUM(H7:H8) -> 13268.772 | I9: =SUM(I7:I8) -> 13268.772 | J9: =SUM(J7:J8) -> 13268.772 | ... L9: =SUM(L7:L8) -> 13268.772
A11: Outgoing
A12: Capex | B12: ='IRR inputs & outputs'!B6 -> 0 | G12: ='IRR inputs & outputs'!B15 -> 3000
A13: Site establishment | B13: ='IRR inputs & outputs'!B16 -> 500
A14: Site license | C14: ='IRR inputs & outputs'!$B$17 -> 750 | D14: ='IRR inputs & outputs'!$B$17 -> 750 | E14: ='IRR inputs & outputs'!$B$17 -> 750 | F14: ='IRR inputs & outputs'!$B$17 -> 750 | G14: ='IRR inputs & outputs'!$B$17 -> 750 | H14: ='IRR inputs & outputs'!$B$17 -> 750 | I14: ='IRR inputs & outputs'!$B$17 -> 750 | J14: ='IRR inputs & outputs'!$B$17 -> 750 | ... L14: ='IRR inputs & outputs'!$B$17 -> 750
A15: Maintenance | C15: ='IRR inputs & outputs'!B14 -> 500 | D15: ='IRR inputs & outputs'!B14 -> 500 | E15: ='IRR inputs & outputs'!B14 -> 500 | F15: ='IRR inputs & outputs'!B14 -> 500 | G15: ='IRR inputs & outputs'!B14 -> 500 | H15: ='IRR inputs & outputs'!B14 -> 500 | I15: ='IRR inputs & outputs'!B14 -> 500 | J15: ='IRR inputs & outputs'!B14 -> 500 | K15: ='IRR inputs & outputs'!B14 -> 500 | L15: ='IRR inputs & outputs'!B14 -> 500
A16: Electricity | C16: =(1/'IRR inputs & outputs'!$B$8)*$B$3*'IRR inputs & outputs'!$B$9+'IRR inputs & outputs'!$B$10 -> 6207.6126 | D16: =(1/'IRR inputs & outputs'!$B$8)*$B$3*'IRR inputs & outputs'!$B$9+'IRR inputs & outputs'!$B$10 -> 6207.6126 | E16: =(1/'IRR inputs & outputs'!$B$8)*$B$3*'IRR inputs & outputs'!$B$9+'IRR inputs & outputs'!$B$10 -> 6207.6126 | F16: =(1/'IRR inputs & outputs'!$B$8)*$B$3*'IRR inputs & outputs'!$B$9+'IRR inputs & outputs'!$B$10 -> 6207.6126 | G16: =(1/'IRR inputs & outputs'!$B$8)*$B$3*'IRR inputs & outputs'!$B$9+'IRR inputs & outputs'!$B$10 -> 6207.6126 | H16: =(1/'IRR inputs & outputs'!$B$8)*$B$3*'IRR inputs & outputs'!$B$9+'IRR inputs & outputs'!$B$10 -> 6207.6126 | I16: =(1/'IRR inputs & outputs'!$B$8)*$B$3*'IRR inputs & outputs'!$B$9+'IRR inputs & outputs'!$B$10 -> 6207.6126 | J16: =(1/'IRR inputs & outputs'!$B$8)*$B$3*'IRR inputs & outputs'!$B$9+'IRR inputs & outputs'!$B$10 -> 6207.6126 | ... L16: =(1/'IRR inputs & outputs'!$B$8)*$B$3*'IRR inputs & outputs'!$B$9+'IRR inputs & outputs'!$B$10 -> 6207.6126
A17: Software - fixed | C17: ='IRR inputs & outputs'!$B$12 -> 300 | D17: ='IRR inputs & outputs'!$B$12 -> 300 | E17: ='IRR inputs & outputs'!$B$12 -> 300 | F17: ='IRR inputs & outputs'!$B$12 -> 300 | G17: ='IRR inputs & outputs'!$B$12 -> 300 | H17: ='IRR inputs & outputs'!$B$12 -> 300 | I17: ='IRR inputs & outputs'!$B$12 -> 300 | J17: ='IRR inputs & outputs'!$B$12 -> 300 | ... L17: ='IRR inputs & outputs'!$B$12 -> 300
A18: Software - variable | C18: =$B$3*'IRR inputs & outputs'!$B$11*'IRR inputs & outputs'!$B$13 -> 995.1579 | D18: =$B$3*'IRR inputs & outputs'!$B$11*'IRR inputs & outputs'!$B$13 -> 995.1579 | E18: =$B$3*'IRR inputs & outputs'!$B$11*'IRR inputs & outputs'!$B$13 -> 995.1579 | F18: =$B$3*'IRR inputs & outputs'!$B$11*'IRR inputs & outputs'!$B$13 -> 995.1579 | G18: =$B$3*'IRR inputs & outputs'!$B$11*'IRR inputs & outputs'!$B$13 -> 995.1579 | H18: =$B$3*'IRR inputs & outputs'!$B$11*'IRR inputs & outputs'!$B$13 -> 995.1579 | I18: =$B$3*'IRR inputs & outputs'!$B$11*'IRR inputs & outputs'!$B$13 -> 995.1579 | J18: =$B$3*'IRR inputs & outputs'!$B$11*'IRR inputs & outputs'!$B$13 -> 995.1579 | ... L18: =$B$3*'IRR inputs & outputs'!$B$11*'IRR inputs & outputs'!$B$13 -> 995.1579
A19: Total outgoings | B19: =SUM(B12:B18) -> 500 | C19: =SUM(C12:C18) -> 8752.7705 | D19: =SUM(D12:D18) -> 8752.7705 | E19: =SUM(E12:E18) -> 8752.7705 | F19: =SUM(F12:F18) -> 8752.7705 | G19: =SUM(G12:G18) -> 11752.771 | H19: =SUM(H12:H18) -> 8752.7705 | I19: =SUM(I12:I18) -> 8752.7705 | ... L19: =SUM(L12:L18) -> 8752.7705
A21: Total | B21: =B9-B19 -> -500 | C21: =C9-C19 -> 4516.0015 | D21: =D9-D19 -> 4516.0015 | E21: =E9-E19 -> 4516.0015 | F21: =F9-F19 -> 4516.0015 | G21: =G9-G19 -> 1516.0015 | H21: =H9-H19 -> 4516.0015 | I21: =I9-I19 -> 4516.0015 | ... L21: =L9-L19 -> 4516.0015
A23: IRR | B23: =IFERROR(IRR(B21:L21),NA()) -> 9.0314695
A25: Subsidy effect
A26: Subsidy | B26: 0.1
A27: Subsidised capex | B27: =$B$12*(1-B26) -> 0
A28: Cashflow | B28: =-B27 -> 0 | C28: =$C$21 -> 4516.0015 | D28: =$D$21 -> 4516.0015 | E28: =$E$21 -> 4516.0015 | F28: =$F$21 -> 4516.0015 | G28: =$G$21 -> 1516.0015 | H28: =$H$21 -> 4516.0015 | I28: =$I$21 -> 4516.0015 | J28: =$J$21 -> 4516.0015 | K28: =$K$21 -> 4516.0015 | L28: =$L$21 -> 4516.0015
A29: IRR | B29: =IFERROR(IRR(B28:L28),NA()) -> #N/A
A31: Subsidy | B31: 0.15
A32: Subsidised capex | B32: =$B$12*(1-B31) -> 0
A33: Cashflow | B33: =-B32 -> 0 | C33: =$C$21 -> 4516.0015 | D33: =$D$21 -> 4516.0015 | E33: =$E$21 -> 4516.0015 | F33: =$F$21 -> 4516.0015 | G33: =$G$21 -> 1516.0015 | H33: =$H$21 -> 4516.0015 | I33: =$I$21 -> 4516.0015 | J33: =$J$21 -> 4516.0015 | K33: =$K$21 -> 4516.0015 | L33: =$L$21 -> 4516.0015
A34: IRR | B34: =IFERROR(IRR(B33:L33),NA()) -> #N/A
A36: Subsidy | B36: 0.2
A37: Subsidised capex | B37: =$B$12*(1-B36) -> 0
A38: Cashflow | B38: =-B37 -> 0 | C38: =$C$21 -> 4516.0015 | D38: =$D$21 -> 4516.0015 | E38: =$E$21 -> 4516.0015 | F38: =$F$21 -> 4516.0015 | G38: =$G$21 -> 1516.0015 | H38: =$H$21 -> 4516.0015 | I38: =$I$21 -> 4516.0015 | J38: =$J$21 -> 4516.0015 | K38: =$K$21 -> 4516.0015 | L38: =$L$21 -> 4516.0015
A39: IRR | B39: =IFERROR(IRR(B38:L38),NA()) -> #N/A
A41: Subsidy | B41: 0.25
A42: Subsidised capex | B42: =$B$12*(1-B41) -> 0
A43: Cashflow | B43: =-B42 -> 0 | C43: =$C$21 -> 4516.0015 | D43: =$D$21 -> 4516.0015 | E43: =$E$21 -> 4516.0015 | F43: =$F$21 -> 4516.0015 | G43: =$G$21 -> 1516.0015 | H43: =$H$21 -> 4516.0015 | I43: =$I$21 -> 4516.0015 | J43: =$J$21 -> 4516.0015 | K43: =$K$21 -> 4516.0015 | L43: =$L$21 -> 4516.0015
A44: IRR | B44: =IFERROR(IRR(B43:L43),NA()) -> #N/A
A46: Subsidy | B46: 0.3
A47: Subsidised capex | B47: =$B$12*(1-B46) -> 0
A48: Cashflow | B48: =-B47 -> 0 | C48: =$C$21 -> 4516.0015 | D48: =$D$21 -> 4516.0015 | E48: =$E$21 -> 4516.0015 | F48: =$F$21 -> 4516.0015 | G48: =$G$21 -> 1516.0015 | H48: =$H$21 -> 4516.0015 | I48: =$I$21 -> 4516.0015 | J48: =$J$21 -> 4516.0015 | K48: =$K$21 -> 4516.0015 | L48: =$L$21 -> 4516.0015
A49: IRR | B49: =IFERROR(IRR(B48:L48),NA()) -> #N/A
A51: Subsidy | B51: 0.35
A52: Subsidised capex | B52: =$B$12*(1-B51) -> 0
A53: Cashflow | B53: =-B52 -> 0 | C53: =$C$21 -> 4516.0015 | D53: =$D$21 -> 4516.0015 | E53: =$E$21 -> 4516.0015 | F53: =$F$21 -> 4516.0015 | G53: =$G$21 -> 1516.0015 | H53: =$H$21 -> 4516.0015 | I53: =$I$21 -> 4516.0015 | J53: =$J$21 -> 4516.0015 | K53: =$K$21 -> 4516.0015 | L53: =$L$21 -> 4516.0015
A54: IRR | B54: =IFERROR(IRR(B53:L53),NA()) -> #N/A
A56: Subsidy | B56: 0.4
A57: Subsidised capex | B57: =$B$12*(1-B56) -> 0
A58: Cashflow | B58: =-B57 -> 0 | C58: =$C$21 -> 4516.0015 | D58: =$D$21 -> 4516.0015 | E58: =$E$21 -> 4516.0015 | F58: =$F$21 -> 4516.0015 | G58: =$G$21 -> 1516.0015 | H58: =$H$21 -> 4516.0015 | I58: =$I$21 -> 4516.0015 | J58: =$J$21 -> 4516.0015 | K58: =$K$21 -> 4516.0015 | L58: =$L$21 -> 4516.0015
A59: IRR | B59: =IFERROR(IRR(B58:L58),NA()) -> #N/A
A61: Subsidy | B61: 0.45
A62: Subsidised capex | B62: =$B$12*(1-B61) -> 0
A63: Cashflow | B63: =-B62 -> 0 | C63: =$C$21 -> 4516.0015 | D63: =$D$21 -> 4516.0015 | E63: =$E$21 -> 4516.0015 | F63: =$F$21 -> 4516.0015 | G63: =$G$21 -> 1516.0015 | H63: =$H$21 -> 4516.0015 | I63: =$I$21 -> 4516.0015 | J63: =$J$21 -> 4516.0015 | K63: =$K$21 -> 4516.0015 | L63: =$L$21 -> 4516.0015
A64: IRR | B64: =IFERROR(IRR(B63:L63),NA()) -> #N/A
A66: Subsidy | B66: 0.5
A67: Subsidised capex | B67: =$B$12*(1-B66) -> 0
A68: Cashflow | B68: =-B67 -> 0 | C68: =$C$21 -> 4516.0015 | D68: =$D$21 -> 4516.0015 | E68: =$E$21 -> 4516.0015 | F68: =$F$21 -> 4516.0015 | G68: =$G$21 -> 1516.0015 | H68: =$H$21 -> 4516.0015 | I68: =$I$21 -> 4516.0015 | J68: =$J$21 -> 4516.0015 | K68: =$K$21 -> 4516.0015 | L68: =$L$21 -> 4516.0015
A69: IRR | B69: =IFERROR(IRR(B68:L68),NA()) -> #N/A
A71: Subsidy | B71: 0.55
A72: Subsidised capex | B72: =$B$12*(1-B71) -> 0
A73: Cashflow | B73: =-B72 -> 0 | C73: =$C$21 -> 4516.0015 | D73: =$D$21 -> 4516.0015 | E73: =$E$21 -> 4516.0015 | F73: =$F$21 -> 4516.0015 | G73: =$G$21 -> 1516.0015 | H73: =$H$21 -> 4516.0015 | I73: =$I$21 -> 4516.0015 | J73: =$J$21 -> 4516.0015 | K73: =$K$21 -> 4516.0015 | L73: =$L$21 -> 4516.0015
A74: IRR | B74: =IFERROR(IRR(B73:L73),NA()) -> #N/A
A76: Subsidy | B76: 0.6
A77: Subsidised capex | B77: =$B$12*(1-B76) -> 0
A78: Cashflow | B78: =-B77 -> 0 | C78: =$C$21 -> 4516.0015 | D78: =$D$21 -> 4516.0015 | E78: =$E$21 -> 4516.0015 | F78: =$F$21 -> 4516.0015 | G78: =$G$21 -> 1516.0015 | H78: =$H$21 -> 4516.0015 | I78: =$I$21 -> 4516.0015 | J78: =$J$21 -> 4516.0015 | K78: =$K$21 -> 4516.0015 | L78: =$L$21 -> 4516.0015
A79: IRR | B79: =IFERROR(IRR(B78:L78),NA()) -> #N/A
A81: Subsidy | B81: 0.65
A82: Subsidised capex | B82: =$B$12*(1-B81) -> 0
A83: Cashflow | B83: =-B82 -> 0 | C83: =$C$21 -> 4516.0015 | D83: =$D$21 -> 4516.0015 | E83: =$E$21 -> 4516.0015 | F83: =$F$21 -> 4516.0015 | G83: =$G$21 -> 1516.0015 | H83: =$H$21 -> 4516.0015 | I83: =$I$21 -> 4516.0015 | J83: =$J$21 -> 4516.0015 | K83: =$K$21 -> 4516.0015 | L83: =$L$21 -> 4516.0015
A84: IRR | B84: =IFERROR(IRR(B83:L83),NA()) -> #N/A
A86: Subsidy | B86: 0.7
A87: Subsidised capex | B87: =$B$12*(1-B86) -> 0
A88: Cashflow | B88: =-B87 -> 0 | C88: =$C$21 -> 4516.0015 | D88: =$D$21 -> 4516.0015 | E88: =$E$21 -> 4516.0015 | F88: =$F$21 -> 4516.0015 | G88: =$G$21 -> 1516.0015 | H88: =$H$21 -> 4516.0015 | I88: =$I$21 -> 4516.0015 | J88: =$J$21 -> 4516.0015 | K88: =$K$21 -> 4516.0015 | L88: =$L$21 -> 4516.0015
A89: IRR | B89: =IFERROR(IRR(B88:L88),NA()) -> #N/A
A91: Subsidy | B91: 0.75
A92: Subsidised capex | B92: =$B$12*(1-B91) -> 0
A93: Cashflow | B93: =-B92 -> 0 | C93: =$C$21 -> 4516.0015 | D93: =$D$21 -> 4516.0015 | E93: =$E$21 -> 4516.0015 | F93: =$F$21 -> 4516.0015 | G93: =$G$21 -> 1516.0015 | H93: =$H$21 -> 4516.0015 | I93: =$I$21 -> 4516.0015 | J93: =$J$21 -> 4516.0015 | K93: =$K$21 -> 4516.0015 | L93: =$L$21 -> 4516.0015
A94: IRR | B94: =IFERROR(IRR(B93:L93),NA()) -> #N/A
A96: Subsidy | B96: 0.8
A97: Subsidised capex | B97: =$B$12*(1-B96) -> 0
A98: Cashflow | B98: =-B97 -> 0 | C98: =$C$21 -> 4516.0015 | D98: =$D$21 -> 4516.0015 | E98: =$E$21 -> 4516.0015 | F98: =$F$21 -> 4516.0015 | G98: =$G$21 -> 1516.0015 | H98: =$H$21 -> 4516.0015 | I98: =$I$21 -> 4516.0015 | J98: =$J$21 -> 4516.0015 | K98: =$K$21 -> 4516.0015 | L98: =$L$21 -> 4516.0015
A99: IRR | B99: =IFERROR(IRR(B98:L98),NA()) -> #N/A
A101: Subsidy | B101: 0.85
A102: Subsidised capex | B102: =$B$12*(1-B101) -> 0
A103: Cashflow | B103: =-B102 -> 0 | C103: =$C$21 -> 4516.0015 | D103: =$D$21 -> 4516.0015 | E103: =$E$21 -> 4516.0015 | F103: =$F$21 -> 4516.0015 | G103: =$G$21 -> 1516.0015 | H103: =$H$21 -> 4516.0015 | I103: =$I$21 -> 4516.0015 | J103: =$J$21 -> 4516.0015 | K103: =$K$21 -> 4516.0015 | L103: =$L$21 -> 4516.0015
A104: IRR | B104: =IFERROR(IRR(B103:L103),NA()) -> #N/A
A106: Subsidy | B106: 0.9
A107: Subsidised capex | B107: =$B$12*(1-B106) -> 0
A108: Cashflow | B108: =-B107 -> 0 | C108: =$C$21 -> 4516.0015 | D108: =$D$21 -> 4516.0015 | E108: =$E$21 -> 4516.0015 | F108: =$F$21 -> 4516.0015 | G108: =$G$21 -> 1516.0015 | H108: =$H$21 -> 4516.0015 | I108: =$I$21 -> 4516.0015 | J108: =$J$21 -> 4516.0015 | K108: =$K$21 -> 4516.0015 | L108: =$L$21 -> 4516.0015
A109: IRR | B109: =IFERROR(IRR(B108:L108),NA()) -> #N/A
A111: Subsidy | B111: 0.95
A112: Subsidised capex | B112: =$B$12*(1-B111) -> 0
A113: Cashflow | B113: =-B112 -> 0 | C113: =$C$21 -> 4516.0015 | D113: =$D$21 -> 4516.0015 | E113: =$E$21 -> 4516.0015 | F113: =$F$21 -> 4516.0015 | G113: =$G$21 -> 1516.0015 | H113: =$H$21 -> 4516.0015 | I113: =$I$21 -> 4516.0015 | J113: =$J$21 -> 4516.0015 | K113: =$K$21 -> 4516.0015 | L113: =$L$21 -> 4516.0015
A114: IRR | B114: =IFERROR(IRR(B113:L113),NA()) -> #N/A
A116: Subsidy | B116: 1
A117: Subsidised capex | B117: =$B$12*(1-B116) -> 0
A118: Cashflow | B118: =-B117 -> 0 | C118: =$C$21 -> 4516.0015 | D118: =$D$21 -> 4516.0015 | E118: =$E$21 -> 4516.0015 | F118: =$F$21 -> 4516.0015 | G118: =$G$21 -> 1516.0015 | H118: =$H$21 -> 4516.0015 | I118: =$I$21 -> 4516.0015 | J118: =$J$21 -> 4516.0015 | K118: =$K$21 -> 4516.0015 | L118: =$L$21 -> 4516.0015
A119: IRR | B119: =IFERROR(IRR(B118:L118),NA()) -> #N/A
A122: Subsidy summary
B123: 0.1 | C123: 0.15 | D123: 0.2 | E123: 0.25 | F123: 0.3 | G123: 0.35 | H123: 0.4 | I123: 0.45 | J123: 0.5 | K123: 0.55 | L123: 0.6 | M123: 0.65 | N123: 0.7 | O123: 0.75 | P123: 0.8 | Q123: 0.85 | R123: 0.9 | S123: 0.95 | T123: 1
B124: =B29 -> #N/A | C124: =B34 -> #N/A | D124: =B39 -> #N/A | E124: =B44 -> #N/A | F124: =B49 -> #N/A | G124: =B54 -> #N/A | H124: =B59 -> #N/A | I124: =B64 -> #N/A | J124: =B69 -> #N/A | K124: =B74 -> #N/A | L124: =B79 -> #N/A | M124: =B84 -> #N/A | N124: =B89 -> #N/A | O124: =B94 -> #N/A | P124: =B99 -> #N/A | Q124: =B104 -> #N/A | R124: =B109 -> #N/A | S124: =B114 -> #N/A | T124: =B119 -> #N/A
A125: Min subsidy for DNSP | B125: =LOOKUP('IRR inputs & outputs'!B18, B124:P124, B123:P123) -> #N/A
A126: Min subsidy for CPO | B126: =LOOKUP('IRR inputs & outputs'!B19, B124:P124, B123:P123) -> #N/A

Sheet 35% utilisation
A1: Utilisation | B1: 0.35
A2: Hours in year | B2: =24*365 -> 8760
A3: Energy delivered | B3: =B2*B1*'IRR inputs & outputs'!B2*'IRR inputs & outputs'!B3*'IRR inputs & outputs'!$B$7 -> 34400.52 | C3: kWh p.a.
A5: Year | B5: 0 | C5: 1 | D5: 2 | E5: 3 | F5: 4 | G5: 5 | H5: 6 | I5: 7 | J5: 8 | K5: 9 | L5: 10
A6: Income
A7: Charging | C7: =$B$3*'IRR inputs & outputs'!$B$13 -> 15480.234 | D7: =$B$3*'IRR inputs & outputs'!$B$13 -> 15480.234 | E7: =$B$3*'IRR inputs & outputs'!$B$13 -> 15480.234 | F7: =$B$3*'IRR inputs & outputs'!$B$13 -> 15480.234 | G7: =$B$3*'IRR inputs & outputs'!$B$13 -> 15480.234 | H7: =$B$3*'IRR inputs & outputs'!$B$13 -> 15480.234 | I7: =$B$3*'IRR inputs & outputs'!$B$13 -> 15480.234 | J7: =$B$3*'IRR inputs & outputs'!$B$13 -> 15480.234 | ... L7: =$B$3*'IRR inputs & outputs'!$B$13 -> 15480.234
A9: Total income | C9: =SUM(C7:C8) -> 15480.234 | D9: =SUM(D7:D8) -> 15480.234 | E9: =SUM(E7:E8) -> 15480.234 | F9: =SUM(F7:F8) -> 15480.234 | G9: =SUM(G7:G8) -> 15480.234 | H9: =SUM(H7:H8) -> 15480.234 | I9: =SUM(I7:I8) -> 15480.234 | J9: =SUM(J7:J8) -> 15480.234 | ... L9: =SUM(L7:L8) -> 15480.234
A11: Outgoing
A12: Capex | B12: ='IRR inputs & outputs'!B6 -> 0 | G12: ='IRR inputs & outputs'!B15 -> 3000
A13: Site establishment | B13: ='IRR inputs & outputs'!B16 -> 500
A14: Site license | C14: ='IRR inputs & outputs'!$B$17 -> 750 | D14: ='IRR inputs & outputs'!$B$17 -> 750 | E14: ='IRR inputs & outputs'!$B$17 -> 750 | F14: ='IRR inputs & outputs'!$B$17 -> 750 | G14: ='IRR inputs & outputs'!$B$17 -> 750 | H14: ='IRR inputs & outputs'!$B$17 -> 750 | I14: ='IRR inputs & outputs'!$B$17 -> 750 | J14: ='IRR inputs & outputs'!$B$17 -> 750 | ... L14: ='IRR inputs & outputs'!$B$17 -> 750
A15: Maintenance | C15: ='IRR inputs & outputs'!B14 -> 500 | D15: ='IRR inputs & outputs'!B14 -> 500 | E15: ='IRR inputs & outputs'!B14 -> 500 | F15: ='IRR inputs & outputs'!B14 -> 500 | G15: ='IRR inputs & outputs'!B14 -> 500 | H15: ='IRR inputs & outputs'!B14 -> 500 | I15: ='IRR inputs & outputs'!B14 -> 500 | J15: ='IRR inputs & outputs'!B14 -> 500 | K15: ='IRR inputs & outputs'!B14 -> 500 | L15: ='IRR inputs & outputs'!B14 -> 500
A16: Electricity | C16: =(1/'IRR inputs & outputs'!$B$8)*$B$3*'IRR inputs & outputs'!$B$9+'IRR inputs & outputs'!$B$10 -> 7242.2147 | D16: =(1/'IRR inputs & outputs'!$B$8)*$B$3*'IRR inputs & outputs'!$B$9+'IRR inputs & outputs'!$B$10 -> 7242.2147 | E16: =(1/'IRR inputs & outputs'!$B$8)*$B$3*'IRR inputs & outputs'!$B$9+'IRR inputs & outputs'!$B$10 -> 7242.2147 | F16: =(1/'IRR inputs & outputs'!$B$8)*$B$3*'IRR inputs & outputs'!$B$9+'IRR inputs & outputs'!$B$10 -> 7242.2147 | G16: =(1/'IRR inputs & outputs'!$B$8)*$B$3*'IRR inputs & outputs'!$B$9+'IRR inputs & outputs'!$B$10 -> 7242.2147 | H16: =(1/'IRR inputs & outputs'!$B$8)*$B$3*'IRR inputs & outputs'!$B$9+'IRR inputs & outputs'!$B$10 -> 7242.2147 | I16: =(1/'IRR inputs & outputs'!$B$8)*$B$3*'IRR inputs & outputs'!$B$9+'IRR inputs & outputs'!$B$10 -> 7242.2147 | J16: =(1/'IRR inputs & outputs'!$B$8)*$B$3*'IRR inputs & outputs'!$B$9+'IRR inputs & outputs'!$B$10 -> 7242.2147 | ... L16: =(1/'IRR inputs & outputs'!$B$8)*$B$3*'IRR inputs & outputs'!$B$9+'IRR inputs & outputs'!$B$10 -> 7242.2147
A17: Software - fixed | C17: ='IRR inputs & outputs'!$B$12 -> 300 | D17: ='IRR inputs & outputs'!$B$12 -> 300 | E17: ='IRR inputs & outputs'!$B$12 -> 300 | F17: ='IRR inputs & outputs'!$B$12 -> 300 | G17: ='IRR inputs & outputs'!$B$12 -> 300 | H17: ='IRR inputs & outputs'!$B$12 -> 300 | I17: ='IRR inputs & outputs'!$B$12 -> 300 | J17: ='IRR inputs & outputs'!$B$12 -> 300 | ... L17: ='IRR inputs & outputs'!$B$12 -> 300
A18: Software - variable | C18: =$B$3*'IRR inputs & outputs'!$B$11*'IRR inputs & outputs'!$B$13 -> 1161.0176 | D18: =$B$3*'IRR inputs & outputs'!$B$11*'IRR inputs & outputs'!$B$13 -> 1161.0176 | E18: =$B$3*'IRR inputs & outputs'!$B$11*'IRR inputs & outputs'!$B$13 -> 1161.0176 | F18: =$B$3*'IRR inputs & outputs'!$B$11*'IRR inputs & outputs'!$B$13 -> 1161.0176 | G18: =$B$3*'IRR inputs & outputs'!$B$11*'IRR inputs & outputs'!$B$13 -> 1161.0176 | H18: =$B$3*'IRR inputs & outputs'!$B$11*'IRR inputs & outputs'!$B$13 -> 1161.0176 | I18: =$B$3*'IRR inputs & outputs'!$B$11*'IRR inputs & outputs'!$B$13 -> 1161.0176 | J18: =$B$3*'IRR inputs & outputs'!$B$11*'IRR inputs & outputs'!$B$13 -> 1161.0176 | ... L18: =$B$3*'IRR inputs & outputs'!$B$11*'IRR inputs & outputs'!$B$13 -> 1161.0176
A19: Total outgoings | B19: =SUM(B12:B18) -> 500 | C19: =SUM(C12:C18) -> 9953.2323 | D19: =SUM(D12:D18) -> 9953.2323 | E19: =SUM(E12:E18) -> 9953.2323 | F19: =SUM(F12:F18) -> 9953.2323 | G19: =SUM(G12:G18) -> 12953.232 | H19: =SUM(H12:H18) -> 9953.2323 | I19: =SUM(I12:I18) -> 9953.2323 | ... L19: =SUM(L12:L18) -> 9953.2323
A21: Total | B21: =B9-B19 -> -500 | C21: =C9-C19 -> 5527.0017 | D21: =D9-D19 -> 5527.0017 | E21: =E9-E19 -> 5527.0017 | F21: =F9-F19 -> 5527.0017 | G21: =G9-G19 -> 2527.0017 | H21: =H9-H19 -> 5527.0017 | I21: =I9-I19 -> 5527.0017 | ... L21: =L9-L19 -> 5527.0017
A23: IRR | B23: =IFERROR(IRR(B21:L21),NA()) -> 11.053743
A25: Subsidy effect
A26: Subsidy | B26: 0.1
A27: Subsidised capex | B27: =$B$12*(1-B26) -> 0
A28: Cashflow | B28: =-B27 -> 0 | C28: =$C$21 -> 5527.0017 | D28: =$D$21 -> 5527.0017 | E28: =$E$21 -> 5527.0017 | F28: =$F$21 -> 5527.0017 | G28: =$G$21 -> 2527.0017 | H28: =$H$21 -> 5527.0017 | I28: =$I$21 -> 5527.0017 | J28: =$J$21 -> 5527.0017 | K28: =$K$21 -> 5527.0017 | L28: =$L$21 -> 5527.0017
A29: IRR | B29: =IFERROR(IRR(B28:L28),NA()) -> #N/A
A31: Subsidy | B31: 0.15
A32: Subsidised capex | B32: =$B$12*(1-B31) -> 0
A33: Cashflow | B33: =-B32 -> 0 | C33: =$C$21 -> 5527.0017 | D33: =$D$21 -> 5527.0017 | E33: =$E$21 -> 5527.0017 | F33: =$F$21 -> 5527.0017 | G33: =$G$21 -> 2527.0017 | H33: =$H$21 -> 5527.0017 | I33: =$I$21 -> 5527.0017 | J33: =$J$21 -> 5527.0017 | K33: =$K$21 -> 5527.0017 | L33: =$L$21 -> 5527.0017
A34: IRR | B34: =IFERROR(IRR(B33:L33),NA()) -> #N/A
A36: Subsidy | B36: 0.2
A37: Subsidised capex | B37: =$B$12*(1-B36) -> 0
A38: Cashflow | B38: =-B37 -> 0 | C38: =$C$21 -> 5527.0017 | D38: =$D$21 -> 5527.0017 | E38: =$E$21 -> 5527.0017 | F38: =$F$21 -> 5527.0017 | G38: =$G$21 -> 2527.0017 | H38: =$H$21 -> 5527.0017 | I38: =$I$21 -> 5527.0017 | J38: =$J$21 -> 5527.0017 | K38: =$K$21 -> 5527.0017 | L38: =$L$21 -> 5527.0017
A39: IRR | B39: =IFERROR(IRR(B38:L38),NA()) -> #N/A
A41: Subsidy | B41: 0.25
A42: Subsidised capex | B42: =$B$12*(1-B41) -> 0
A43: Cashflow | B43: =-B42 -> 0 | C43: =$C$21 -> 5527.0017 | D43: =$D$21 -> 5527.0017 | E43: =$E$21 -> 5527.0017 | F43: =$F$21 -> 5527.0017 | G43: =$G$21 -> 2527.0017 | H43: =$H$21 -> 5527.0017 | I43: =$I$21 -> 5527.0017 | J43: =$J$21 -> 5527.0017 | K43: =$K$21 -> 5527.0017 | L43: =$L$21 -> 5527.0017
A44: IRR | B44: =IFERROR(IRR(B43:L43),NA()) -> #N/A
A46: Subsidy | B46: 0.3
A47: Subsidised capex | B47: =$B$12*(1-B46) -> 0
A48: Cashflow | B48: =-B47 -> 0 | C48: =$C$21 -> 5527.0017 | D48: =$D$21 -> 5527.0017 | E48: =$E$21 -> 5527.0017 | F48: =$F$21 -> 5527.0017 | G48: =$G$21 -> 2527.0017 | H48: =$H$21 -> 5527.0017 | I48: =$I$21 -> 5527.0017 | J48: =$J$21 -> 5527.0017 | K48: =$K$21 -> 5527.0017 | L48: =$L$21 -> 5527.0017
A49: IRR | B49: =IFERROR(IRR(B48:L48),NA()) -> #N/A
A51: Subsidy | B51: 0.35
A52: Subsidised capex | B52: =$B$12*(1-B51) -> 0
A53: Cashflow | B53: =-B52 -> 0 | C53: =$C$21 -> 5527.0017 | D53: =$D$21 -> 5527.0017 | E53: =$E$21 -> 5527.0017 | F53: =$F$21 -> 5527.0017 | G53: =$G$21 -> 2527.0017 | H53: =$H$21 -> 5527.0017 | I53: =$I$21 -> 5527.0017 | J53: =$J$21 -> 5527.0017 | K53: =$K$21 -> 5527.0017 | L53: =$L$21 -> 5527.0017
A54: IRR | B54: =IFERROR(IRR(B53:L53),NA()) -> #N/A
A56: Subsidy | B56: 0.4
A57: Subsidised capex | B57: =$B$12*(1-B56) -> 0
A58: Cashflow | B58: =-B57 -> 0 | C58: =$C$21 -> 5527.0017 | D58: =$D$21 -> 5527.0017 | E58: =$E$21 -> 5527.0017 | F58: =$F$21 -> 5527.0017 | G58: =$G$21 -> 2527.0017 | H58: =$H$21 -> 5527.0017 | I58: =$I$21 -> 5527.0017 | J58: =$J$21 -> 5527.0017 | K58: =$K$21 -> 5527.0017 | L58: =$L$21 -> 5527.0017
A59: IRR | B59: =IFERROR(IRR(B58:L58),NA()) -> #N/A
A61: Subsidy | B61: 0.45
A62: Subsidised capex | B62: =$B$12*(1-B61) -> 0
A63: Cashflow | B63: =-B62 -> 0 | C63: =$C$21 -> 5527.0017 | D63: =$D$21 -> 5527.0017 | E63: =$E$21 -> 5527.0017 | F63: =$F$21 -> 5527.0017 | G63: =$G$21 -> 2527.0017 | H63: =$H$21 -> 5527.0017 | I63: =$I$21 -> 5527.0017 | J63: =$J$21 -> 5527.0017 | K63: =$K$21 -> 5527.0017 | L63: =$L$21 -> 5527.0017
A64: IRR | B64: =IFERROR(IRR(B63:L63),NA()) -> #N/A
A66: Subsidy | B66: 0.5
A67: Subsidised capex | B67: =$B$12*(1-B66) -> 0
A68: Cashflow | B68: =-B67 -> 0 | C68: =$C$21 -> 5527.0017 | D68: =$D$21 -> 5527.0017 | E68: =$E$21 -> 5527.0017 | F68: =$F$21 -> 5527.0017 | G68: =$G$21 -> 2527.0017 | H68: =$H$21 -> 5527.0017 | I68: =$I$21 -> 5527.0017 | J68: =$J$21 -> 5527.0017 | K68: =$K$21 -> 5527.0017 | L68: =$L$21 -> 5527.0017
A69: IRR | B69: =IFERROR(IRR(B68:L68),NA()) -> #N/A
A71: Subsidy | B71: 0.55
A72: Subsidised capex | B72: =$B$12*(1-B71) -> 0
A73: Cashflow | B73: =-B72 -> 0 | C73: =$C$21 -> 5527.0017 | D73: =$D$21 -> 5527.0017 | E73: =$E$21 -> 5527.0017 | F73: =$F$21 -> 5527.0017 | G73: =$G$21 -> 2527.0017 | H73: =$H$21 -> 5527.0017 | I73: =$I$21 -> 5527.0017 | J73: =$J$21 -> 5527.0017 | K73: =$K$21 -> 5527.0017 | L73: =$L$21 -> 5527.0017
A74: IRR | B74: =IFERROR(IRR(B73:L73),NA()) -> #N/A
A76: Subsidy | B76: 0.6
A77: Subsidised capex | B77: =$B$12*(1-B76) -> 0
A78: Cashflow | B78: =-B77 -> 0 | C78: =$C$21 -> 5527.0017 | D78: =$D$21 -> 5527.0017 | E78: =$E$21 -> 5527.0017 | F78: =$F$21 -> 5527.0017 | G78: =$G$21 -> 2527.0017 | H78: =$H$21 -> 5527.0017 | I78: =$I$21 -> 5527.0017 | J78: =$J$21 -> 5527.0017 | K78: =$K$21 -> 5527.0017 | L78: =$L$21 -> 5527.0017
A79: IRR | B79: =IFERROR(IRR(B78:L78),NA()) -> #N/A
A81: Subsidy | B81: 0.65
A82: Subsidised capex | B82: =$B$12*(1-B81) -> 0
A83: Cashflow | B83: =-B82 -> 0 | C83: =$C$21 -> 5527.0017 | D83: =$D$21 -> 5527.0017 | E83: =$E$21 -> 5527.0017 | F83: =$F$21 -> 5527.0017 | G83: =$G$21 -> 2527.0017 | H83: =$H$21 -> 5527.0017 | I83: =$I$21 -> 5527.0017 | J83: =$J$21 -> 5527.0017 | K83: =$K$21 -> 5527.0017 | L83: =$L$21 -> 5527.0017
A84: IRR | B84: =IFERROR(IRR(B83:L83),NA()) -> #N/A
A86: Subsidy | B86: 0.7
A87: Subsidised capex | B87: =$B$12*(1-B86) -> 0
A88: Cashflow | B88: =-B87 -> 0 | C88: =$C$21 -> 5527.0017 | D88: =$D$21 -> 5527.0017 | E88: =$E$21 -> 5527.0017 | F88: =$F$21 -> 5527.0017 | G88: =$G$21 -> 2527.0017 | H88: =$H$21 -> 5527.0017 | I88: =$I$21 -> 5527.0017 | J88: =$J$21 -> 5527.0017 | K88: =$K$21 -> 5527.0017 | L88: =$L$21 -> 5527.0017
A89: IRR | B89: =IFERROR(IRR(B88:L88),NA()) -> #N/A
A91: Subsidy | B91: 0.75
A92: Subsidised capex | B92: =$B$12*(1-B91) -> 0
A93: Cashflow | B93: =-B92 -> 0 | C93: =$C$21 -> 5527.0017 | D93: =$D$21 -> 5527.0017 | E93: =$E$21 -> 5527.0017 | F93: =$F$21 -> 5527.0017 | G93: =$G$21 -> 2527.0017 | H93: =$H$21 -> 5527.0017 | I93: =$I$21 -> 5527.0017 | J93: =$J$21 -> 5527.0017 | K93: =$K$21 -> 5527.0017 | L93: =$L$21 -> 5527.0017
A94: IRR | B94: =IFERROR(IRR(B93:L93),NA()) -> #N/A
A96: Subsidy | B96: 0.8
A97: Subsidised capex | B97: =$B$12*(1-B96) -> 0
A98: Cashflow | B98: =-B97 -> 0 | C98: =$C$21 -> 5527.0017 | D98: =$D$21 -> 5527.0017 | E98: =$E$21 -> 5527.0017 | F98: =$F$21 -> 5527.0017 | G98: =$G$21 -> 2527.0017 | H98: =$H$21 -> 5527.0017 | I98: =$I$21 -> 5527.0017 | J98: =$J$21 -> 5527.0017 | K98: =$K$21 -> 5527.0017 | L98: =$L$21 -> 5527.0017
A99: IRR | B99: =IFERROR(IRR(B98:L98),NA()) -> #N/A
A101: Subsidy | B101: 0.85
A102: Subsidised capex | B102: =$B$12*(1-B101) -> 0
A103: Cashflow | B103: =-B102 -> 0 | C103: =$C$21 -> 5527.0017 | D103: =$D$21 -> 5527.0017 | E103: =$E$21 -> 5527.0017 | F103: =$F$21 -> 5527.0017 | G103: =$G$21 -> 2527.0017 | H103: =$H$21 -> 5527.0017 | I103: =$I$21 -> 5527.0017 | J103: =$J$21 -> 5527.0017 | K103: =$K$21 -> 5527.0017 | L103: =$L$21 -> 5527.0017
A104: IRR | B104: =IFERROR(IRR(B103:L103),NA()) -> #N/A
A106: Subsidy | B106: 0.9
A107: Subsidised capex | B107: =$B$12*(1-B106) -> 0
A108: Cashflow | B108: =-B107 -> 0 | C108: =$C$21 -> 5527.0017 | D108: =$D$21 -> 5527.0017 | E108: =$E$21 -> 5527.0017 | F108: =$F$21 -> 5527.0017 | G108: =$G$21 -> 2527.0017 | H108: =$H$21 -> 5527.0017 | I108: =$I$21 -> 5527.0017 | J108: =$J$21 -> 5527.0017 | K108: =$K$21 -> 5527.0017 | L108: =$L$21 -> 5527.0017
A109: IRR | B109: =IFERROR(IRR(B108:L108),NA()) -> #N/A
A111: Subsidy | B111: 0.95
A112: Subsidised capex | B112: =$B$12*(1-B111) -> 0
A113: Cashflow | B113: =-B112 -> 0 | C113: =$C$21 -> 5527.0017 | D113: =$D$21 -> 5527.0017 | E113: =$E$21 -> 5527.0017 | F113: =$F$21 -> 5527.0017 | G113: =$G$21 -> 2527.0017 | H113: =$H$21 -> 5527.0017 | I113: =$I$21 -> 5527.0017 | J113: =$J$21 -> 5527.0017 | K113: =$K$21 -> 5527.0017 | L113: =$L$21 -> 5527.0017
A114: IRR | B114: =IFERROR(IRR(B113:L113),NA()) -> #N/A
A116: Subsidy | B116: 1
A117: Subsidised capex | B117: =$B$12*(1-B116) -> 0
A118: Cashflow | B118: =-B117 -> 0 | C118: =$C$21 -> 5527.0017 | D118: =$D$21 -> 5527.0017 | E118: =$E$21 -> 5527.0017 | F118: =$F$21 -> 5527.0017 | G118: =$G$21 -> 2527.0017 | H118: =$H$21 -> 5527.0017 | I118: =$I$21 -> 5527.0017 | J118: =$J$21 -> 5527.0017 | K118: =$K$21 -> 5527.0017 | L118: =$L$21 -> 5527.0017
A119: IRR | B119: =IFERROR(IRR(B118:L118),NA()) -> #N/A
A122: Subsidy summary
B123: 0.1 | C123: 0.15 | D123: 0.2 | E123: 0.25 | F123: 0.3 | G123: 0.35 | H123: 0.4 | I123: 0.45 | J123: 0.5 | K123: 0.55 | L123: 0.6 | M123: 0.65 | N123: 0.7 | O123: 0.75 | P123: 0.8 | Q123: 0.85 | R123: 0.9 | S123: 0.95 | T123: 1
B124: =B29 -> #N/A | C124: =B34 -> #N/A | D124: =B39 -> #N/A | E124: =B44 -> #N/A | F124: =B49 -> #N/A | G124: =B54 -> #N/A | H124: =B59 -> #N/A | I124: =B64 -> #N/A | J124: =B69 -> #N/A | K124: =B74 -> #N/A | L124: =B79 -> #N/A | M124: =B84 -> #N/A | N124: =B89 -> #N/A | O124: =B94 -> #N/A | P124: =B99 -> #N/A | Q124: =B104 -> #N/A | R124: =B109 -> #N/A | S124: =B114 -> #N/A | T124: =B119 -> #N/A
A125: Min subsidy for DNSP | B125: =LOOKUP('IRR inputs & outputs'!B18, B124:P124, B123:P123) -> #N/A
A126: Min subsidy for CPO | B126: =LOOKUP('IRR inputs & outputs'!B19, B124:P124, B123:P123) -> #N/A

Sheet 40% utilisation
A1: Utilisation | B1: 0.4
A2: Hours in year | B2: =24*365 -> 8760
A3: Energy delivered | B3: =B2*B1*'IRR inputs & outputs'!B2*'IRR inputs & outputs'!B3*'IRR inputs & outputs'!$B$7 -> 39314.88 | C3: kWh p.a.
A5: Year | B5: 0 | C5: 1 | D5: 2 | E5: 3 | F5: 4 | G5: 5 | H5: 6 | I5: 7 | J5: 8 | K5: 9 | L5: 10
A6: Income
A7: Charging | C7: =$B$3*'IRR inputs & outputs'!$B$13 -> 17691.696 | D7: =$B$3*'IRR inputs & outputs'!$B$13 -> 17691.696 | E7: =$B$3*'IRR inputs & outputs'!$B$13 -> 17691.696 | F7: =$B$3*'IRR inputs & outputs'!$B$13 -> 17691.696 | G7: =$B$3*'IRR inputs & outputs'!$B$13 -> 17691.696 | H7: =$B$3*'IRR inputs & outputs'!$B$13 -> 17691.696 | I7: =$B$3*'IRR inputs & outputs'!$B$13 -> 17691.696 | J7: =$B$3*'IRR inputs & outputs'!$B$13 -> 17691.696 | ... L7: =$B$3*'IRR inputs & outputs'!$B$13 -> 17691.696
A9: Total income | C9: =SUM(C7:C8) -> 17691.696 | D9: =SUM(D7:D8) -> 17691.696 | E9: =SUM(E7:E8) -> 17691.696 | F9: =SUM(F7:F8) -> 17691.696 | G9: =SUM(G7:G8) -> 17691.696 | H9: =SUM(H7:H8) -> 17691.696 | I9: =SUM(I7:I8) -> 17691.696 | J9: =SUM(J7:J8) -> 17691.696 | ... L9: =SUM(L7:L8) -> 17691.696
A11: Outgoing
A12: Capex | B12: ='IRR inputs & outputs'!B6 -> 0 | G12: ='IRR inputs & outputs'!B15 -> 3000
A13: Site establishment | B13: ='IRR inputs & outputs'!B16 -> 500
A14: Site license | C14: ='IRR inputs & outputs'!$B$17 -> 750 | D14: ='IRR inputs & outputs'!$B$17 -> 750 | E14: ='IRR inputs & outputs'!$B$17 -> 750 | F14: ='IRR inputs & outputs'!$B$17 -> 750 | G14: ='IRR inputs & outputs'!$B$17 -> 750 | H14: ='IRR inputs & outputs'!$B$17 -> 750 | I14: ='IRR inputs & outputs'!$B$17 -> 750 | J14: ='IRR inputs & outputs'!$B$17 -> 750 | ... L14: ='IRR inputs & outputs'!$B$17 -> 750
A15: Maintenance | C15: ='IRR inputs & outputs'!B14 -> 500 | D15: ='IRR inputs & outputs'!B14 -> 500 | E15: ='IRR inputs & outputs'!B14 -> 500 | F15: ='IRR inputs & outputs'!B14 -> 500 | G15: ='IRR inputs & outputs'!B14 -> 500 | H15: ='IRR inputs & outputs'!B14 -> 500 | I15: ='IRR inputs & outputs'!B14 -> 500 | J15: ='IRR inputs & outputs'!B14 -> 500 | K15: ='IRR inputs & outputs'!B14 -> 500 | L15: ='IRR inputs & outputs'!B14 -> 500
A16: Electricity | C16: =(1/'IRR inputs & outputs'!$B$8)*$B$3*'IRR inputs & outputs'!$B$9+'IRR inputs & outputs'!$B$10 -> 8276.8168 | D16: =(1/'IRR inputs & outputs'!$B$8)*$B$3*'IRR inputs & outputs'!$B$9+'IRR inputs & outputs'!$B$10 -> 8276.8168 | E16: =(1/'IRR inputs & outputs'!$B$8)*$B$3*'IRR inputs & outputs'!$B$9+'IRR inputs & outputs'!$B$10 -> 8276.8168 | F16: =(1/'IRR inputs & outputs'!$B$8)*$B$3*'IRR inputs & outputs'!$B$9+'IRR inputs & outputs'!$B$10 -> 8276.8168 | G16: =(1/'IRR inputs & outputs'!$B$8)*$B$3*'IRR inputs & outputs'!$B$9+'IRR inputs & outputs'!$B$10 -> 8276.8168 | H16: =(1/'IRR inputs & outputs'!$B$8)*$B$3*'IRR inputs & outputs'!$B$9+'IRR inputs & outputs'!$B$10 -> 8276.8168 | I16: =(1/'IRR inputs & outputs'!$B$8)*$B$3*'IRR inputs & outputs'!$B$9+'IRR inputs & outputs'!$B$10 -> 8276.8168 | J16: =(1/'IRR inputs & outputs'!$B$8)*$B$3*'IRR inputs & outputs'!$B$9+'IRR inputs & outputs'!$B$10 -> 8276.8168 | ... L16: =(1/'IRR inputs & outputs'!$B$8)*$B$3*'IRR inputs & outputs'!$B$9+'IRR inputs & outputs'!$B$10 -> 8276.8168
A17: Software - fixed | C17: ='IRR inputs & outputs'!$B$12 -> 300 | D17: ='IRR inputs & outputs'!$B$12 -> 300 | E17: ='IRR inputs & outputs'!$B$12 -> 300 | F17: ='IRR inputs & outputs'!$B$12 -> 300 | G17: ='IRR inputs & outputs'!$B$12 -> 300 | H17: ='IRR inputs & outputs'!$B$12 -> 300 | I17: ='IRR inputs & outputs'!$B$12 -> 300 | J17: ='IRR inputs & outputs'!$B$12 -> 300 | ... L17: ='IRR inputs & outputs'!$B$12 -> 300
A18: Software - variable | C18: =$B$3*'IRR inputs & outputs'!$B$11*'IRR inputs & outputs'!$B$13 -> 1326.8772 | D18: =$B$3*'IRR inputs & outputs'!$B$11*'IRR inputs & outputs'!$B$13 -> 1326.8772 | E18: =$B$3*'IRR inputs & outputs'!$B$11*'IRR inputs & outputs'!$B$13 -> 1326.8772 | F18: =$B$3*'IRR inputs & outputs'!$B$11*'IRR inputs & outputs'!$B$13 -> 1326.8772 | G18: =$B$3*'IRR inputs & outputs'!$B$11*'IRR inputs & outputs'!$B$13 -> 1326.8772 | H18: =$B$3*'IRR inputs & outputs'!$B$11*'IRR inputs & outputs'!$B$13 -> 1326.8772 | I18: =$B$3*'IRR inputs & outputs'!$B$11*'IRR inputs & outputs'!$B$13 -> 1326.8772 | J18: =$B$3*'IRR inputs & outputs'!$B$11*'IRR inputs & outputs'!$B$13 -> 1326.8772 | ... L18: =$B$3*'IRR inputs & outputs'!$B$11*'IRR inputs & outputs'!$B$13 -> 1326.8772
A19: Total outgoings | B19: =SUM(B12:B18) -> 500 | C19: =SUM(C12:C18) -> 11153.694 | D19: =SUM(D12:D18) -> 11153.694 | E19: =SUM(E12:E18) -> 11153.694 | F19: =SUM(F12:F18) -> 11153.694 | G19: =SUM(G12:G18) -> 14153.694 | H19: =SUM(H12:H18) -> 11153.694 | I19: =SUM(I12:I18) -> 11153.694 | ... L19: =SUM(L12:L18) -> 11153.694
A21: Total | B21: =B9-B19 -> -500 | C21: =C9-C19 -> 6538.002 | D21: =D9-D19 -> 6538.002 | E21: =E9-E19 -> 6538.002 | F21: =F9-F19 -> 6538.002 | G21: =G9-G19 -> 3538.002 | H21: =H9-H19 -> 6538.002 | I21: =I9-I19 -> 6538.002 | ... L21: =L9-L19 -> 6538.002
A23: IRR | B23: =IFERROR(IRR(B21:L21),NA()) -> 13.075862
A25: Subsidy effect
A26: Subsidy | B26: 0.1
A27: Subsidised capex | B27: =$B$12*(1-B26) -> 0
A28: Cashflow | B28: =-B27 -> 0 | C28: =$C$21 -> 6538.002 | D28: =$D$21 -> 6538.002 | E28: =$E$21 -> 6538.002 | F28: =$F$21 -> 6538.002 | G28: =$G$21 -> 3538.002 | H28: =$H$21 -> 6538.002 | I28: =$I$21 -> 6538.002 | J28: =$J$21 -> 6538.002 | K28: =$K$21 -> 6538.002 | L28: =$L$21 -> 6538.002
A29: IRR | B29: =IFERROR(IRR(B28:L28),NA()) -> #N/A
A31: Subsidy | B31: 0.15
A32: Subsidised capex | B32: =$B$12*(1-B31) -> 0
A33: Cashflow | B33: =-B32 -> 0 | C33: =$C$21 -> 6538.002 | D33: =$D$21 -> 6538.002 | E33: =$E$21 -> 6538.002 | F33: =$F$21 -> 6538.002 | G33: =$G$21 -> 3538.002 | H33: =$H$21 -> 6538.002 | I33: =$I$21 -> 6538.002 | J33: =$J$21 -> 6538.002 | K33: =$K$21 -> 6538.002 | L33: =$L$21 -> 6538.002
A34: IRR | B34: =IFERROR(IRR(B33:L33),NA()) -> #N/A
A36: Subsidy | B36: 0.2
A37: Subsidised capex | B37: =$B$12*(1-B36) -> 0
A38: Cashflow | B38: =-B37 -> 0 | C38: =$C$21 -> 6538.002 | D38: =$D$21 -> 6538.002 | E38: =$E$21 -> 6538.002 | F38: =$F$21 -> 6538.002 | G38: =$G$21 -> 3538.002 | H38: =$H$21 -> 6538.002 | I38: =$I$21 -> 6538.002 | J38: =$J$21 -> 6538.002 | K38: =$K$21 -> 6538.002 | L38: =$L$21 -> 6538.002
A39: IRR | B39: =IFERROR(IRR(B38:L38),NA()) -> #N/A
A41: Subsidy | B41: 0.25
A42: Subsidised capex | B42: =$B$12*(1-B41) -> 0
A43: Cashflow | B43: =-B42 -> 0 | C43: =$C$21 -> 6538.002 | D43: =$D$21 -> 6538.002 | E43: =$E$21 -> 6538.002 | F43: =$F$21 -> 6538.002 | G43: =$G$21 -> 3538.002 | H43: =$H$21 -> 6538.002 | I43: =$I$21 -> 6538.002 | J43: =$J$21 -> 6538.002 | K43: =$K$21 -> 6538.002 | L43: =$L$21 -> 6538.002
A44: IRR | B44: =IFERROR(IRR(B43:L43),NA()) -> #N/A
A46: Subsidy | B46: 0.3
A47: Subsidised capex | B47: =$B$12*(1-B46) -> 0
A48: Cashflow | B48: =-B47 -> 0 | C48: =$C$21 -> 6538.002 | D48: =$D$21 -> 6538.002 | E48: =$E$21 -> 6538.002 | F48: =$F$21 -> 6538.002 | G48: =$G$21 -> 3538.002 | H48: =$H$21 -> 6538.002 | I48: =$I$21 -> 6538.002 | J48: =$J$21 -> 6538.002 | K48: =$K$21 -> 6538.002 | L48: =$L$21 -> 6538.002
A49: IRR | B49: =IFERROR(IRR(B48:L48),NA()) -> #N/A
A51: Subsidy | B51: 0.35
A52: Subsidised capex | B52: =$B$12*(1-B51) -> 0
A53: Cashflow | B53: =-B52 -> 0 | C53: =$C$21 -> 6538.002 | D53: =$D$21 -> 6538.002 | E53: =$E$21 -> 6538.002 | F53: =$F$21 -> 6538.002 | G53: =$G$21 -> 3538.002 | H53: =$H$21 -> 6538.002 | I53: =$I$21 -> 6538.002 | J53: =$J$21 -> 6538.002 | K53: =$K$21 -> 6538.002 | L53: =$L$21 -> 6538.002
A54: IRR | B54: =IFERROR(IRR(B53:L53),NA()) -> #N/A
A56: Subsidy | B56: 0.4
A57: Subsidised capex | B57: =$B$12*(1-B56) -> 0
A58: Cashflow | B58: =-B57 -> 0 | C58: =$C$21 -> 6538.002 | D58: =$D$21 -> 6538.002 | E58: =$E$21 -> 6538.002 | F58: =$F$21 -> 6538.002 | G58: =$G$21 -> 3538.002 | H58: =$H$21 -> 6538.002 | I58: =$I$21 -> 6538.002 | J58: =$J$21 -> 6538.002 | K58: =$K$21 -> 6538.002 | L58: =$L$21 -> 6538.002
A59: IRR | B59: =IFERROR(IRR(B58:L58),NA()) -> #N/A
A61: Subsidy | B61: 0.45
A62: Subsidised capex | B62: =$B$12*(1-B61) -> 0
A63: Cashflow | B63: =-B62 -> 0 | C63: =$C$21 -> 6538.002 | D63: =$D$21 -> 6538.002 | E63: =$E$21 -> 6538.002 | F63: =$F$21 -> 6538.002 | G63: =$G$21 -> 3538.002 | H63: =$H$21 -> 6538.002 | I63: =$I$21 -> 6538.002 | J63: =$J$21 -> 6538.002 | K63: =$K$21 -> 6538.002 | L63: =$L$21 -> 6538.002
A64: IRR | B64: =IFERROR(IRR(B63:L63),NA()) -> #N/A
A66: Subsidy | B66: 0.5
A67: Subsidised capex | B67: =$B$12*(1-B66) -> 0
A68: Cashflow | B68: =-B67 -> 0 | C68: =$C$21 -> 6538.002 | D68: =$D$21 -> 6538.002 | E68: =$E$21 -> 6538.002 | F68: =$F$21 -> 6538.002 | G68: =$G$21 -> 3538.002 | H68: =$H$21 -> 6538.002 | I68: =$I$21 -> 6538.002 | J68: =$J$21 -> 6538.002 | K68: =$K$21 -> 6538.002 | L68: =$L$21 -> 6538.002
A69: IRR | B69: =IFERROR(IRR(B68:L68),NA()) -> #N/A
A71: Subsidy | B71: 0.55
A72: Subsidised capex | B72: =$B$12*(1-B71) -> 0
A73: Cashflow | B73: =-B72 -> 0 | C73: =$C$21 -> 6538.002 | D73: =$D$21 -> 6538.002 | E73: =$E$21 -> 6538.002 | F73: =$F$21 -> 6538.002 | G73: =$G$21 -> 3538.002 | H73: =$H$21 -> 6538.002 | I73: =$I$21 -> 6538.002 | J73: =$J$21 -> 6538.002 | K73: =$K$21 -> 6538.002 | L73: =$L$21 -> 6538.002
A74: IRR | B74: =IFERROR(IRR(B73:L73),NA()) -> #N/A
A76: Subsidy | B76: 0.6
A77: Subsidised capex | B77: =$B$12*(1-B76) -> 0
A78: Cashflow | B78: =-B77 -> 0 | C78: =$C$21 -> 6538.002 | D78: =$D$21 -> 6538.002 | E78: =$E$21 -> 6538.002 | F78: =$F$21 -> 6538.002 | G78: =$G$21 -> 3538.002 | H78: =$H$21 -> 6538.002 | I78: =$I$21 -> 6538.002 | J78: =$J$21 -> 6538.002 | K78: =$K$21 -> 6538.002 | L78: =$L$21 -> 6538.002
A79: IRR | B79: =IFERROR(IRR(B78:L78),NA()) -> #N/A
A81: Subsidy | B81: 0.65
A82: Subsidised capex | B82: =$B$12*(1-B81) -> 0
A83: Cashflow | B83: =-B82 -> 0 | C83: =$C$21 -> 6538.002 | D83: =$D$21 -> 6538.002 | E83: =$E$21 -> 6538.002 | F83: =$F$21 -> 6538.002 | G83: =$G$21 -> 3538.002 | H83: =$H$21 -> 6538.002 | I83: =$I$21 -> 6538.002 | J83: =$J$21 -> 6538.002 | K83: =$K$21 -> 6538.002 | L83: =$L$21 -> 6538.002
A84: IRR | B84: =IFERROR(IRR(B83:L83),NA()) -> #N/A
A86: Subsidy | B86: 0.7
A87: Subsidised capex | B87: =$B$12*(1-B86) -> 0
A88: Cashflow | B88: =-B87 -> 0 | C88: =$C$21 -> 6538.002 | D88: =$D$21 -> 6538.002 | E88: =$E$21 -> 6538.002 | F88: =$F$21 -> 6538.002 | G88: =$G$21 -> 3538.002 | H88: =$H$21 -> 6538.002 | I88: =$I$21 -> 6538.002 | J88: =$J$21 -> 6538.002 | K88: =$K$21 -> 6538.002 | L88: =$L$21 -> 6538.002
A89: IRR | B89: =IFERROR(IRR(B88:L88),NA()) -> #N/A
A91: Subsidy | B91: 0.75
A92: Subsidised capex | B92: =$B$12*(1-B91) -> 0
A93: Cashflow | B93: =-B92 -> 0 | C93: =$C$21 -> 6538.002 | D93: =$D$21 -> 6538.002 | E93: =$E$21 -> 6538.002 | F93: =$F$21 -> 6538.002 | G93: =$G$21 -> 3538.002 | H93: =$H$21 -> 6538.002 | I93: =$I$21 -> 6538.002 | J93: =$J$21 -> 6538.002 | K93: =$K$21 -> 6538.002 | L93: =$L$21 -> 6538.002
A94: IRR | B94: =IFERROR(IRR(B93:L93),NA()) -> #N/A
A96: Subsidy | B96: 0.8
A97: Subsidised capex | B97: =$B$12*(1-B96) -> 0
A98: Cashflow | B98: =-B97 -> 0 | C98: =$C$21 -> 6538.002 | D98: =$D$21 -> 6538.002 | E98: =$E$21 -> 6538.002 | F98: =$F$21 -> 6538.002 | G98: =$G$21 -> 3538.002 | H98: =$H$21 -> 6538.002 | I98: =$I$21 -> 6538.002 | J98: =$J$21 -> 6538.002 | K98: =$K$21 -> 6538.002 | L98: =$L$21 -> 6538.002
A99: IRR | B99: =IFERROR(IRR(B98:L98),NA()) -> #N/A
A101: Subsidy | B101: 0.85
A102: Subsidised capex | B102: =$B$12*(1-B101) -> 0
A103: Cashflow | B103: =-B102 -> 0 | C103: =$C$21 -> 6538.002 | D103: =$D$21 -> 6538.002 | E103: =$E$21 -> 6538.002 | F103: =$F$21 -> 6538.002 | G103: =$G$21 -> 3538.002 | H103: =$H$21 -> 6538.002 | I103: =$I$21 -> 6538.002 | J103: =$J$21 -> 6538.002 | K103: =$K$21 -> 6538.002 | L103: =$L$21 -> 6538.002
A104: IRR | B104: =IFERROR(IRR(B103:L103),NA()) -> #N/A
A106: Subsidy | B106: 0.9
A107: Subsidised capex | B107: =$B$12*(1-B106) -> 0
A108: Cashflow | B108: =-B107 -> 0 | C108: =$C$21 -> 6538.002 | D108: =$D$21 -> 6538.002 | E108: =$E$21 -> 6538.002 | F108: =$F$21 -> 6538.002 | G108: =$G$21 -> 3538.002 | H108: =$H$21 -> 6538.002 | I108: =$I$21 -> 6538.002 | J108: =$J$21 -> 6538.002 | K108: =$K$21 -> 6538.002 | L108: =$L$21 -> 6538.002
A109: IRR | B109: =IFERROR(IRR(B108:L108),NA()) -> #N/A
A111: Subsidy | B111: 0.95
A112: Subsidised capex | B112: =$B$12*(1-B111) -> 0
A113: Cashflow | B113: =-B112 -> 0 | C113: =$C$21 -> 6538.002 | D113: =$D$21 -> 6538.002 | E113: =$E$21 -> 6538.002 | F113: =$F$21 -> 6538.002 | G113: =$G$21 -> 3538.002 | H113: =$H$21 -> 6538.002 | I113: =$I$21 -> 6538.002 | J113: =$J$21 -> 6538.002 | K113: =$K$21 -> 6538.002 | L113: =$L$21 -> 6538.002
A114: IRR | B114: =IFERROR(IRR(B113:L113),NA()) -> #N/A
A116: Subsidy | B116: 1
A117: Subsidised capex | B117: =$B$12*(1-B116) -> 0
A118: Cashflow | B118: =-B117 -> 0 | C118: =$C$21 -> 6538.002 | D118: =$D$21 -> 6538.002 | E118: =$E$21 -> 6538.002 | F118: =$F$21 -> 6538.002 | G118: =$G$21 -> 3538.002 | H118: =$H$21 -> 6538.002 | I118: =$I$21 -> 6538.002 | J118: =$J$21 -> 6538.002 | K118: =$K$21 -> 6538.002 | L118: =$L$21 -> 6538.002
A119: IRR | B119: =IFERROR(IRR(B118:L118),NA()) -> #N/A
A122: Subsidy summary
B123: 0.1 | C123: 0.15 | D123: 0.2 | E123: 0.25 | F123: 0.3 | G123: 0.35 | H123: 0.4 | I123: 0.45 | J123: 0.5 | K123: 0.55 | L123: 0.6 | M123: 0.65 | N123: 0.7 | O123: 0.75 | P123: 0.8 | Q123: 0.85 | R123: 0.9 | S123: 0.95 | T123: 1
B124: =B29 -> #N/A | C124: =B34 -> #N/A | D124: =B39 -> #N/A | E124: =B44 -> #N/A | F124: =B49 -> #N/A | G124: =B54 -> #N/A | H124: =B59 -> #N/A | I124: =B64 -> #N/A | J124: =B69 -> #N/A | K124: =B74 -> #N/A | L124: =B79 -> #N/A | M124: =B84 -> #N/A | N124: =B89 -> #N/A | O124: =B94 -> #N/A | P124: =B99 -> #N/A | Q124: =B104 -> #N/A | R124: =B109 -> #N/A | S124: =B114 -> #N/A | T124: =B119 -> #N/A
A125: Min subsidy for DNSP | B125: =LOOKUP('IRR inputs & outputs'!B18, B124:P124, B123:P123) -> #N/A
A126: Min subsidy for CPO | B126: =LOOKUP('IRR inputs & outputs'!B19, B124:P124, B123:P123) -> #N/A

Sheet 45% utilisation
A1: Utilisation | B1: 0.45
A2: Hours in year | B2: =24*365 -> 8760
A3: Energy delivered | B3: =B2*B1*'IRR inputs & outputs'!B2*'IRR inputs & outputs'!B3*'IRR inputs & outputs'!$B$7 -> 44229.24 | C3: kWh p.a.
A5: Year | B5: 0 | C5: 1 | D5: 2 | E5: 3 | F5: 4 | G5: 5 | H5: 6 | I5: 7 | J5: 8 | K5: 9 | L5: 10
A6: Income
A7: Charging | C7: =$B$3*'IRR inputs & outputs'!$B$13 -> 19903.158 | D7: =$B$3*'IRR inputs & outputs'!$B$13 -> 19903.158 | E7: =$B$3*'IRR inputs & outputs'!$B$13 -> 19903.158 | F7: =$B$3*'IRR inputs & outputs'!$B$13 -> 19903.158 | G7: =$B$3*'IRR inputs & outputs'!$B$13 -> 19903.158 | H7: =$B$3*'IRR inputs & outputs'!$B$13 -> 19903.158 | I7: =$B$3*'IRR inputs & outputs'!$B$13 -> 19903.158 | J7: =$B$3*'IRR inputs & outputs'!$B$13 -> 19903.158 | ... L7: =$B$3*'IRR inputs & outputs'!$B$13 -> 19903.158
A9: Total income | C9: =SUM(C7:C8) -> 19903.158 | D9: =SUM(D7:D8) -> 19903.158 | E9: =SUM(E7:E8) -> 19903.158 | F9: =SUM(F7:F8) -> 19903.158 | G9: =SUM(G7:G8) -> 19903.158 | H9: =SUM(H7:H8) -> 19903.158 | I9: =SUM(I7:I8) -> 19903.158 | J9: =SUM(J7:J8) -> 19903.158 | ... L9: =SUM(L7:L8) -> 19903.158
A11: Outgoing
A12: Capex | B12: ='IRR inputs & outputs'!B6 -> 0 | G12: ='IRR inputs & outputs'!B15 -> 3000
A13: Site establishment | B13: ='IRR inputs & outputs'!B16 -> 500
A14: Site license | C14: ='IRR inputs & outputs'!$B$17 -> 750 | D14: ='IRR inputs & outputs'!$B$17 -> 750 | E14: ='IRR inputs & outputs'!$B$17 -> 750 | F14: ='IRR inputs & outputs'!$B$17 -> 750 | G14: ='IRR inputs & outputs'!$B$17 -> 750 | H14: ='IRR inputs & outputs'!$B$17 -> 750 | I14: ='IRR inputs & outputs'!$B$17 -> 750 | J14: ='IRR inputs & outputs'!$B$17 -> 750 | ... L14: ='IRR inputs & outputs'!$B$17 -> 750
A15: Maintenance | C15: ='IRR inputs & outputs'!B14 -> 500 | D15: ='IRR inputs & outputs'!B14 -> 500 | E15: ='IRR inputs & outputs'!B14 -> 500 | F15: ='IRR inputs & outputs'!B14 -> 500 | G15: ='IRR inputs & outputs'!B14 -> 500 | H15: ='IRR inputs & outputs'!B14 -> 500 | I15: ='IRR inputs & outputs'!B14 -> 500 | J15: ='IRR inputs & outputs'!B14 -> 500 | K15: ='IRR inputs & outputs'!B14 -> 500 | L15: ='IRR inputs & outputs'!B14 -> 500
A16: Electricity | C16: =(1/'IRR inputs & outputs'!$B$8)*$B$3*'IRR inputs & outputs'!$B$9+'IRR inputs & outputs'!$B$10 -> 9311.4189 | D16: =(1/'IRR inputs & outputs'!$B$8)*$B$3*'IRR inputs & outputs'!$B$9+'IRR inputs & outputs'!$B$10 -> 9311.4189 | E16: =(1/'IRR inputs & outputs'!$B$8)*$B$3*'IRR inputs & outputs'!$B$9+'IRR inputs & outputs'!$B$10 -> 9311.4189 | F16: =(1/'IRR inputs & outputs'!$B$8)*$B$3*'IRR inputs & outputs'!$B$9+'IRR inputs & outputs'!$B$10 -> 9311.4189 | G16: =(1/'IRR inputs & outputs'!$B$8)*$B$3*'IRR inputs & outputs'!$B$9+'IRR inputs & outputs'!$B$10 -> 9311.4189 | H16: =(1/'IRR inputs & outputs'!$B$8)*$B$3*'IRR inputs & outputs'!$B$9+'IRR inputs & outputs'!$B$10 -> 9311.4189 | I16: =(1/'IRR inputs & outputs'!$B$8)*$B$3*'IRR inputs & outputs'!$B$9+'IRR inputs & outputs'!$B$10 -> 9311.4189 | J16: =(1/'IRR inputs & outputs'!$B$8)*$B$3*'IRR inputs & outputs'!$B$9+'IRR inputs & outputs'!$B$10 -> 9311.4189 | ... L16: =(1/'IRR inputs & outputs'!$B$8)*$B$3*'IRR inputs & outputs'!$B$9+'IRR inputs & outputs'!$B$10 -> 9311.4189
A17: Software - fixed | C17: ='IRR inputs & outputs'!$B$12 -> 300 | D17: ='IRR inputs & outputs'!$B$12 -> 300 | E17: ='IRR inputs & outputs'!$B$12 -> 300 | F17: ='IRR inputs & outputs'!$B$12 -> 300 | G17: ='IRR inputs & outputs'!$B$12 -> 300 | H17: ='IRR inputs & outputs'!$B$12 -> 300 | I17: ='IRR inputs & outputs'!$B$12 -> 300 | J17: ='IRR inputs & outputs'!$B$12 -> 300 | ... L17: ='IRR inputs & outputs'!$B$12 -> 300
A18: Software - variable | C18: =$B$3*'IRR inputs & outputs'!$B$11*'IRR inputs & outputs'!$B$13 -> 1492.7369 | D18: =$B$3*'IRR inputs & outputs'!$B$11*'IRR inputs & outputs'!$B$13 -> 1492.7369 | E18: =$B$3*'IRR inputs & outputs'!$B$11*'IRR inputs & outputs'!$B$13 -> 1492.7369 | F18: =$B$3*'IRR inputs & outputs'!$B$11*'IRR inputs & outputs'!$B$13 -> 1492.7369 | G18: =$B$3*'IRR inputs & outputs'!$B$11*'IRR inputs & outputs'!$B$13 -> 1492.7369 | H18: =$B$3*'IRR inputs & outputs'!$B$11*'IRR inputs & outputs'!$B$13 -> 1492.7369 | I18: =$B$3*'IRR inputs & outputs'!$B$11*'IRR inputs & outputs'!$B$13 -> 1492.7369 | J18: =$B$3*'IRR inputs & outputs'!$B$11*'IRR inputs & outputs'!$B$13 -> 1492.7369 | ... L18: =$B$3*'IRR inputs & outputs'!$B$11*'IRR inputs & outputs'!$B$13 -> 1492.7369
A19: Total outgoings | B19: =SUM(B12:B18) -> 500 | C19: =SUM(C12:C18) -> 12354.156 | D19: =SUM(D12:D18) -> 12354.156 | E19: =SUM(E12:E18) -> 12354.156 | F19: =SUM(F12:F18) -> 12354.156 | G19: =SUM(G12:G18) -> 15354.156 | H19: =SUM(H12:H18) -> 12354.156 | I19: =SUM(I12:I18) -> 12354.156 | ... L19: =SUM(L12:L18) -> 12354.156
A21: Total | B21: =B9-B19 -> -500 | C21: =C9-C19 -> 7549.0022 | D21: =D9-D19 -> 7549.0022 | E21: =E9-E19 -> 7549.0022 | F21: =F9-F19 -> 7549.0022 | G21: =G9-G19 -> 4549.0022 | H21: =H9-H19 -> 7549.0022 | I21: =I9-I19 -> 7549.0022 | ... L21: =L9-L19 -> 7549.0022
A23: IRR | B23: =IFERROR(IRR(B21:L21),NA()) -> 15.097921
A25: Subsidy effect
A26: Subsidy | B26: 0.1
A27: Subsidised capex | B27: =$B$12*(1-B26) -> 0
A28: Cashflow | B28: =-B27 -> 0 | C28: =$C$21 -> 7549.0022 | D28: =$D$21 -> 7549.0022 | E28: =$E$21 -> 7549.0022 | F28: =$F$21 -> 7549.0022 | G28: =$G$21 -> 4549.0022 | H28: =$H$21 -> 7549.0022 | I28: =$I$21 -> 7549.0022 | J28: =$J$21 -> 7549.0022 | K28: =$K$21 -> 7549.0022 | L28: =$L$21 -> 7549.0022
A29: IRR | B29: =IFERROR(IRR(B28:L28),NA()) -> #N/A
A31: Subsidy | B31: 0.15
A32: Subsidised capex | B32: =$B$12*(1-B31) -> 0
A33: Cashflow | B33: =-B32 -> 0 | C33: =$C$21 -> 7549.0022 | D33: =$D$21 -> 7549.0022 | E33: =$E$21 -> 7549.0022 | F33: =$F$21 -> 7549.0022 | G33: =$G$21 -> 4549.0022 | H33: =$H$21 -> 7549.0022 | I33: =$I$21 -> 7549.0022 | J33: =$J$21 -> 7549.0022 | K33: =$K$21 -> 7549.0022 | L33: =$L$21 -> 7549.0022
A34: IRR | B34: =IFERROR(IRR(B33:L33),NA()) -> #N/A
A36: Subsidy | B36: 0.2
A37: Subsidised capex | B37: =$B$12*(1-B36) -> 0
A38: Cashflow | B38: =-B37 -> 0 | C38: =$C$21 -> 7549.0022 | D38: =$D$21 -> 7549.0022 | E38: =$E$21 -> 7549.0022 | F38: =$F$21 -> 7549.0022 | G38: =$G$21 -> 4549.0022 | H38: =$H$21 -> 7549.0022 | I38: =$I$21 -> 7549.0022 | J38: =$J$21 -> 7549.0022 | K38: =$K$21 -> 7549.0022 | L38: =$L$21 -> 7549.0022
A39: IRR | B39: =IFERROR(IRR(B38:L38),NA()) -> #N/A
A41: Subsidy | B41: 0.25
A42: Subsidised capex | B42: =$B$12*(1-B41) -> 0
A43: Cashflow | B43: =-B42 -> 0 | C43: =$C$21 -> 7549.0022 | D43: =$D$21 -> 7549.0022 | E43: =$E$21 -> 7549.0022 | F43: =$F$21 -> 7549.0022 | G43: =$G$21 -> 4549.0022 | H43: =$H$21 -> 7549.0022 | I43: =$I$21 -> 7549.0022 | J43: =$J$21 -> 7549.0022 | K43: =$K$21 -> 7549.0022 | L43: =$L$21 -> 7549.0022
A44: IRR | B44: =IFERROR(IRR(B43:L43),NA()) -> #N/A
A46: Subsidy | B46: 0.3
A47: Subsidised capex | B47: =$B$12*(1-B46) -> 0
A48: Cashflow | B48: =-B47 -> 0 | C48: =$C$21 -> 7549.0022 | D48: =$D$21 -> 7549.0022 | E48: =$E$21 -> 7549.0022 | F48: =$F$21 -> 7549.0022 | G48: =$G$21 -> 4549.0022 | H48: =$H$21 -> 7549.0022 | I48: =$I$21 -> 7549.0022 | J48: =$J$21 -> 7549.0022 | K48: =$K$21 -> 7549.0022 | L48: =$L$21 -> 7549.0022
A49: IRR | B49: =IFERROR(IRR(B48:L48),NA()) -> #N/A
A51: Subsidy | B51: 0.35
A52: Subsidised capex | B52: =$B$12*(1-B51) -> 0
A53: Cashflow | B53: =-B52 -> 0 | C53: =$C$21 -> 7549.0022 | D53: =$D$21 -> 7549.0022 | E53: =$E$21 -> 7549.0022 | F53: =$F$21 -> 7549.0022 | G53: =$G$21 -> 4549.0022 | H53: =$H$21 -> 7549.0022 | I53: =$I$21 -> 7549.0022 | J53: =$J$21 -> 7549.0022 | K53: =$K$21 -> 7549.0022 | L53: =$L$21 -> 7549.0022
A54: IRR | B54: =IFERROR(IRR(B53:L53),NA()) -> #N/A
A56: Subsidy | B56: 0.4
A57: Subsidised capex | B57: =$B$12*(1-B56) -> 0
A58: Cashflow | B58: =-B57 -> 0 | C58: =$C$21 -> 7549.0022 | D58: =$D$21 -> 7549.0022 | E58: =$E$21 -> 7549.0022 | F58: =$F$21 -> 7549.0022 | G58: =$G$21 -> 4549.0022 | H58: =$H$21 -> 7549.0022 | I58: =$I$21 -> 7549.0022 | J58: =$J$21 -> 7549.0022 | K58: =$K$21 -> 7549.0022 | L58: =$L$21 -> 7549.0022
A59: IRR | B59: =IFERROR(IRR(B58:L58),NA()) -> #N/A
A61: Subsidy | B61: 0.45
A62: Subsidised capex | B62: =$B$12*(1-B61) -> 0
A63: Cashflow | B63: =-B62 -> 0 | C63: =$C$21 -> 7549.0022 | D63: =$D$21 -> 7549.0022 | E63: =$E$21 -> 7549.0022 | F63: =$F$21 -> 7549.0022 | G63: =$G$21 -> 4549.0022 | H63: =$H$21 -> 7549.0022 | I63: =$I$21 -> 7549.0022 | J63: =$J$21 -> 7549.0022 | K63: =$K$21 -> 7549.0022 | L63: =$L$21 -> 7549.0022
A64: IRR | B64: =IFERROR(IRR(B63:L63),NA()) -> #N/A
A66: Subsidy | B66: 0.5
A67: Subsidised capex | B67: =$B$12*(1-B66) -> 0
A68: Cashflow | B68: =-B67 -> 0 | C68: =$C$21 -> 7549.0022 | D68: =$D$21 -> 7549.0022 | E68: =$E$21 -> 7549.0022 | F68: =$F$21 -> 7549.0022 | G68: =$G$21 -> 4549.0022 | H68: =$H$21 -> 7549.0022 | I68: =$I$21 -> 7549.0022 | J68: =$J$21 -> 7549.0022 | K68: =$K$21 -> 7549.0022 | L68: =$L$21 -> 7549.0022
A69: IRR | B69: =IFERROR(IRR(B68:L68),NA()) -> #N/A
A71: Subsidy | B71: 0.55
A72: Subsidised capex | B72: =$B$12*(1-B71) -> 0
A73: Cashflow | B73: =-B72 -> 0 | C73: =$C$21 -> 7549.0022 | D73: =$D$21 -> 7549.0022 | E73: =$E$21 -> 7549.0022 | F73: =$F$21 -> 7549.0022 | G73: =$G$21 -> 4549.0022 | H73: =$H$21 -> 7549.0022 | I73: =$I$21 -> 7549.0022 | J73: =$J$21 -> 7549.0022 | K73: =$K$21 -> 7549.0022 | L73: =$L$21 -> 7549.0022
A74: IRR | B74: =IFERROR(IRR(B73:L73),NA()) -> #N/A
A76: Subsidy | B76: 0.6
A77: Subsidised capex | B77: =$B$12*(1-B76) -> 0
A78: Cashflow | B78: =-B77 -> 0 | C78: =$C$21 -> 7549.0022 | D78: =$D$21 -> 7549.0022 | E78: =$E$21 -> 7549.0022 | F78: =$F$21 -> 7549.0022 | G78: =$G$21 -> 4549.0022 | H78: =$H$21 -> 7549.0022 | I78: =$I$21 -> 7549.0022 | J78: =$J$21 -> 7549.0022 | K78: =$K$21 -> 7549.0022 | L78: =$L$21 -> 7549.0022
A79: IRR | B79: =IFERROR(IRR(B78:L78),NA()) -> #N/A
A81: Subsidy | B81: 0.65
A82: Subsidised capex | B82: =$B$12*(1-B81) -> 0
A83: Cashflow | B83: =-B82 -> 0 | C83: =$C$21 -> 7549.0022 | D83: =$D$21 -> 7549.0022 | E83: =$E$21 -> 7549.0022 | F83: =$F$21 -> 7549.0022 | G83: =$G$21 -> 4549.0022 | H83: =$H$21 -> 7549.0022 | I83: =$I$21 -> 7549.0022 | J83: =$J$21 -> 7549.0022 | K83: =$K$21 -> 7549.0022 | L83: =$L$21 -> 7549.0022
A84: IRR | B84: =IFERROR(IRR(B83:L83),NA()) -> #N/A
A86: Subsidy | B86: 0.7
A87: Subsidised capex | B87: =$B$12*(1-B86) -> 0
A88: Cashflow | B88: =-B87 -> 0 | C88: =$C$21 -> 7549.0022 | D88: =$D$21 -> 7549.0022 | E88: =$E$21 -> 7549.0022 | F88: =$F$21 -> 7549.0022 | G88: =$G$21 -> 4549.0022 | H88: =$H$21 -> 7549.0022 | I88: =$I$21 -> 7549.0022 | J88: =$J$21 -> 7549.0022 | K88: =$K$21 -> 7549.0022 | L88: =$L$21 -> 7549.0022
A89: IRR | B89: =IFERROR(IRR(B88:L88),NA()) -> #N/A
A91: Subsidy | B91: 0.75
A92: Subsidised capex | B92: =$B$12*(1-B91) -> 0
A93: Cashflow | B93: =-B92 -> 0 | C93: =$C$21 -> 7549.0022 | D93: =$D$21 -> 7549.0022 | E93: =$E$21 -> 7549.0022 | F93: =$F$21 -> 7549.0022 | G93: =$G$21 -> 4549.0022 | H93: =$H$21 -> 7549.0022 | I93: =$I$21 -> 7549.0022 | J93: =$J$21 -> 7549.0022 | K93: =$K$21 -> 7549.0022 | L93: =$L$21 -> 7549.0022
A94: IRR | B94: =IFERROR(IRR(B93:L93),NA()) -> #N/A
A96: Subsidy | B96: 0.8
A97: Subsidised capex | B97: =$B$12*(1-B96) -> 0
A98: Cashflow | B98: =-B97 -> 0 | C98: =$C$21 -> 7549.0022 | D98: =$D$21 -> 7549.0022 | E98: =$E$21 -> 7549.0022 | F98: =$F$21 -> 7549.0022 | G98: =$G$21 -> 4549.0022 | H98: =$H$21 -> 7549.0022 | I98: =$I$21 -> 7549.0022 | J98: =$J$21 -> 7549.0022 | K98: =$K$21 -> 7549.0022 | L98: =$L$21 -> 7549.0022
A99: IRR | B99: =IFERROR(IRR(B98:L98),NA()) -> #N/A
A101: Subsidy | B101: 0.85
A102: Subsidised capex | B102: =$B$12*(1-B101) -> 0
A103: Cashflow | B103: =-B102 -> 0 | C103: =$C$21 -> 7549.0022 | D103: =$D$21 -> 7549.0022 | E103: =$E$21 -> 7549.0022 | F103: =$F$21 -> 7549.0022 | G103: =$G$21 -> 4549.0022 | H103: =$H$21 -> 7549.0022 | I103: =$I$21 -> 7549.0022 | J103: =$J$21 -> 7549.0022 | K103: =$K$21 -> 7549.0022 | L103: =$L$21 -> 7549.0022
A104: IRR | B104: =IFERROR(IRR(B103:L103),NA()) -> #N/A
A106: Subsidy | B106: 0.9
A107: Subsidised capex | B107: =$B$12*(1-B106) -> 0
A108: Cashflow | B108: =-B107 -> 0 | C108: =$C$21 -> 7549.0022 | D108: =$D$21 -> 7549.0022 | E108: =$E$21 -> 7549.0022 | F108: =$F$21 -> 7549.0022 | G108: =$G$21 -> 4549.0022 | H108: =$H$21 -> 7549.0022 | I108: =$I$21 -> 7549.0022 | J108: =$J$21 -> 7549.0022 | K108: =$K$21 -> 7549.0022 | L108: =$L$21 -> 7549.0022
A109: IRR | B109: =IFERROR(IRR(B108:L108),NA()) -> #N/A
A111: Subsidy | B111: 0.95
A112: Subsidised capex | B112: =$B$12*(1-B111) -> 0
A113: Cashflow | B113: =-B112 -> 0 | C113: =$C$21 -> 7549.0022 | D113: =$D$21 -> 7549.0022 | E113: =$E$21 -> 7549.0022 | F113: =$F$21 -> 7549.0022 | G113: =$G$21 -> 4549.0022 | H113: =$H$21 -> 7549.0022 | I113: =$I$21 -> 7549.0022 | J113: =$J$21 -> 7549.0022 | K113: =$K$21 -> 7549.0022 | L113: =$L$21 -> 7549.0022
A114: IRR | B114: =IFERROR(IRR(B113:L113),NA()) -> #N/A
A116: Subsidy | B116: 1
A117: Subsidised capex | B117: =$B$12*(1-B116) -> 0
A118: Cashflow | B118: =-B117 -> 0 | C118: =$C$21 -> 7549.0022 | D118: =$D$21 -> 7549.0022 | E118: =$E$21 -> 7549.0022 | F118: =$F$21 -> 7549.0022 | G118: =$G$21 -> 4549.0022 | H118: =$H$21 -> 7549.0022 | I118: =$I$21 -> 7549.0022 | J118: =$J$21 -> 7549.0022 | K118: =$K$21 -> 7549.0022 | L118: =$L$21 -> 7549.0022
A119: IRR | B119: =IFERROR(IRR(B118:L118),NA()) -> #N/A
A122: Subsidy summary
B123: 0.1 | C123: 0.15 | D123: 0.2 | E123: 0.25 | F123: 0.3 | G123: 0.35 | H123: 0.4 | I123: 0.45 | J123: 0.5 | K123: 0.55 | L123: 0.6 | M123: 0.65 | N123: 0.7 | O123: 0.75 | P123: 0.8 | Q123: 0.85 | R123: 0.9 | S123: 0.95 | T123: 1
B124: =B29 -> #N/A | C124: =B34 -> #N/A | D124: =B39 -> #N/A | E124: =B44 -> #N/A | F124: =B49 -> #N/A | G124: =B54 -> #N/A | H124: =B59 -> #N/A | I124: =B64 -> #N/A | J124: =B69 -> #N/A | K124: =B74 -> #N/A | L124: =B79 -> #N/A | M124: =B84 -> #N/A | N124: =B89 -> #N/A | O124: =B94 -> #N/A | P124: =B99 -> #N/A | Q124: =B104 -> #N/A | R124: =B109 -> #N/A | S124: =B114 -> #N/A | T124: =B119 -> #N/A
A125: Min subsidy for DNSP | B125: =LOOKUP('IRR inputs & outputs'!B18, B124:P124, B123:P123) -> #N/A
A126: Min subsidy for CPO | B126: =LOOKUP('IRR inputs & outputs'!B19, B124:P124, B123:P123) -> #N/A

Sheet 50% utilisation
A1: Utilisation | B1: 0.5
A2: Hours in year | B2: =24*365 -> 8760
A3: Energy delivered | B3: =B2*B1*'IRR inputs & outputs'!B2*'IRR inputs & outputs'!B3*'IRR inputs & outputs'!$B$7 -> 49143.6 | C3: kWh p.a.
A5: Year | B5: 0 | C5: 1 | D5: 2 | E5: 3 | F5: 4 | G5: 5 | H5: 6 | I5: 7 | J5: 8 | K5: 9 | L5: 10
A6: Income
A7: Charging | C7: =$B$3*'IRR inputs & outputs'!$B$13 -> 22114.62 | D7: =$B$3*'IRR inputs & outputs'!$B$13 -> 22114.62 | E7: =$B$3*'IRR inputs & outputs'!$B$13 -> 22114.62 | F7: =$B$3*'IRR inputs & outputs'!$B$13 -> 22114.62 | G7: =$B$3*'IRR inputs & outputs'!$B$13 -> 22114.62 | H7: =$B$3*'IRR inputs & outputs'!$B$13 -> 22114.62 | I7: =$B$3*'IRR inputs & outputs'!$B$13 -> 22114.62 | J7: =$B$3*'IRR inputs & outputs'!$B$13 -> 22114.62 | ... L7: =$B$3*'IRR inputs & outputs'!$B$13 -> 22114.62
A9: Total income | C9: =SUM(C7:C8) -> 22114.62 | D9: =SUM(D7:D8) -> 22114.62 | E9: =SUM(E7:E8) -> 22114.62 | F9: =SUM(F7:F8) -> 22114.62 | G9: =SUM(G7:G8) -> 22114.62 | H9: =SUM(H7:H8) -> 22114.62 | I9: =SUM(I7:I8) -> 22114.62 | J9: =SUM(J7:J8) -> 22114.62 | ... L9: =SUM(L7:L8) -> 22114.62
A11: Outgoing
A12: Capex | B12: ='IRR inputs & outputs'!B6 -> 0 | G12: ='IRR inputs & outputs'!B15 -> 3000
A13: Site establishment | B13: ='IRR inputs & outputs'!B16 -> 500
A14: Site license | C14: ='IRR inputs & outputs'!$B$17 -> 750 | D14: ='IRR inputs & outputs'!$B$17 -> 750 | E14: ='IRR inputs & outputs'!$B$17 -> 750 | F14: ='IRR inputs & outputs'!$B$17 -> 750 | G14: ='IRR inputs & outputs'!$B$17 -> 750 | H14: ='IRR inputs & outputs'!$B$17 -> 750 | I14: ='IRR inputs & outputs'!$B$17 -> 750 | J14: ='IRR inputs & outputs'!$B$17 -> 750 | ... L14: ='IRR inputs & outputs'!$B$17 -> 750
A15: Maintenance | C15: ='IRR inputs & outputs'!B14 -> 500 | D15: ='IRR inputs & outputs'!B14 -> 500 | E15: ='IRR inputs & outputs'!B14 -> 500 | F15: ='IRR inputs & outputs'!B14 -> 500 | G15: ='IRR inputs & outputs'!B14 -> 500 | H15: ='IRR inputs & outputs'!B14 -> 500 | I15: ='IRR inputs & outputs'!B14 -> 500 | J15: ='IRR inputs & outputs'!B14 -> 500 | K15: ='IRR inputs & outputs'!B14 -> 500 | L15: ='IRR inputs & outputs'!B14 -> 500
A16: Electricity | C16: =(1/'IRR inputs & outputs'!$B$8)*$B$3*'IRR inputs & outputs'!$B$9+'IRR inputs & outputs'!$B$10 -> 10346.021 | D16: =(1/'IRR inputs & outputs'!$B$8)*$B$3*'IRR inputs & outputs'!$B$9+'IRR inputs & outputs'!$B$10 -> 10346.021 | E16: =(1/'IRR inputs & outputs'!$B$8)*$B$3*'IRR inputs & outputs'!$B$9+'IRR inputs & outputs'!$B$10 -> 10346.021 | F16: =(1/'IRR inputs & outputs'!$B$8)*$B$3*'IRR inputs & outputs'!$B$9+'IRR inputs & outputs'!$B$10 -> 10346.021 | G16: =(1/'IRR inputs & outputs'!$B$8)*$B$3*'IRR inputs & outputs'!$B$9+'IRR inputs & outputs'!$B$10 -> 10346.021 | H16: =(1/'IRR inputs & outputs'!$B$8)*$B$3*'IRR inputs & outputs'!$B$9+'IRR inputs & outputs'!$B$10 -> 10346.021 | I16: =(1/'IRR inputs & outputs'!$B$8)*$B$3*'IRR inputs & outputs'!$B$9+'IRR inputs & outputs'!$B$10 -> 10346.021 | J16: =(1/'IRR inputs & outputs'!$B$8)*$B$3*'IRR inputs & outputs'!$B$9+'IRR inputs & outputs'!$B$10 -> 10346.021 | ... L16: =(1/'IRR inputs & outputs'!$B$8)*$B$3*'IRR inputs & outputs'!$B$9+'IRR inputs & outputs'!$B$10 -> 10346.021
A17: Software - fixed | C17: ='IRR inputs & outputs'!$B$12 -> 300 | D17: ='IRR inputs & outputs'!$B$12 -> 300 | E17: ='IRR inputs & outputs'!$B$12 -> 300 | F17: ='IRR inputs & outputs'!$B$12 -> 300 | G17: ='IRR inputs & outputs'!$B$12 -> 300 | H17: ='IRR inputs & outputs'!$B$12 -> 300 | I17: ='IRR inputs & outputs'!$B$12 -> 300 | J17: ='IRR inputs & outputs'!$B$12 -> 300 | ... L17: ='IRR inputs & outputs'!$B$12 -> 300
A18: Software - variable | C18: =$B$3*'IRR inputs & outputs'!$B$11*'IRR inputs & outputs'!$B$13 -> 1658.5965 | D18: =$B$3*'IRR inputs & outputs'!$B$11*'IRR inputs & outputs'!$B$13 -> 1658.5965 | E18: =$B$3*'IRR inputs & outputs'!$B$11*'IRR inputs & outputs'!$B$13 -> 1658.5965 | F18: =$B$3*'IRR inputs & outputs'!$B$11*'IRR inputs & outputs'!$B$13 -> 1658.5965 | G18: =$B$3*'IRR inputs & outputs'!$B$11*'IRR inputs & outputs'!$B$13 -> 1658.5965 | H18: =$B$3*'IRR inputs & outputs'!$B$11*'IRR inputs & outputs'!$B$13 -> 1658.5965 | I18: =$B$3*'IRR inputs & outputs'!$B$11*'IRR inputs & outputs'!$B$13 -> 1658.5965 | J18: =$B$3*'IRR inputs & outputs'!$B$11*'IRR inputs & outputs'!$B$13 -> 1658.5965 | ... L18: =$B$3*'IRR inputs & outputs'!$B$11*'IRR inputs & outputs'!$B$13 -> 1658.5965
A19: Total outgoings | B19: =SUM(B12:B18) -> 500 | C19: =SUM(C12:C18) -> 13554.618 | D19: =SUM(D12:D18) -> 13554.618 | E19: =SUM(E12:E18) -> 13554.618 | F19: =SUM(F12:F18) -> 13554.618 | G19: =SUM(G12:G18) -> 16554.618 | H19: =SUM(H12:H18) -> 13554.618 | I19: =SUM(I12:I18) -> 13554.618 | ... L19: =SUM(L12:L18) -> 13554.618
A21: Total | B21: =B9-B19 -> -500 | C21: =C9-C19 -> 8560.0024 | D21: =D9-D19 -> 8560.0024 | E21: =E9-E19 -> 8560.0024 | F21: =F9-F19 -> 8560.0024 | G21: =G9-G19 -> 5560.0024 | H21: =H9-H19 -> 8560.0024 | I21: =I9-I19 -> 8560.0024 | ... L21: =L9-L19 -> 8560.0024
A23: IRR | B23: =IFERROR(IRR(B21:L21),NA()) -> 17.119952
A25: Subsidy effect
A26: Subsidy | B26: 0.1
A27: Subsidised capex | B27: =$B$12*(1-B26) -> 0
A28: Cashflow | B28: =-B27 -> 0 | C28: =$C$21 -> 8560.0024 | D28: =$D$21 -> 8560.0024 | E28: =$E$21 -> 8560.0024 | F28: =$F$21 -> 8560.0024 | G28: =$G$21 -> 5560.0024 | H28: =$H$21 -> 8560.0024 | I28: =$I$21 -> 8560.0024 | J28: =$J$21 -> 8560.0024 | K28: =$K$21 -> 8560.0024 | L28: =$L$21 -> 8560.0024
A29: IRR | B29: =IFERROR(IRR(B28:L28),NA()) -> #N/A
A31: Subsidy | B31: 0.15
A32: Subsidised capex | B32: =$B$12*(1-B31) -> 0
A33: Cashflow | B33: =-B32 -> 0 | C33: =$C$21 -> 8560.0024 | D33: =$D$21 -> 8560.0024 | E33: =$E$21 -> 8560.0024 | F33: =$F$21 -> 8560.0024 | G33: =$G$21 -> 5560.0024 | H33: =$H$21 -> 8560.0024 | I33: =$I$21 -> 8560.0024 | J33: =$J$21 -> 8560.0024 | K33: =$K$21 -> 8560.0024 | L33: =$L$21 -> 8560.0024
A34: IRR | B34: =IFERROR(IRR(B33:L33),NA()) -> #N/A
A36: Subsidy | B36: 0.2
A37: Subsidised capex | B37: =$B$12*(1-B36) -> 0
A38: Cashflow | B38: =-B37 -> 0 | C38: =$C$21 -> 8560.0024 | D38: =$D$21 -> 8560.0024 | E38: =$E$21 -> 8560.0024 | F38: =$F$21 -> 8560.0024 | G38: =$G$21 -> 5560.0024 | H38: =$H$21 -> 8560.0024 | I38: =$I$21 -> 8560.0024 | J38: =$J$21 -> 8560.0024 | K38: =$K$21 -> 8560.0024 | L38: =$L$21 -> 8560.0024
A39: IRR | B39: =IFERROR(IRR(B38:L38),NA()) -> #N/A
A41: Subsidy | B41: 0.25
A42: Subsidised capex | B42: =$B$12*(1-B41) -> 0
A43: Cashflow | B43: =-B42 -> 0 | C43: =$C$21 -> 8560.0024 | D43: =$D$21 -> 8560.0024 | E43: =$E$21 -> 8560.0024 | F43: =$F$21 -> 8560.0024 | G43: =$G$21 -> 5560.0024 | H43: =$H$21 -> 8560.0024 | I43: =$I$21 -> 8560.0024 | J43: =$J$21 -> 8560.0024 | K43: =$K$21 -> 8560.0024 | L43: =$L$21 -> 8560.0024
A44: IRR | B44: =IFERROR(IRR(B43:L43),NA()) -> #N/A
A46: Subsidy | B46: 0.3
A47: Subsidised capex | B47: =$B$12*(1-B46) -> 0
A48: Cashflow | B48: =-B47 -> 0 | C48: =$C$21 -> 8560.0024 | D48: =$D$21 -> 8560.0024 | E48: =$E$21 -> 8560.0024 | F48: =$F$21 -> 8560.0024 | G48: =$G$21 -> 5560.0024 | H48: =$H$21 -> 8560.0024 | I48: =$I$21 -> 8560.0024 | J48: =$J$21 -> 8560.0024 | K48: =$K$21 -> 8560.0024 | L48: =$L$21 -> 8560.0024
A49: IRR | B49: =IFERROR(IRR(B48:L48),NA()) -> #N/A
A51: Subsidy | B51: 0.35
A52: Subsidised capex | B52: =$B$12*(1-B51) -> 0
A53: Cashflow | B53: =-B52 -> 0 | C53: =$C$21 -> 8560.0024 | D53: =$D$21 -> 8560.0024 | E53: =$E$21 -> 8560.0024 | F53: =$F$21 -> 8560.0024 | G53: =$G$21 -> 5560.0024 | H53: =$H$21 -> 8560.0024 | I53: =$I$21 -> 8560.0024 | J53: =$J$21 -> 8560.0024 | K53: =$K$21 -> 8560.0024 | L53: =$L$21 -> 8560.0024
A54: IRR | B54: =IFERROR(IRR(B53:L53),NA()) -> #N/A
A56: Subsidy | B56: 0.4
A57: Subsidised capex | B57: =$B$12*(1-B56) -> 0
A58: Cashflow | B58: =-B57 -> 0 | C58: =$C$21 -> 8560.0024 | D58: =$D$21 -> 8560.0024 | E58: =$E$21 -> 8560.0024 | F58: =$F$21 -> 8560.0024 | G58: =$G$21 -> 5560.0024 | H58: =$H$21 -> 8560.0024 | I58: =$I$21 -> 8560.0024 | J58: =$J$21 -> 8560.0024 | K58: =$K$21 -> 8560.0024 | L58: =$L$21 -> 8560.0024
A59: IRR | B59: =IFERROR(IRR(B58:L58),NA()) -> #N/A
A61: Subsidy | B61: 0.45
A62: Subsidised capex | B62: =$B$12*(1-B61) -> 0
A63: Cashflow | B63: =-B62 -> 0 | C63: =$C$21 -> 8560.0024 | D63: =$D$21 -> 8560.0024 | E63: =$E$21 -> 8560.0024 | F63: =$F$21 -> 8560.0024 | G63: =$G$21 -> 5560.0024 | H63: =$H$21 -> 8560.0024 | I63: =$I$21 -> 8560.0024 | J63: =$J$21 -> 8560.0024 | K63: =$K$21 -> 8560.0024 | L63: =$L$21 -> 8560.0024
A64: IRR | B64: =IFERROR(IRR(B63:L63),NA()) -> #N/A
A66: Subsidy | B66: 0.5
A67: Subsidised capex | B67: =$B$12*(1-B66) -> 0
A68: Cashflow | B68: =-B67 -> 0 | C68: =$C$21 -> 8560.0024 | D68: =$D$21 -> 8560.0024 | E68: =$E$21 -> 8560.0024 | F68: =$F$21 -> 8560.0024 | G68: =$G$21 -> 5560.0024 | H68: =$H$21 -> 8560.0024 | I68: =$I$21 -> 8560.0024 | J68: =$J$21 -> 8560.0024 | K68: =$K$21 -> 8560.0024 | L68: =$L$21 -> 8560.0024
A69: IRR | B69: =IFERROR(IRR(B68:L68),NA()) -> #N/A
A71: Subsidy | B71: 0.55
A72: Subsidised capex | B72: =$B$12*(1-B71) -> 0
A73: Cashflow | B73: =-B72 -> 0 | C73: =$C$21 -> 8560.0024 | D73: =$D$21 -> 8560.0024 | E73: =$E$21 -> 8560.0024 | F73: =$F$21 -> 8560.0024 | G73: =$G$21 -> 5560.0024 | H73: =$H$21 -> 8560.0024 | I73: =$I$21 -> 8560.0024 | J73: =$J$21 -> 8560.0024 | K73: =$K$21 -> 8560.0024 | L73: =$L$21 -> 8560.0024
A74: IRR | B74: =IFERROR(IRR(B73:L73),NA()) -> #N/A
A76: Subsidy | B76: 0.6
A77: Subsidised capex | B77: =$B$12*(1-B76) -> 0
